Workbook
Name tbl_Application_domain: [1]TablesLookup!$A$2:$A$8
Name tbl_AppraisalArtifacts: [2]Tables!$AL$5:$AL$10
Name tbl_Business_Category: [3]TableLookup!$A$11:$A$15
Name tbl_CMMI_models: [3]TableLookup!$A$22:$A$25
Name tbl_COI: [2]Tables!$AF$5:$AF$19
Name tbl_CollectionApproach: [2]Tables!$R$5:$R$7
Name tbl_collectiontechnique: [2]Tables!$T$5:$T$11
Name tbl_constraints: [2]Tables!$AB$5:$AB$11
Name tbl_country: [2]Tables!$B$5:$B$258
Name tbl_Day_of_week: [3]TableLookup!$C$2:$D$8
Name tbl_equipment: [2]Tables!$Z$5:$Z$17
Name tbl_followon: [2]Tables!$AH$5:$AH$9
Name tbl_isic: [2]Tables!$D$5:$D$92
Name tbl_logisticalRequirement: [2]Tables!$X$5:$X$9
Name tbl_modelview: [2]Tables!$H$5:$H$9
Name tbl_PAcount: [2]Tables!$U$36:$Z$56
Name tbl_practiceCharacterization: Tables!$B$2:$B$6
Name tbl_practiceCharacterization: [4]Tables!$B$2:$B$6
Name tbl_practiceCharacterization: [4]Tables!$B$2:$B$6
Name tbl_practiceCharacterization: [4]Tables!$B$2:$B$6
Name tbl_practiceCharacterization: [4]Tables!$B$2:$B$6
Name tbl_practiceCharacterization: [4]Tables!$B$2:$B$6
Name tbl_practiceCharacterization: [4]Tables!$B$2:$B$6
Name tbl_practiceCharacterization: #REF!
Name tbl_practiceGroupRated: Tables!$B$9:$B$11
Name tbl_practiceGroupRated: [4]Tables!$B$9:$B$11
Name tbl_practiceGroupRated: [4]Tables!$B$9:$B$11
Name tbl_practiceGroupRated: [4]Tables!$B$9:$B$11
Name tbl_practiceGroupRated: [4]Tables!$B$9:$B$11
Name tbl_practiceGroupRated: [4]Tables!$B$9:$B$11
Name tbl_practiceGroupRated: [4]Tables!$B$9:$B$11
Name tbl_practiceGroupRated: #REF!
Name tbl_projectNames: '[2]Project&Support'!$A$3:$B$59
Name tbl_reportingRelationship: [2]Tables!$AJ$5:$AJ$10
Name tbl_responsibleEntity: [2]Tables!$V$5:$V$9
Name tbl_riskCategory: [2]Tables!$AD$5:$AD$11
Name tbl_RolePAlookup: [2]StaffGuide!$A$3:$V$13
Name tbl_sampling: [2]Tables!$L$5:$L$10
Name tbl_Staff: Tables!$D$16:$D$38
Name tbl_StaffRole: Tables!$H$16:$H$26
Name tbl_StaffRoleX: Tables!$E$16:$H$26
Name tbl_StaffX: Tables!$A$16:$D$37
Name tbl_target: [2]Tables!$F$5:$F$9
Name tbl_TaskCodeX: Tables!$I$16:$L$26
Name tbl_TaskStatusX: Tables!$M$16:$P$19
Name tbl_timezone: [2]Tables!$N$5:$N$143
Name tbl_WorkTaskCode: Tables!$L$16:$L$26
Name tbl_WorkTaskStatus: Tables!$P$16:$P$19

Sheet Tools
B2: https://www.whatismyip.com/
B3: https://www.microsoft.com/en-us/sql-server/sql-server-downloads
B5: Characterisation and filtering
B10: PAs: | C10: RDM, TS, PI, VV, PR, CM, EST, PLAN, MC, RSK, PCM, PAD, MPM, CAR, OT, PQA, DAR, GOV, II
D12: Summarise at levels
D14: Summarise at PA level
D16: Summarise at Process level
D18: Summarise at PA instantiation level
D21: Clear all filters
D23: Clear all Level characterisations
D25: Set levels = 's'
D27: Set levels = 'FM'
D29: Clear PAs
D31: Set PA's = 'FM'
D33: Clear instantiations
B36: NOTE: KEEP SPACE BETWEEN PA AND x.y, for example CAR 1.1 (NOT CAR1.1)
B37: https://docs.microsoft.com/en-us/sql/connect/oledb/download-oledb-driver-for-sql-server?view=sql-server-ver15
B38: https://go.microsoft.com/fwlink/?linkid=866658
B39: https://translate.google.com/?sl=auto&tl=en&op=translate
B40: https://www.onlinedoctranslator.com/en/translationform
B41: TV sheets

Sheet TV_TS
A1: TS - TECHNICAL SOLUTION (TS)
A2: Intent | E2: Design and build solutions that meet customer requirements.
A3: Value | E3: Provides a cost-effective design and solution that meets customer requirements and reduces rework.
E4: Level 1 | F4: Level 2 | I4: Level 3
E5: some measurement in place | F5: achieve full intent; use local measures to analyse performance / data stored / actions taken | I5: use organisational standards and tailoring; contribute improvements; set performance objectives; proactive not reactive
E6: TS 1.1 | F6: TS 2.1 | G6: TS 2.2 | H6: TS 2.3 | I6: TS 3.1 | J6: TS 3.2 | K6: TS 3.3 | L6: TS 3.4 | M6: TS 3.5 | N6: TS 3.6
A7: Practices | E7: Build solution to meet requirements. | F7: Design and build a solution to meet requirements. | G7: Evaluate the design and address identified issues. | H7: Provide guidance on use of the solution. | I7: Develop criteria for design decisions. | J7: Develop alternative solutions for selected components. | K7: Perform a build, buy, or reuse analysis. | L7: Select solutions based on design criteria. | M7: Develop, keep updated, and use information needed to implement the design. | N7: Design solution interfaces or connections using established criteria.
A8: Example Work Products | E8: product or service; | F8: architecture; component design (preliminary and detailed); completed solution; | G8: design evaluation issues; design review meeting minutes; updated design; updated solution; | H8: guidance material; | I8: design criteria (cost, complexity, time, technology, resources, performance, etc.) | J8: alternative solutions; | K8: build, buy or re-use analysis; | L8: recorded solutions, evaluations and rationale; | M8: technical data package requirements, design, test and traceability information; | N8: interface or connection - specification criteria (safety, security, performance etc); - design specification; - control documents; rationale for design selection;
A9: Example Activities | E9: build a solution; | F9: define the architecture; identify, develop or acquire effective design methods or tools; evaluate COTS products; develop a preliminary design; develop a detailed design; track requirements against design; build the solution; | G9: determine what types of reviews to perform; identify review participants; send draft designs to reviewers; conduct technical review; record decisions, issues and concerns; identify potential fixes; communicate issues and decisions; update the design; review the solution; revise components as necessary; | H9: develop and provide guidance material; | I9: analyse, develop, evaluate, use, update design criteria; review and revise design criteria with stakeholders; | J9: develop, identify, record alternative solutions; record requirements allocation for each alternative; communicate results; | K9: perform a build buy or re-use analysis; record analysis and communicate results; | L9: evaluate alternatives against criteria; select solutions that satisfy criteria; reassess and update criteria when necessary; develop, use and update records of evaluations; | M9: record the information needed to implement the solution; revise information as needed; | N9: define interface or connection criteria; develop design alternatives; identify internal and external interfaces or connections; identify interfaces or connections between components and related processes; identify user interfaces or connections; record, update, use, communicate the criteria, design and selection rationale;
A10: Standard Questions - explain how / what ? ... | F10: - Describe how you design and build a solution to meet the requirements? | G10: - How do you evaluate the designs and how do you address identified issues? | H10: - What guidance material do you provide on the use of the solution? | I10: - What criteria do you develop for design decisions? | J10: - What alternative solutions for selected components do you make? | K10: - How do you perform, build, buy or re-use decisions? | L10: - How do you use criteria to select your solutions? How do you select the solutions using the criteria? | M10: - What do you develop, keep updated, and use as the information needed to implement the design? | N10: How do you design solution interfaces (or connections) using established criteria?
A11: Questions | F11: 如何设计和构建能够满足需求的解决方案？ | G11: 如何评估设计并解决已识别的问题？ | H11: 提供了哪些解决方案的使用指南？ | I11: 会制定哪些设计决策标准？ | J11: 会制定哪些针对选定组件的备选解决方案？ | K11: 如何执行构建、采购或复用分析？ | L11: 如何使用设计标准选择解决方案？ | M11: 如何制定、保持更新并采用实现设计所需的信息？ | N11: 如何使用既定标准来设计解决方案的接口或连接？
A15: Name | B15: link | C15: engl | D15: \PAs | E15: TS 1.1 | F15: TS 2.1 | G15: TS 2.2 | H15: TS 2.3 | I15: TS 3.1 | J15: TS 3.2 | K15: TS 3.3 | L15: TS 3.4 | M15: TS 3.5 | N15: TS 3.6
A16: atm to complete | B16: link | C16: =HYPERLINK("02-项目级\P2-Qcubic to MySQL数据同步工具 V1.0\01-生存周期\05-设计\01-概要设计书(QCUBIC-SJTB-TS-BD)V1.0-engl.docx", "engl") -> engl | E16: x | F16: x | G16: x | I16: x | J16: x | K16: x | L16: x | M16: x | N16: x
A17: atm to complete | B17: link | C17: =HYPERLINK("02-项目级\P2-Qcubic to MySQL数据同步工具 V1.0\01-生存周期\05-设计\03-详细设计说明书(QCUBIC-SJTB-TS-DD)V1.0-engl.docx", "engl") -> engl | E17: x | F17: x | G17: x | I17: x | J17: x | K17: x | L17: x | M17: x | N17: x
A18: atm to complete | B18: link | C18: =HYPERLINK("02-项目级\P2-Qcubic to MySQL数据同步工具 V1.0\02-全程管理\05-评审管理\05-设计评审\01-概要设计说明书\05-评审报告_概要设计书(QCUBIC-SJTB-PR-ReviewRpt)V1.1-engl.xlsx", "engl") -> engl | G18: x
A19: atm to complete | B19: link | C19: =HYPERLINK("02-项目级\P2-Qcubic to MySQL数据同步工具 V1.0\02-全程管理\05-评审管理\05-设计评审\02-详细设计说明书\05-评审报告_详细设计(QCUBIC-SJTB-PR-ReviewRpt)V1.1-engl.xlsx", "engl") -> engl | G19: x
A20: atm to complete | B20: link | C20: =HYPERLINK("02-项目级\P2-Qcubic to MySQL数据同步工具 V1.0\01-生存周期\05-设计\04-用户手册(QCUBIC-SJTB-TS-Tem-UserMPMnual)V1.0-engl.docx", "engl") -> engl | H20: x
A21: atm to complete | B21: link | C21: =HYPERLINK("01-组织级\01-组织财富库\01-标准过程文件库\02-软件工程规范\03-设计\设计过程文件(QCUBIC-SPI-TS-Proc-Design)V1.2-engl.docx", "engl") -> engl | I21: x
A22: atm to complete | B22: link | C22: =HYPERLINK("02-项目级\P2-Qcubic to MySQL数据同步工具 V1.0\02-全程管理\04-决策分析\01-决策分析报告（QCUBIC-SJTB-dar-evaluaterpt)V1.0-engl.xlsx", "engl") -> engl | J22: x | L22: x
A23: atm to complete | B23: link | C23: =HYPERLINK("02-项目级\P2-Qcubic to MySQL数据同步工具 V1.0\01-生存周期\05-设计\05-购买,复用,自制评价表(QCUBIC-SJTB-TS-Purchase, reuse, self-made evaluation)V1.0-engl.xlsx", "engl") -> engl | K23: x
A24: atm to complete | B24: link | C24: =HYPERLINK("01-组织级\01-组织财富库\01-标准过程文件库\02-软件工程规范\03-设计\设计规范(QCUBIC-SPI-TS-Std-Design)V1.2-engl.docx", "engl") -> engl | N24: x
A25: atm to complete | B25: link | C25: =HYPERLINK("01-组织级\01-组织财富库\01-标准过程文件库\02-软件工程规范\03-设计\设计指南(QCUBIC-SPI-TS-Guid-Design)V1.2-engl.docx", "engl") -> engl | N25: x

Sheet TV_PI
A1: PI - PRODUCT INTEGRATION (PI)
A2: Intent | E2: Integrate and deliver the solution that addresses functionality and quality requirements.
A3: Value | E3: Increases customers' satisfaction by giving them a solution that meets or exceeds their functionality and quality requirements.
E4: Level 1 | F4: Level 2 | L4: Level 3
E5: some measurement in place | F5: achieve full intent; use local measures to analyse performance / data stored / actions taken | L5: use organisational standards and tailoring; contribute improvements; set performance objectives; proactive not reactive
E6: PI 1.1 | F6: PI 2.1 | G6: PI 2.2 | H6: PI 2.3 | I6: PI 2.4 | J6: PI 2.5 | K6: PI 2.6 | L6: PI 3.1 | M6: PI 3.2 | N6: PI 3.3
A7: Practices | E7: Assemble solutions and deliver to the customer. | F7: Develop, keep updated, and follow an integration strategy. | G7: Develop, keep updated, and use the integration environment. | H7: Develop, keep updated, and follow procedures and criteria for integrating solutions and components. | I7: Confirm, prior to integration, that each component has been properly identified and operates according to its requirements and design. | J7: Evaluate integrated components to ensure conformance to the solution's requirements and design. | K7: Integrate solutions and components according to the integration strategy. | L7: Review and keep updated interface or connection descriptions for coverage, completeness, and consistency throughout the solution's life. | M7: Confirm, prior to integration, that component interfaces or connections comply with interface or connection descriptions. | N7: Evaluate integrated components for interface or connection compatibility.
A8: Example Work Products | E8: assembled solutions and related documentation; | F8: product integration strategy (includes detail of content); recorded rationale for selection; selected integration strategy; | G8: verified and validated environment; build, buy or re-use analyses; support documentation for the environment; | H8: product integration procedures; product integration criteria; | I8: acceptance documents or test criteria for each product component; exception reports; | J8: integration evaluation reports; interface or connection evaluation reports; test reports; exception reports; | K8: integrated solution or components; exception or test report | L8: interface or connection review results; list of action items for updating interfaces or connections; updated interface or connection descriptions; | M8: results of comparison to description of component interfaces or connections; list of non-compliances; list of action items for updating descriptions; updated descriptions | N8: Interface or connection issues report;
A9: Example Activities | E9: assemble solution; record all necessary information to install and use; use applicable methods to package and deliver; deliver solution and related doc.; | F9: identify and record product components to be integrated; identify how solutions and components will be verified and validated; identify alternative integration strategies; select best alternative; periodically review strategy and revise; record and communicate decision rationale and status; | G9: develop requirements for the integration environment; develop verification and validation procedures and criteria; decide whether to build, buy or re-use the environment; develop or acquire an integration environment; verify and validate the environment; use the environment; revise as needed; communicate with stakeholders; | H9: develop, use and update procedures for integration of product components; develop, use and update criteria for integration and evaluation; record, update and communicate product integration procedures and criteria; | I9: track the integration readiness status of the components; ensure components are delivered as described in strategy and procedures; confirm each component is correctly identified and received; verify and validate each received component meets its requirements and design; check the status of the current configuration against expected; check all physical interfaces before integration; communicate results with stakeholders; | J9: evaluate integrated components, interfaces and testing using the integration strategy, procedures and criteria; record and communicate evaluation results; | K9: confirm readiness of the product integration environment; integrate components according to the strategy, procedures and criteria; update the product integration strategy, procedures and criteria as needed; integrate and deliver the product and communicate results; | L9: review with stakeholders and update interface or connection descriptions for coverage, completeness, and consistency; resolve interface or connection issues; update interface or connection descriptions and make accessible; | M9: compare interface or connection descriptions with component interfaces or connections and identify non-compliances; address non-compliances and communicate results | N9: Evaluate integrated components for compatibility; record and communicate the evaluation results;
A10: Standard Questions - explain how / what ? ... | F10: - Describe your integration strategy and how it is updated. | G10: - Describe your integration environment and how it is updated or maintained. | H10: - Describe the procedures and criteria you use to integrate components and solutions? | I10: - How do you ensure, prior to integration, that each component has been properly identified and operates according to its requirements and design? | J10: - How do you evaluate integrated components to ensure conformance to the solution's requirements and design? | K10: - Describe the integration of the components - how you follow the strategy? | L10: - How do you review and keep updated interface or connection descriptions for coverage, completeness, and consistency throughout the solution's life? | M10: - How do you confirm, prior to integration, that component interfaces or connections comply with interface or connection descriptions? | N10: - How do you evaluate integrated components for interface or connection compatibility?
A11: Questions | F11: 描述集成策略 | G11: 描述集成环境 | H11: 描述用于集成组件和解决方案的规程和准则 | I11: 在集成之前，如何确认每个组件已被正确识别、并按照其需求和设计正常工作？ | J11: 如何评价已集成的组件以确保其符合解决方案的需求和设计？ | K11: 描述下您是如何按照集成策略来集成组件的。 | L11: 在整个解决方案的生命周期中，如何评审并持续更新接口或连接描述的覆盖范围、完整性和一致性？ | M11: 在集成之前，如何确认组件的接口是符合接口描述的？ | N11: 如何评价已集成组件的接口的兼容性？
A15: Name | B15: link | C15: engl | D15: \PAs | E15: PI 1.1 | F15: PI 2.1 | G15: PI 2.2 | H15: PI 2.3 | I15: PI 2.4 | J15: PI 2.5 | K15: PI 2.6 | L15: PI 3.1 | M15: PI 3.2 | N15: PI 3.3
A16: Product Integration Plan | B16: link | C16: =HYPERLINK("02-项目级\P2-Qcubic to MySQL数据同步工具 V1.0\01-生存周期\06-实现\02-产品集成\01-产品集成计划(QCUBIC-SJTB-PI-Plan)V1.0-engl.docx", "engl") -> engl | E16: x | F16: x | G16: x | H16: x
A17: Product Integration Phase Report | B17: link | C17: =HYPERLINK("02-项目级\P2-Qcubic to MySQL数据同步工具 V1.0\01-生存周期\06-实现\02-产品集成\06-产品集成阶段报告\03-产品集成阶段报告(QCUBIC-SJTB-PI-InterimReport-3)V1.0-engl.docx", "engl") -> engl | E17: x | H17: x | J17: x | K17: x | N17: x
A18: atm to complete | B18: link | C18: =HYPERLINK("01-组织级\01-组织财富库\01-标准过程文件库\02-软件工程规范\04-实现\实现过程文件 (QCUBIC-SPI-DEV-Proc-Doc)V1.2-engl.docx", "engl") -> engl | H18: x
A19: atm to complete | B19: link | C19: =HYPERLINK("01-组织级\01-组织财富库\01-标准过程文件库\02-软件工程规范\05-测试\02-产品集成及集成测试\产品集成指南(QCUBIC-SPI-VV-Guid-PI)V1.2-engl.docx", "engl") -> engl | H19: x
A20: atm to complete | B20: link | C20: =HYPERLINK("02-项目级\P2-Qcubic to MySQL数据同步工具 V1.0\01-生存周期\06-实现\02-产品集成\03-产品集成检查列表(QCUBIC-SJTB-PI-PIChkList)V1.0-engl.xlsx", "engl") -> engl | I20: x
A21: atm to complete | B21: link | C21: =HYPERLINK("02-项目级\P2-Qcubic to MySQL数据同步工具 V1.0\01-生存周期\07-测试\02-集成测试\01-集成测试用例(QCUBIC-SJTB-VV-TestCase-SystemTest)V1.0-engl.xlsx", "engl") -> engl | J21: x
A22: atm to complete | B22: link | C22: =HYPERLINK("02-项目级\P2-Qcubic to MySQL数据同步工具 V1.0\01-生存周期\07-测试\02-集成测试\04-集成测试报告(QCUBIC-SJTB-LP_VV_IntegrationTestRet)V1.0-engl.docx", "engl") -> engl | J22: x
A23: atm to complete | B23: link | C23: =HYPERLINK("02-项目级\P2-Qcubic to MySQL数据同步工具 V1.0\01-生存周期\05-设计\01-概要设计书(QCUBIC-SJTB-TS-BD)V1.0-engl.docx", "engl") -> engl | L23: x | M23: x
A24: atm to complete | B24: link | C24: =HYPERLINK("02-项目级\P2-Qcubic to MySQL数据同步工具 V1.0\01-生存周期\05-设计\03-详细设计说明书(QCUBIC-SJTB-TS-DD)V1.0-engl.docx", "engl") -> engl | L24: x | M24: x
A25: atm to complete | B25: link | C25: =HYPERLINK("02-项目级\P2-Qcubic to MySQL数据同步工具 V1.0\01-生存周期\06-实现\02-产品集成\04-接口检查列表(QCUBIC-SJTB-PI-PIChkList)V1.0-engl.xlsx", "engl") -> engl | L25: x | M25: x | N25: x
A26: atm to complete | B26: link | C26: =HYPERLINK("02-项目级\P2-Qcubic to MySQL数据同步工具 V1.0\01-生存周期\06-实现\03-代码检查\02-代码调试BUG管理表(QCUBIC-SJTB-VV-CDBugList)V1.0-engl.xlsx", "engl") -> engl | L26: x | M26: x

Sheet TV_PR
A1: PR -PEER REVIEWS (PR)
A2: Intent | E2: Identify and address work product issues through reviews by the producer's peers or Subject Matter Experts (SMEs).
A3: Value | E3: Reduce cost and rework by uncovering issues or defects early.
E4: Level 1 | F4: Level 2 | J4: Level 3
E5: some measurement in place | F5: achieve full intent; use local measures to analyse performance / data stored / actions taken | J5: use organisational standards and tailoring; contribute improvements; set performance objectives; proactive not reactive
E6: PR 1.1 | F6: PR 2.1 | G6: PR 2.2 | H6: PR 2.3 | I6: PR 2.4 | J6: PR 3.1
A7: Practice | E7: Perform reviews of work products and record issues. | F7: Develop and keep updated procedures and supporting materials used to prepare for and perform peer reviews. | G7: Select work products to be peer reviewed. | H7: Prepare and perform peer reviews on selected work products using established procedures. | I7: Resolve issues identified in peer reviews. | J7: Analyze results and data from peer reviews.
A8: Example Work Products | E8: list of issues from work product reviews; | F8: procedures for preparing and performing peer reviews; supporting materials; | G8: work product selection criteria; list of selected work products; | H8: list of work products; schedule; peer review results; | I8: resolution of issues; results; | J8: analysis results;
A9: Example Activities | E9: review work products to identify issues; record results; | F9: record and update peer review procedures; record and update related supporting materials; | G9: evaluate the criticality of the work product; determine and record the review type to use; | H9: develop schedule; follow procedures; record results; communicate results to stakeholders; | I9: resolve issues; record resolutions and results and communicate to stakeholders; | J9: analyse the results of peer reviews; record and communicate analysis results; register improvements based on results; take corrective action on the project based on the results of the peer reviews; monitor the performance of processes for possible signals from peer review data;
A10: Standard Questions - explain how / what ? ... | F10: What procedures and supporting materials do you have in place to perform peer reviews? | G10: What work products have been selected to be reviewed? How do you select work products to be peer reviewed? | H10: Explain how you prepare for and perform peer reviews. | I10: Explain how you resolve the issues identified in the peer reviews. | J10: Explain how you analyse the results and what do you do with the analysed data from the peer reviews?
A11: Questions | F11: 准备和执行同行评审的步骤有哪些 | G11: 选择进行同行评审的工作产品有哪些？ | H11: 同行评审的既定程序（从准备阶段到结束）有哪些？请描述 | I11: 如何解决同行评审中发现的问题 | J11: 如何分析从同行评审得到的结果和数据
A15: Name | B15: link | C15: engl | D15: \PAs | E15: PR 1.1 | F15: PR 2.1 | G15: PR 2.2 | H15: PR 2.3 | I15: PR 2.4 | J15: PR 3.1
A16: atm to complete | B16: link | C16: =HYPERLINK("02-项目级\P3-主从数据库复制及性能提升项目\01-生存周期\03-项目策划\03-项目计划书 (QCUBIC-XNTS-PLAN-Plan)V1.1-engl.docx", "engl") -> engl | E16: x | H16: x
A17: atm to complete | B17: link | C17: =HYPERLINK("02-项目级\P3-主从数据库复制及性能提升项目\02-全程管理\05-评审管理\03-计划评审\05-评审报告_项目计划(QCUBIC-XNTS-PR-ReviewRpt)V1.1-engl.xlsx", "engl") -> engl | E17: x | F17: x | G17: x | H17: x | I17: x
A18: atm to complete | B18: link | C18: =HYPERLINK("02-项目级\P3-主从数据库复制及性能提升项目\02-全程管理\05-评审管理\04-需求评审\01-需求规格说明书\05-评审报告_需求规格说明书(QCUBIC-XNTS-PR-ReviewRpt)V1.1-engl.xlsx", "engl") -> engl | E18: x | G18: x | H18: x | I18: x
A19: atm to complete | B19: link | C19: =HYPERLINK("02-项目级\P3-主从数据库复制及性能提升项目\02-全程管理\05-评审管理\04-需求评审\02-用户需求说明书\03-评审报告_用户需求说明书(QCUBIC-XNTS-PR-ReviewRpt)V1.0-engl.xlsx", "engl") -> engl | E19: x | G19: x | H19: x | I19: x
A20: atm to complete | B20: link | C20: =HYPERLINK("02-项目级\P3-主从数据库复制及性能提升项目\02-全程管理\05-评审管理\05-设计评审\01-概要设计说明书\05-评审报告_概要设计书(QCUBIC-XNTS-PR-ReviewRpt)V1.1-engl.xlsx", "engl") -> engl | E20: x | G20: x | H20: x | I20: x
A21: atm to complete | B21: link | C21: =HYPERLINK("02-项目级\P3-主从数据库复制及性能提升项目\02-全程管理\05-评审管理\05-设计评审\02-详细设计说明书\05-评审报告_详细设计(QCUBIC-XNTS-PR-ReviewRpt)V1.1-engl.xlsx", "engl") -> engl | E21: x | G21: x | H21: x | I21: x
A22: atm to complete | B22: link | C22: =HYPERLINK("02-项目级\P3-主从数据库复制及性能提升项目\02-全程管理\05-评审管理\07-测试评审\02-系统测试用例\05-评审报告_系统测试用例(QCUBIC-XNTS-PR-ReviewRpt)V1.1-engl.xlsx", "engl") -> engl | E22: x | G22: x | H22: x | I22: x | J22: x
A23: atm to complete | B23: link | C23: =HYPERLINK("02-项目级\P3-主从数据库复制及性能提升项目\02-全程管理\05-评审管理\03-计划评审\01-评审准备表_项目计划(QCUBIC-XNTS-PR-ReviewPrp)V1.0-engl.docx", "engl") -> engl | F23: x
A24: atm to complete | B24: link | C24: =HYPERLINK("02-项目级\P3-主从数据库复制及性能提升项目\02-全程管理\05-评审管理\03-计划评审\02-评审检查表_项目计划(QCUBIC-XNTS-PR-RevChkList)V1.0-engl.xlsx", "engl") -> engl | F24: x
A25: atm to complete | B25: link | C25: =HYPERLINK("01-组织级\01-组织财富库\01-标准过程文件库\03-支持类\05-评审管理\评审管理过程文件(QCUBIC-SPI-VV-Proc-Doc)V1.2-engl.docx", "engl") -> engl | F25: x | H25: x
A26: atm to complete | B26: link | C26: =HYPERLINK("01-组织级\01-组织财富库\01-标准过程文件库\03-支持类\05-评审管理\评审指南(QCUBIC-SPI-VV-Guid-Review)V1.2-engl.docx", "engl") -> engl | F26: x
A27: atm to complete | B27: link | C27: =HYPERLINK("02-项目级\P3-主从数据库复制及性能提升项目\02-全程管理\05-评审管理\01-评审缺陷管理表(QCUBIC-XNTS-MC-DefectList)V1.0-engl.xlsx", "engl") -> engl | I27: x | J27: x

Sheet TV_VV
A1: VV -VERIFICATION AND VALIDATION (VV)
A2: Intent | E2: Verification and validation includes activities that: Confirm selected solutions and components meet their requirements Validate selected solutions and components fulfill their intended use in their target environment
A3: Value | E3: Verification and validation of selected solutions and components throughout the project increases the likelihood that the solution will satisfy the customer.
E4: Level 1 | G4: Level 2 | J4: Level 3
E5: some measurement in place | G5: achieve full intent; use local measures to analyse performance / data stored / actions taken | J5: use organisational standards and tailoring; contribute improvements; set performance objectives; proactive not reactive
E6: VV 1.1 | F6: VV 1.2 | G6: VV 2.1 | H6: VV 2.2 | I6: VV 2.3 | J6: VV 3.1 | K6: VV 3.2
A7: Practice | E7: Perform verification to ensure the requirements are implemented and record and communicate results. | F7: Perform validation to ensure the solution will function as intended in its target environment and record and communicate results. | G7: Select components and methods for verification and validation. | H7: Develop, keep updated, and use the environment needed to support verification and validation. | I7: Develop, keep updated, and follow procedures for verification and validation. | J7: Develop, keep updated, and use criteria for verification and validation. | K7: Analyze and communicate verification and validation results.
A8: Example Work Products | E8: verfication results; action items; | F8: validation results; analysis results; | G8: list of solution components for verification and validation; verfification and validation methods for each component; list of requirements to be verified and validated; | H8: verification environment; validation environment; | I8: verification procedures; validation procedures; verification and validation results; | J8: verification criteria; validation criteria; | K8: results of actual vs expected (test results); analysis results; corrective actions; improvement proposals;
A9: Example Activities | E9: perform verification of selected work products and solns, against requirements; record and communicate results of activities; identify action items resulting from verification; | F9: validate selected work products and solns. with stakeholders throughout life cycle to ensure they function as intended; analyse and communicate results of validation activities; | G9: select solution components for verification and validation; identify requirements to be satisfied by each; determine customer requirements and end user needs to be validated; define, record and update verification and validation methods; review validation selection, roles, responsibilities, constraints and methods with stakeholders; | H9: identify requirements for the verfification and validation environment; identify customer-supplied solutions and components; identify verification and validation resources, equipment and tools; develop or acquire and keep the verification and validation environments updated; | I9: identify criteria for selecting work products and activities for verification and validation; develop and keep updated procedures for verification and validation; perform verification and validation in accordance with procedures; | J9: develop verification and validation criteria and refine them as work progresses; | K9: compare actual to expected results; identify results that do not meet criteria for verification; identify results that do not meet criteria for validation; analyse results; submit improvement proposals where process improvements are identified; record and communicate analysis results and corrective actions to stakeholders;
A10: Standard Questions - explain how / what ? ... | G10: Explain how you select the components and the methods for verification and validation. | H10: Explain how you develop and maintain the environment needed to support verification and validation. | I10: How do you develop and maintain the procedures for verification and validation. | J10: How do you develop and maintain the criteria for verification and validation? | K10: How do you analyse and communicate the results of verification and validation?
A11: Questions | G11: 如何选择用于验证和确认的组件和方法？ | H11: 如何开发、使用并保持更新支持验证和确认所需的环境？ | I11: 这些(验证和确认的流程）是如何开发和维护的？ | J11: 这些（验证与确认的准则）是如何开发和维护的？ | K11: 如何使用和传达验证与确认的结果？
A15: Name | B15: link | C15: engl | D15: \PAs | E15: VV 1.1 | F15: VV 1.2 | G15: VV 2.1 | H15: VV 2.2 | I15: VV 2.3 | J15: VV 3.1 | K15: VV 3.2
A16: atm to complete | B16: link | C16: =HYPERLINK("02-项目级\P3-主从数据库复制及性能提升项目\01-生存周期\07-测试\01-测试计划(QCUBIC-XNTS-VV-TestPlan)V1.0-engl.docx", "engl") -> engl | E16: x | F16: x | G16: x | H16: x | I16: x | J16: x | K16: x
A17: atm to complete | B17: link | C17: =HYPERLINK("02-项目级\P3-主从数据库复制及性能提升项目\01-生存周期\07-测试\03-系统测试\03-系统测试BUG管理表(QCUBIC-XNTS-VV-STBugList)V1.0-engl.xlsx", "engl") -> engl | E17: x | F17: x | G17: x | H17: x
A18: atm to complete | B18: link | C18: =HYPERLINK("02-项目级\P3-主从数据库复制及性能提升项目\01-生存周期\07-测试\03-系统测试\04-系统测试报告(QCUBIC-XNTS-VV-TestReport-SystemTest)V1.0-engl.docx", "engl") -> engl | E18: x | G18: x | H18: x | I18: x | K18: x
A19: atm to complete | B19: link | C19: =HYPERLINK("02-项目级\P3-主从数据库复制及性能提升项目\01-生存周期\07-测试\02-集成测试\04-集成测试报告(QCUBIC-XNTS-LP_VV_IntegrationTestRet)V1.0-engl.docx", "engl") -> engl | E19: x | G19: x | H19: x | I19: x | K19: x
A20: atm to complete | B20: link | C20: =HYPERLINK("02-项目级\P3-主从数据库复制及性能提升项目\01-生存周期\08-试运行及验收\02-验收\01-验收计划(QCUBIC-XNTS-DA-AcceptencePlan)V1.0-engl.docx", "engl") -> engl | F20: x | I20: x | J20: x
A21: atm to complete | B21: link | C21: =HYPERLINK("02-项目级\P3-主从数据库复制及性能提升项目\01-生存周期\08-试运行及验收\02-验收\03-验收报告(QCUBIC-XNTS-VV-TestReport-AcceptenceReport)V1.0-engl.docx", "engl") -> engl | F21: x | I21: x | K21: x
A22: atm to complete | B22: link | C22: =HYPERLINK("01-组织级\01-组织财富库\01-标准过程文件库\02-软件工程规范\05-测试\测试用例规范(QCUBIC-SPI-VV-Tem-STD-TestExampleStd)V1.2-engl.docx", "engl") -> engl | I22: x
A23: atm to complete | B23: link | C23: =HYPERLINK("01-组织级\01-组织财富库\01-标准过程文件库\02-软件工程规范\06-试运行及验收\试运行及验收过程文件(QCUBIC-SPI-DA-Proc-Doc)V1.2-engl.docx", "engl") -> engl | I23: x
A24: atm to complete | B24: link | C24: =HYPERLINK("01-组织级\01-组织财富库\01-标准过程文件库\02-软件工程规范\05-测试\软件测试过程文件(QCUBIC-SPI-Tes-Proc-Doc)V1.2-engl.docx", "engl") -> engl | I24: x

Sheet TV_PQA
A1: PQA - PROCESS QUALITY ASSURANCE (PQA)
A2: Intent | E2: Verify and enable improvement of the quality of the performed processes and resulting work products.
A3: Value | E3: Increases the consistent use and improvement of the processes to maximize business benefit and customer satisfaction.
E4: Level 1 | F4: Level 2 | J4: Level 3
E5: some measurement in place | F5: achieve full intent; use local measures to analyse performance / data stored / actions taken | J5: use organisational standards and tailoring; contribute improvements; set performance objectives; proactive not reactive
E6: PQA 1.1 | F6: PQA 2.1 | G6: PQA 2.2 | H6: PQA 2.3 | I6: PQA 2.4 | J6: PQA 3.1
A7: Practice | E7: Identify and address process and work product issues. | F7: Develop, keep updated, and follow a quality assurance approach and plan based on historical quality data. | G7: Throughout the project, objectively evaluate selected performed processes and work products against the recorded process and applicable standards. | H7: Communicate quality and non-compliance issues and ensure their resolution. | I7: Record and use results of quality assurance activities. | J7: Identify and record opportunities for improvement during quality assurance activities.
A8: Example Work Products | E8: recorded issues; addressed issues; | F8: Quality assurance approach and plan; | G8: criteria; checklists; evaluation reports; non-compliance reports; improvement proposals; | H8: quality trend analysis reports; non-compliance resolutions; | I8: evaluation records; quality assurance reports; status reports of non-compliance issues and corrective actions; reports of quality trends; | J8: improvement proposals;
A9: Example Activities | E9: identify issues; record issues; resolve issues; | F9: develop, record and update the quality approach and plan; identify areas for evaluation; review, update and approve approach with stakeholders; | G9: develop and update clearly stated criteria for evaluations; develop and update checklists based on process descriptions; use the defined criteria and checklists to evaluate if performed processes follow process descriptions; identify and record non-compliances; leverage recorded best practices; | H9: communicate and resolve each non-compliance issue; escalate non-compliance issues that cannot be resolved; analyse to identify trends; ensure stakeholders are aware of evaluation results; | I9: record and update information about quality assurance activities; | J9: record potential improvements observed during QA activities; submit improvement proposals;
A10: Standard Questions - explain how / what ? ... | E10: *How do you identify which work products and processes you want to check for process quality assurance? | F10: *How do you develop the approach or plan for quality assurance? *What historical data do you use? | G10: *How do you evaluate compliance to the recorded processes and work products? *What do you check for? | H10: * How do you communicate and address the non-compliance issues that have been identified? | I10: *Where do you record the results of quality assurance activities? *How do you use the results? What actions follow? *Where does your function report to? *Repeat offenders? *Who has accountability for taking action on results? *Most common areas of non-compliance? | J10: *What do you do with the improvement opportunities that you identify? *Do you follow-up on the use of these opportunities identified? *Effect of non-compliance on process performance baseline? Used by MA?
A11: Questions | F11: 你是如何指定QA方法或计划的？使用到了哪些历史数据？ | G11: “*您如何评估所记录过程和工作产品的合规性? 你检查什么? | H11: “*对于已发现的不符合项问题，你们如何沟通和解决的?” | I11: *你们在哪里记录QA活动的结果? 你如何使用这些结果?遵循什么行动? *你的职能部门向哪里报告? *常出现的不符合项? 谁有责任根据结果采取行动? *最常见的违规行为? | J11: “*当你发现有改进的机会时，你会怎么做?” *你会继续利用这些发现的机会吗? *不合规对过程性能基线的影响?度量分析人员会使用这些（改进机会）嘛?
A15: Name | B15: link | C15: engl | D15: \PAs | E15: PQA 1.1 | F15: PQA 2.1 | G15: PQA 2.2 | H15: PQA 2.3 | I15: PQA 2.4 | J15: PQA 3.1
A16: atm to complete | B16: link | C16: =HYPERLINK("01-组织级\02-组织工作库\03-PQA活动库\组织级的质量保证计划(QCUBIC-SPI-PQA-OQAPlan)V1.4-engl.xlsx", "engl") -> engl | E16: x | F16: x | G16: x | H16: x | I16: x | J16: x
A17: atm to complete | B17: link | C17: =HYPERLINK("01-组织级\02-组织工作库\03-PQA活动库\组织级不符合项管理表(QCUBIC-SPI-PQA-NCList)V1.2-engl.xlsx", "engl") -> engl | E17: x | F17: x | H17: x | I17: x
A18: atm to complete | B18: link | C18: =HYPERLINK("01-组织级\02-组织工作库\03-PQA活动库\组织级工作产品和过程检查表(QCUBIC-ORG-PQA-Checklist_20200627)V1.0-engl.xlsx", "engl") -> engl | G18: x
A19: atm to complete | B19: link | C19: =HYPERLINK("01-组织级\02-组织工作库\03-PQA活动库\组织质量保证报告\质量保证报告(QCUBIC-SPI-PQA-Report_20200627)V1.0-engl.xlsx", "engl") -> engl | I19: x
A20: atm to complete | B20: link | C20: =HYPERLINK("01-组织级\02-组织工作库\02-EPG活动库\07-EPG跟踪\05-过程改进建议表\过程改进建议表(QCUBIC-SPI-PIM-SPIAdvic)V1.2-engl.xlsx", "engl") -> engl | J20: x

Sheet TV_RDM
A1: RDM - REQUIREMENTS DEVELOPMENT AND MANAGEMENT (RDM)
A2: Intent | E2: Elicit requirements, ensure common understanding by stakeholders, and align requirements, plans, and work products.
A3: Value | E3: Ensures that customer's needs and expectations are satisfied.
E4: Level 1 | F4: Level 2 | L4: Level 3
E5: some measurement in place | F5: achieve full intent; use local measures to analyse performance / data stored / actions taken | L5: use organisational standards and tailoring; contribute improvements; set performance objectives; proactive not reactive
E6: RDM 1.1 | F6: RDM 2.1 | G6: RDM 2.2 | H6: RDM 2.3 | I6: RDM 2.4 | J6: RDM 2.5 | K6: RDM 2.6 | L6: RDM 3.1 | M6: RDM 3.2 | N6: RDM 3.3 | O6: RDM 3.4 | P6: RDM 3.5 | Q6: RDM 3.6 | R6: RDM 3.7
A7: Practice | E7: Record requirements. | F7: Elicit stakeholder needs, expectations, constraints, and interfaces or connections. | G7: Transform stakeholder needs, expectations, constraints, and interfaces or connections into prioritized customer requirements. | H7: Develop an understanding with the requirements providers on the meaning of the requirements. | I7: Obtain commitment from project participants that they can implement the requirements. | J7: Develop, record, and maintain bidirectional traceability among requirements and activities or work products. | K7: Ensure that plans and activities or work products remain consistent with requirements. | L7: Develop and keep requirements updated for the solution and its components. | M7: Develop operational concepts and scenarios. | N7: Allocate the requirements to be implemented. | O7: Identify, develop, and keep updated interface or connection requirements. | P7: Ensure that requirements are necessary and sufficient. | Q7: Balance stakeholder needs and constraints | R7: Validate requirements to ensure the resulting solution will perform as intended in the target environment.
A8: Example Work Products | E8: list of requirements; statement of work; use cases; | F8: list of stakeholder needs, constraints, expectations; list of interfaces or connections; | G8: prioritised customer requirements; customer constraints; | H8: list of appropriate requirements providers; criteria for evaluation and acceptance of requirements; results of analyses against criteria; - Recorded changes to requirements - Set of approved requirements | I8: impact assessment; recorded commitments that requirements can be met; | J8: records of bidirectional requirements traceability; | K8: records of inconsistencies between requirements, plans and work products; | L8: requirements; | M8: operational concepts and scenarios; | N8: requirement allocations; | O8: interface or connection requirements; interface or connection requirements review results; action items for updating interface or connection requirements; - Updated interface or connection requirements | P8: requirements analysis results; | Q8: analysis results; proposed requirements changes; | R8: selected validation techniques; record of validation results; updated requirements;
A9: Example Activities | E9: record the requirements; | F9: demonstrations, interviews, questionnaires, scenarios, surveys, brainstorming, beta testing, use cases, business cases | G9: document customer requirements; develop a prioritisation of customer requirements; | H9: develop criteria for identifying providers; develop criteria for evaluation and acceptance of req.; analyse req. to ensure criteria are met; obtain commitments from providers and participants; record changes; | I9: assess impact on existing commitments; negotiate and record commitments; | J9: Develop, record, and maintain bidirectional traceability; | K9: review plans, activities for consistency with requirements; record inconsistencies and sources; initiate and record any corrective actions and communicate to stakeholders; | L9: develop, record, and update requirements in technical terms for solution selections and component design; record bidirectional traceability; review for impoact to architecture and design; record prioritisation; record nontechnical req.; identify and record req. for external interfaces and connections; | M9: develop operational concepts and scenarios; review and refine with stakeholders; | N9: allocate the requirements to be implemented; record and update relationships; review allocations and relationships; | O9: identify, record, update internal and external interface or connection requirements; review for coverage and completeness with stakeholders; | P9: perform a requirements analysis; review results and update; | Q9: analyse to ensure they balance; review and negotiate trade-offs; record and update changes with stakeholders; | R9: identify and select validation techniques; validate using techniques; review and communicate results; update requirements;
A10: Standard Questions - explain how / what ? ... | E10: - What requirements have you documented (or recorded) | F10: - (Explain) How do you elicit (extract) stakeholder needs, expectations, constraints, and interfaces (or connections)? | G10: - (Explain) How do you transform stakeholder needs, expectations, contains, and interfaces (or connections) into prioritized customer requirements? | H10: - (Explain) How do you developed and understanding with the requirements provider on the meaning of the requirements? | I10: - (Explain) How (or what) commitments do you obtain from project participants (developers, testers, etc) that they can implement the requirements? | J10: What bidirectional traceability do you develop and maintain among requirements, other work products or planned activities? | K10: How do you ensure that plans and activities (or work products to be delivered) are consistent with the requirements? | L10: How do you ensure that requirements are kept up to date for the solution (and its components)? | M10: - What operational concepts and scenarios do you develop for requirements? | N10: - How do you allocate requirements for implementation? | O10: - How do you identify, develop, and keep updated interfaces or connection requirements? | P10: - How do you ensure requirements are necessary and sufficient? | Q10: - How do you balance stakeholder needs and constraints? | R10: - How do you validate requirements to ensure the resulting solution will perform as intended in the target environment?
A11: Questions | F11: —(解释)您如何引出(获取)干系人的需求、期望、约束和接口(或连接)? | G11: —(解释)你如何将干系人的需求、期望、约束条件和接口(或连接)转换为优先级的客户需求? | H11: —(解释)你是如何开发需求并与需求提供者一起理解需求的含义的? | I11: —(解释)你如何(或什么)从项目参与者(开发人员、测试人员等)那里获得他们能够实现需求的承诺? | J11: 在需求、其他工作产品或计划的活动中，您开发并维护什么样的双向追溯性? | K11: 您如何确保计划和活动(或要交付的工作产品)与需求保持一致? | L11: 您如何确保解决方案(及其组件)的需求是最新的? | M11: ’—您针对需求开发了哪些操作概念和场景? | N11: —如何分配待实现的需求? | O11: —您如何识别、开发和更新接口或连接需求? | P11: —你如何确保需求是必要和充分的? | Q11: ——你如何平衡干系人的需求和约束条件? | R11: ’—您如何验证需求，以确保最终解决方案在目标环境中能够按照预期的方式执行?
A15: Name | B15: link | C15: engl | D15: \PAs | E15: RDM 1.1 | F15: RDM 2.1 | G15: RDM 2.2 | H15: RDM 2.3 | I15: RDM 2.4 | J15: RDM 2.5 | K15: RDM 2.6 | L15: RDM 3.1 | M15: RDM 3.2 | N15: RDM 3.3 | O15: RDM 3.4 | P15: RDM 3.5 | Q15: RDM 3.6 | R15: RDM 3.7
A16: atm to complete | B16: link | C16: =HYPERLINK("02-项目级\P3-主从数据库复制及性能提升项目\01-生存周期\04-需求\04-需求调研报告\01-需求调研报告(QCUBIC-XNTS-RDM-Report-20220113pm)V1.0-engl.docx", "engl") -> engl | E16: x | R16: x
A17: atm to complete | B17: link | C17: =HYPERLINK("02-项目级\P3-主从数据库复制及性能提升项目\01-生存周期\04-需求\02-需求规格说明书 (QCUBIC-XNTS-RDM-SRS)V1.1-engl.docx", "engl") -> engl | E17: x | F17: x | G17: x | H17: x | I17: x | J17: x | L17: x | M17: x | N17: x | O17: x | P17: x | Q17: x | R17: x
A18: atm to complete | B18: link | C18: =HYPERLINK("02-项目级\P3-主从数据库复制及性能提升项目\01-生存周期\04-需求\03-用户需求说明书(QCUBIC-XNTS-RDM-CRS)V1.1-engl.docx", "engl") -> engl | F18: x | G18: x | H18: x | I18: x
A19: atm to complete | B19: link | C19: =HYPERLINK("02-项目级\P3-主从数据库复制及性能提升项目\02-全程管理\05-评审管理\04-需求评审\01-需求规格说明书\05-评审报告_需求规格说明书(QCUBIC-XNTS-PR-ReviewRpt)V1.1-engl.xlsx", "engl") -> engl | H19: x | I19: x | P19: x | Q19: x | R19: x
A20: atm to complete | B20: link | C20: =HYPERLINK("02-项目级\P3-主从数据库复制及性能提升项目\02-全程管理\05-评审管理\04-需求评审\01-需求规格说明书\02-评审检查表_需求规格说明书(QCUBIC-XNTS-PR-Revchklist)V1.0-engl.xlsx", "engl") -> engl | I20: x | P20: x
A21: atm to complete | B21: link | C21: =HYPERLINK("02-项目级\P3-主从数据库复制及性能提升项目\01-生存周期\04-需求\05-需求跟踪矩阵\01-需求跟踪矩阵(QCUBIC-XNTS-RDM-RTX)V1.1-engl.xlsx", "engl") -> engl | J21: x | K21: x
A22: atm to complete | B22: link | C22: =HYPERLINK("02-项目级\P3-主从数据库复制及性能提升项目\01-生存周期\03-项目策划\03-项目计划书 (QCUBIC-XNTS-PLAN-Plan)V1.1-engl.docx", "engl") -> engl | K22: x
A23: atm to complete | B23: link | C23: =HYPERLINK("02-项目级\P3-主从数据库复制及性能提升项目\01-生存周期\04-需求\01-需求调研计划(QCUBIC-XNTS-RDM-Plan)V1.0-engl.docx", "engl") -> engl | K23: x
A24: atm to complete | B24: link | C24: =HYPERLINK("02-项目级\P3-主从数据库复制及性能提升项目\02-全程管理\06-变更管理\03-变更结果报告(QCUBIC-XNTS-mc-changereport_001)V1.0-engl.docx", "engl") -> engl | K24: x | L24: x
A25: atm to complete | B25: link | C25: =HYPERLINK("02-项目级\P3-主从数据库复制及性能提升项目\02-全程管理\06-变更管理\02-变更列表(QCUBIC-XNTS-MC-CRecoRDM)V1.0-engl.xlsx", "engl") -> engl | L25: x

Sheet TV_PCM
A1: PCM - PROCESS MANAGEMENT (PCM)
A2: Intent | E2: Manages and implements the continuous improvement of processes and infrastructure to: Support accomplishing business objectives Identify and implement the most beneficial process improvements Make the results of process improvement visible, accessible, and sustainable
A3: Value | E3: Ensures that processes, infrastructure, and their improvement contribute to successfully meeting business objectives.
E4: Level 1 | H4: Level 2 | J4: Level 3 | O4: Level 3 | P4: Level 4
E5: some measurement in place | H5: achieve full intent; use local measures to analyse performance / data stored / actions taken | J5: use organisational standards and tailoring; contribute improvements; set performance objectives; proactive not reactive | O5: use organisational standards and tailoring; contribute improvements; set performance objectives; proactive not reactive | P5: use measurement and analysis to control/ stabilise/ predict/ identify and reduce variance; set QPPOs to meet Bos
E6: PCM 1.1 | F6: PCM 1.2 | G6: PCM 1.3 | H6: PCM 2.1 | I6: PCM 2.2 | J6: PCM 3.1 | K6: PCM 3.2 | L6: PCM 3.3 | M6: PCM 3.4 | N6: PCM 3.5 | O6: PCM 3.6 | P6: PCM 4.1
A7: Practice | E7: Develop a support structure to provide process guidance, identify and fix process problems, and continuously improve processes. | F7: Appraise the current process implementation and identify strengths and weaknesses. | G7: Address improvement opportunities or process issues. | H7: Identify improvements to the processes and process assets. | I7: Develop, keep updated, and follow plans for implementing selected process improvements. | J7: Develop, keep updated, and use process improvement objectives traceable to the business objectives. | K7: Identify processes that are the largest contributors to meeting business objectives. | L7: Explore and evaluate potential new processes, techniques, methods, and tools to identify improvement opportunities. | M7: Provide support for implementing, deploying, and sustaining process improvements. | N7: Deploy organizational standard processes and process assets. | O7: Evaluate the effectiveness of deployed improvements in achieving process improvement objectives. | P7: Use statistical and other quantitative techniques to validate selected performance improvements against proposed improvement exceptions, business objectives, or quality and process performance objectives.
A8: Example Work Products | E8: process support structure - EPG; | F8: appraisal plan and schedule; appraisal findings; | G8: action items; | H8: proposed improvement list; recorded selection criteria; list of selected improvements for implementation; | I8: process improvement plan; action plan; developed process assets; status report; recorded results; | J8: process improvement objectives traced to business objectives; | K8: description of relationships between bus. obj., processes and process objs.and value; | L8: potential improvement opportunities; | M8: plan for deployment; implementation records; | N8: list of whether improvements will be deployed; deployment status report; | O8: process improvement evaluation report; | P8: validation plans; validation reports (may include PPBs)
A9: Example Activities | E9: identify and apply a structure for supporting process related activities; assign responsibilities for co-ordinating process related activities; | F9: obtain sponsorship and support for appraisal from snr mgt; define scope of appraisal; select or define the criteria and method for appraisal; plan and schedule; perform appraisal; record and communicate findings; | G9: assign relevant personnel to address improvement opportunities and issues; identify and record action items; address opportunities and issues and communicate results; | H9: identify issues and improvements; group and analyse proposed improvements; record and update criteria for selecting improvements; select proposed improvements for implementation; review selections with stakeholders; record proposed improvements and communicate results; | I9: select performance improvements to deploy; develop plan; ensure deployment is announced, well co-ordinated and supported; manage progress, review, update; develop or update process assets; pilot improvements; deploy improvements; analyse and communicate results; record improvements; | J9: identify and record improvement objectives; review with stakeholders; monitor and update improvement objectives; | K9: review current business model, objectives, and environment; review potential internal or external business changes; identify and record relationships between objectives and processes; estimate value of each process contribution; record, update, communicate results; | L9: identify, research, and record improvements; use established criteria to decide which docs and measures to include in PAL; analyse and evaluate potential process improvement opportunities; record, update and communicate results; | M9: identify mechanisms needed to support process implementation and deployment; ensure that implementation and deployment activities are planned and co-ordinated; align multiple improvement activities; obtain snr mgt commitment for visible support of deployment; provide a migration approach; review deployment results with stakeholders; provide records about success, issues, obstacles; | N9: ensure sufficient support for deployment; identify projects for deployment; co-ordinate deployment of improved processes; deply org. set of standard processes and assets to projects; monitor deployment; review results of objective evaluation; identify, record and trackimplementation issues; review results with stakeholders; | O9: analyse current improvement results against business, process, and performance objectives; record results and communicate to stakeholders; initiate and track corrective actions; | P9: plan the validation; review plans with stakeholders; perform each validationaccording to plan; use statistical or other quant. methods to analyse validation results; review, record and communicate results of validation analysis;
A10: Standard Questions - explain how / what ? ... | E10: What process support structure (for example an EPG) do you have in place? | F10: What appraisals do you do on your current processes? - What appraisals (CMMI, COBIT, ISO) have you done on your current processes? | G10: What process improvement are registered? - How do you collect improvements submitted internally within the organisation? | H10: How do you identify improvements in processes and process assets? - How do you select the proposed improvements? | I10: What process improvement actions are followed to implement identified improvements? | J10: Explain how you link your process improvements to business objectives? | K10: How do you prioritise your process improvements? | L10: How do you evaluate potential new improvements opportunities. Improvements include new processes, techniques, methods and tools? | M10: What support is provided for implementing and deploying new process improvements? | N10: How are organisational standard processes and process assets deployed? | O10: How do you evaluate the effectiveness of improvements towards achieving business objectives? How do you evaluate the non-statistically measured improvements (small improvements)? | P10: - How do you make use of statistical and other quantitative techniques to validate selected performance improvements against proposed improvement exceptions, business objectives, or quality and process performance objectives?
A11: Questions | F11: 你是如何评估你目前的工作流程的? -你对目前的流程做过哪些评估(CMMI, COBIT, ISO) ? | G11: 记录了哪些流程改进? -你如何收集组织内部提交的改进? | H11: 针对过程和过程资产确定了哪些改进? -你如何确定和选择建议的改进? | I11: 遵循什么过程改进行动（计划）来实施已确定的改进? | J11: 如何将过程改进与业务目标联系起来? | K11: 您如何确定过程改进的优先级? | L11: 你如何评估潜在的新的改进机会?改进包括对过程、技术、方法和工具的改进。 | M11: 为实现和部署新的过程改进提供了什么支持? | N11: 如何部署组织的标准过程和过程资产? | O11: 您如何评估（为实现业务目标而进行的）改进的有效性? 如何评估非统计度量的改进(小改进)? | P11: - How do you make use of statistical and other quantitative techniques to validate selected performance improvements against proposed improvement exceptions, business objectives, or quality and process performance objectives?
A15: Name | B15: link | C15: engl | D15: \PAs | E15: PCM 1.1 | F15: PCM 1.2 | G15: PCM 1.3 | H15: PCM 2.1 | I15: PCM 2.2 | J15: PCM 3.1 | K15: PCM 3.2 | L15: PCM 3.3 | M15: PCM 3.4 | N15: PCM 3.5 | O15: PCM 3.6 | P15: PCM 4.1 | Q15: PCM 4.1
A16: atm to complete | B16: link | C16: =HYPERLINK("01-组织级\02-组织工作库\02-EPG活动库\03-过程改进计划\过程改进计划(QCUBIC-SPI-PIM-PIPlan)V1.2-engl.docx", "engl") -> engl | E16: x | H16: x | I16: x | J16: x | K16: x
A17: atm to complete | B17: link | C17: =HYPERLINK("01-组织级\02-组织工作库\02-EPG活动库\02-现场诊断\北京快立方科技有限公司现场诊断报告-engl.pptx", "engl") -> engl | F17: x
A18: atm to complete | B18: link | C18: =HYPERLINK("01-组织级\02-组织工作库\02-EPG活动库\过程改进总结报告-engl.pptx", "engl") -> engl | F18: x | L18: x | N18: x | O18: x
A19: atm to complete | B19: link | C19: =HYPERLINK("01-组织级\02-组织工作库\02-EPG活动库\01-EPG章程\EPG章程(QCUBIC-SPI-PIM-Std-EPGRule)V1.2-engl.docx", "engl") -> engl | F19: x
A20: atm to complete | B20: link | C20: =HYPERLINK("01-组织级\02-组织工作库\02-EPG活动库\07-EPG跟踪\05-过程改进建议表\过程改进建议表(QCUBIC-SPI-PIM-SPIAdvic)V1.2-engl.xlsx", "engl") -> engl | G20: x | M20: x
A21: atm to complete | B21: link | K21: x
A22: atm to complete | B22: link | C22: =HYPERLINK("01-组织级\02-组织工作库\02-EPG活动库\03-过程改进计划\关键子过程选择(QCUBIC_PCM_Select subprocess)V1.0-engl.xlsx", "engl") -> engl | K22: x
A23: atm to complete | B23: link | C23: =HYPERLINK("01-组织级\02-组织工作库\02-EPG活动库\03-过程改进计划\过程改进计划评审报告(QCUBIC-SPI-VV-Tem-ReviewRpt)V1.2-engl.xlsx", "engl") -> engl | L23: x
A24: atm to complete | B24: link | M24: x
A25: atm to complete | B25: link | C25: =HYPERLINK("01-组织级\02-组织工作库\02-EPG活动库\05-项目试点\试点行动计划(QCUBIC-SPI-PIM-PilotPlan)V1.1-engl.docx", "engl") -> engl | M25: x
A26: atm to complete | B26: link | C26: =HYPERLINK("01-组织级\02-组织工作库\02-EPG活动库\07-EPG跟踪\06-过程改进里程碑\过程改进里程碑报告(ORG_PCM_Milestone_20220628)V1.0-engl.docx", "engl") -> engl | N26: x
A27: atm to complete | B27: link | C27: =HYPERLINK("01-组织级\02-组织工作库\02-EPG活动库\06-过程推广\过程部署计划(QCUBIC-SPI-PIM-PSPreadPlan)V1.2-engl.docx", "engl") -> engl | N27: x

Sheet TV_PAD
A1: PAD - PROCESS ASSET DEVELOPMENT (PAD)
A2: Intent | E2: Develop and keep updated the process assets necessary to perform the work.
A3: Value | E3: Provides a capability to understand and repeat successful performance.
E4: Level 1 | F4: Level 2 | I4: Level 3
E5: some measurement in place | F5: achieve full intent; use local measures to analyse performance / data stored / actions taken | I5: use organisational standards and tailoring; contribute improvements; set performance objectives; proactive not reactive
E6: PAD 1.1 | F6: PAD 2.1 | G6: PAD 2.2 | H6: PAD 2.3 | I6: PAD 3.1 | J6: PAD 3.2 | K6: PAD 3.3 | L6: PAD 3.4 | M6: PAD 3.5 | N6: PAD 3.6 | O6: PAD 3.7
A7: Practice | E7: Develop process assets to perform the work. | F7: Determine what process assets will be needed to perform the work. | G7: Develop, buy, or reuse process assets. | H7: Make processes and assets available. | I7: Develop, keep updated, and follow a strategy for building and updating process assets. | J7: Develop, record, and keep updated a process architecture that describes the structure of the organization's processes and process assets. | K7: Develop, keep updated, and make processes and assets available for use. | L7: Develop, keep updated, and use tailoring criteria and guidelines for the set of standard processes and assets. | M7: Develop, keep updated, and make the organization's process asset library available for use. | N7: Develop, keep updated, and make work environment standards available for use. | O7: Develop, keep updated, and make organizational measurement and analysis standards available for use.
A8: Example Work Products | E8: work instructions; process descriptions; templates; | F8: templates; work instructions; tools; | G8: build, buy, re-use analysis results; process assets; | H8: process assets; | I8: strategy for building and updating process assets; | J8: process requirements; process architecture format; process architecture; | K8: action plans; status and results of action plans; org. set of standard processes and assets; new processes or assets; | L8: tailoring guidelines; waivers or requests for process waivers; | M8: design of org. PAL; org. PAL; process related work products in PAL; | N8: work env. standards; waivers or requests for work env. waivers; | O8: org. measuremnt and analysis standards; waivers or requests for measurement and analysis waivers;
A9: Example Activities | E9: record work instructions; | F9: identify process assets needed (for the project); | G9: select which assets will be analysed for build, buy, re-use; perform build, buy, re-use analysis; record results; build, buy or re-use the assets; | H9: make assets available for use (by projects); communicate availability of assets for use; | I9: develop a strategy for building and updating process assets; | J9: identify process requirements; identify process architecture objectives; develop and record format; develop, record, update process architecture; review and update with stakeholders; communicate and make available; | K9: verify that org. standard process set is aligned to strategic process needs and objectives; assign responsibilities for acquiring, developing, maintaining processes; review and decide if improvement recommendations should be incorporated; record process action plans; develop org. standards for processes and assets; track progress and commitments; establish process action teams; build and record processesand assets; perform reviews on standard processes and assets; revise processes and assets; make processes and assets available; | L9: specify selection criteria and procedures for tailoring; specify standards for recording defined process; specifu proceudres to submit and approve waivers from org std processes; record, approve, communicate tailoring guidelines; revise tailoring guidelines; | M9: design and implement the org. PAL; specify criteria for including assets in PAL; specify procedures for storing and retrieving assets; make assets available; periodically review usefulness of assets; enter selected assets in library; | N9: evaluate commercially available work environment standards; periodically analyse work env. to identify changes or resources that could improve; prioritise potential improvements to work env.; identify resources that could improve performance; ensure projects have authority to organise or tailor work env.; review work env. with project; adopt, develop or tailor work env. Stds. To fill gaps; | O9: specify org. standards for measurement and analysis; specify tailoring guidelines for applying measurement standards;
A10: Standard Questions - explain how / what ? ... | F10: - How do you determine or identify what process assets are needed? - | G10: - Which process assets have been developed (or re-used) and which purchased? Analysis? | H10: - (3.3) How are the process assets made available to the organisation? | I10: - Which process is defined for developing process assets? | J10: - What process architecture is in place describing the structure of the organization's processes? | K10: - (2.3) How are the process assets made available for use in the organisation? | L10: - How do you use tailoring guidelines for your standard process assets? How do you update the tailoring guidelines? | M10: =K10 -> - (2.3) How are the process assets made available for use in the organisation? | N10: - What work environment standards have been established and maintained? | O10: - What organisational measurement and analysis standards are available for use?
A11: Questions | F11: —根据需要确定了哪些过程资产? - | G11: —哪些过程资产已经被开发(或重用)，哪些被购买? 有没有执行分析? | H11: 组织如何使用过程资产? | I11: —为开发过程资产定义了哪个过程? | J11: —描述组织过程结构的过程体系结构是什么? | K11: —(2.3)如何使过程资产在组织中可用? | L11: —对于您的标准过程资产，您有什么裁剪指南? | M11: =K11 -> —(2.3)如何使过程资产在组织中可用? | N11: 建立并保持了什么样的工作环境标准? | O11: 有什么组织度量和分析标准可供使用?
A15: Name | B15: link | C15: engl | D15: \PAs | E15: PAD 1.1 | F15: PAD 2.1 | G15: PAD 2.2 | H15: PAD 2.3 | I15: PAD 3.1 | J15: PAD 3.2 | K15: PAD 3.3 | L15: PAD 3.4 | M15: PAD 3.5 | N15: PAD 3.6 | O15: PAD 3.7
A16: atm to complete | B16: link | E16: x | F16: x | G16: x | M16: x
A17: atm to complete | B17: link | G17: x
A18: atm to complete | B18: link | H18: x | I18: x | J18: x | K18: x
A19: atm to complete | B19: link | C19: =HYPERLINK("01-组织级\02-组织工作库\02-EPG活动库\03-过程改进计划\过程改进计划(QCUBIC-SPI-PIM-PIPlan)V1.2-engl.docx", "engl") -> engl | I19: x
A20: atm to complete | B20: link | C20: =HYPERLINK("01-组织级\01-组织财富库\01-标准过程文件库\04-组织过程类\02-过程资产管理\过程资产库管理指南 (QCUBIC-SPI-OPAL-Guid-Assetlib)V1.2-engl.docx", "engl") -> engl | I20: x
A21: atm to complete | B21: link | C21: =HYPERLINK("01-组织级\01-组织财富库\01-标准过程文件库\04-组织过程类\02-过程资产管理\过程资产管理过程文件 (QCUBIC-SPI-OPAL-Proc-Doc)V1.2-engl.docx", "engl") -> engl | I21: x
A22: atm to complete | B22: link | J22: x
A23: atm to complete | B23: link | J23: x
A24: atm to complete | B24: link | C24: =HYPERLINK("01-组织级\01-组织财富库\01-标准过程文件库\04-组织过程类\02-过程资产管理\裁剪指南 (QCUBIC-SPI-OPAL-Guid-Tailor)V1.2-engl.xlsx", "engl") -> engl | L24: x
A25: atm to complete | B25: link | C25: =HYPERLINK("01-组织级\01-组织财富库\01-标准过程文件库\04-组织过程类\02-过程资产管理\工作环境标准(QCUBIC-SPI-OPAL-Std-Environment)V1.2(1)-engl.docx", "engl") -> engl | N25: x
A26: atm to complete | B26: link | C26: =HYPERLINK("01-组织级\02-组织工作库\06-度量\组织度量表(QCUBIC-SPI-MPM-Tem-datasheet)V1.3-engl.xlsx", "engl") -> engl | O26: x
A27: atm to complete | B27: link | C27: =HYPERLINK("01-组织级\01-组织财富库\01-标准过程文件库\03-支持类\03-度量分析\度量分析指南 (QCUBIC-SPI-MPM-Guid-Doc)V1.2-engl.docx", "engl") -> engl | O27: x

Sheet TV_MPM
A1: MANAGING PERFORMANCE AND MEASUREMENT
A2: Intent | E2: Manage performance using measurement and analysis to achieve business objectives.
A3: Value | E3: Maximizes business return on investment by focusing management and improvement efforts on cost, schedule, and quality performance.
E4: Level 1 | G4: Level 2 | M4: Level 3 | S4: Level 4 | X4: Level 5
E5: some measurement in place | G5: achieve full intent; use local measures to analyse performance / data stored / actions taken | M5: use organisational standards and tailoring; contribute improvements; set performance objectives; proactive not reactive | S5: use measurement and analysis to control/ stabilise/ predict/ identify and reduce variance; set QPPOs to meet Bos | X5: use stat. analysis to optimise performance and improvement to achieve the QPPO's, business objectives and strategy
E6: MPM 1.1 | F6: MPM 1.2 | G6: MPM 2.1 | H6: MPM 2.2 | I6: MPM 2.3 | J6: MPM 2.4 | K6: MPM 2.5 | L6: MPM 2.6 | M6: MPM 3.1 | N6: MPM 3.2 | O6: MPM 3.3 | P6: MPM 3.4 | Q6: MPM 3.5 | R6: MPM 3.6 | S6: MPM 4.1 | T6: MPM 4.2 | U6: MPM 4.3 | V6: MPM 4.4 | W6: MPM 4.5 | X6: MPM 5.1 | Y6: MPM 5.2 | Z6: MPM 5.3
A7: Practice | E7: Collect measures and record performance. | F7: Identify and address performance issues. | G7: Derive and record measurement and performance objectives (MPOs) from selected business needs and objectives and keep them updated. | H7: Develop, keep updated, and use operational definitions for measures. | I7: Obtain specified measurement data according to the operational definitions. | J7: Analyze performance and measurement data according to the operational definitions. | K7: Store measurement data, measurement specifications, and analysis results according to the operational definitions. | L7: Take actions to address identified issues with meeting measurement and performance objectives. | M7: Develop, keep updated, and use organizational measurement and performance objectives (OMPOs) traceable to business objectives (BOs). | N7: Follow organizational processes and standards to develop and use operational definitions for measures and keep them updated. | O7: Develop, keep updated, and follow a data quality process. | P7: Develop, keep updated, and use the organization's measurement repository. | Q7: Analyze organizational performance using measurement and performance data to determine performance improvement needs. | R7: Periodically communicate performance results to the organization. | S7: Use statistical and other quantitative techniques to develop, keep updated, and communicate quality and process performance objectives (QPPOs) that are traceable to business objectives (BOs). | T7: Select measures and analytical techniques to quantitatively manage performance to achieve quality and process performance objectives (QPPOs). | U7: Use statistical and other quantitative techniques to develop and analyze process performance baselines (PPBs) and keep them updated. | V7: Use statistical and other quantitative techniques to develop and analyze process performance models (PPMs) and keep them updated. | W7: Use statistical and other quantitative techniques to determine or predict achievement of quality and process performance objectives (QPPOs). | X7: Use statistical and other quantitative techniques to ensure that business objectives (BOs) are aligned with business strategy (BS) and performance. | Y7: Analyze performance data using statistical and other quantitative techniques to determine the organization's ability to satisfy selected business objectives and identify potential areas for performance improvement. | Z7: Select and implement improvement proposals, based on the statistical and quantitative analysis of the expected effect of proposed improvements on meeting business, quality and process performance objectives.
A8: Example Work Products | E8: measures; performance analysis results; | F8: list of performance issues; list of suggestions; | G8: measurement and performance objectives; | H8: operational definitions of measures; analysis methods and tools; data collection mechanisms; | I8: base and derived measurement data; results of data integrity checks; | J8: performance data analysis results; updated operational definitions; | K8: stored data | L8: revised objectives, plans, commitments; records of performance evaluations; records of significant deviations; proposed improvements | M8: business objectives traced to measurement and performance objectives; allocation of measurement and performance objectives; | N8: operational definitions following org. stds.; | O8: data quality criteria; meas. rep. data quality report; data quality issues; improvement proposals; | P8: measurement repository design; measurement repository; measurement data; | Q8: aggregated performance results; performance analysis results; performance improvement needs; performance improvement suggestions; | R8: performance improvement and analysis reports; dashboards, monitors, intranet sites; | S8: defined QPPOs traced to business objectives; risks of not achieving QPPO's; | T8: list of selected measures; repository of analytical and stat. techniques; environment to support collection and analysis; results of analyses; traceability to objectives; | U8: results of analysis of process performance data; process performance baselines; | V8: process performance models; validation results; calibration results; | W8: results of analysis, validation and calibration (control charts, regression analysis); prediction of results to be achieved; recorded risks of no achievement; list of actions to address deficiencies in process stability or capability; | X8: results of analysis of current performance against QPPOs, BOs, BS; revised BOs and BS; revised QPPOs; revised measures; | Y8: performance analysis results; list of performance shortfalls; list of potential improvement proposals; | Z8: analysis of potential impacts of proposals; piloting report; cost benefit analysis; list of potential barriers and risks; recorded validation methods; list of submitted proposals for implementation;
A9: Example Activities | E9: identify available measures and collection methods; collect and record measures; | F9: collect measurements and derive performance data; review performance; identify issues; understand causes; make suggestions; address issues; | G9: identify current or planned perf. objectives; record and prioritise business needs and objectives; review and keep updated measurement and perf. obj.; review bus.needs and obj. against performance needs; | H9: identify existing measures; select measures; establish operational definitions; specify collection and storage; select data analysis methods and tools; review with stakeholders; | I9: collect data for specified base measures; calculate derived measures; check data integrity close to source; | J9: perform analyses, interpret results, draw conclusions; record analysis results and significant deviations; review results; refine measurements and analysis techniques; | K9: review data to ensure quality; store data; make available for use; control access to data; | L9: record and implement corrective actions; record and submit proposed improvements; communicate results | M9: develop, review, analyse business objectives; develop, record, use OMPOs; analyse performance of projects; allocate objectives to projects; trace OMPOs to BOs; review and update allocations; | N9: record, communicate, and use org. std. operational definitions; revise as needed; | O9: develop criteria for data quality, accuracy, precision and validity; check whether criteria are met; identify and communicate data quality issues; identify and communicate data improvement proposals; | P9: determine org. needs for storing, retrieving and analysing; design and implement the measurement repository; populate contents, communicate availability; revise as needed; | Q9: aggregate performance data to the business level; analyse OMPOs against current performance; identify shortfalls and pot. improvement areas where not meeting BOs; record performance improvement needs; analyse cost / benefit; communicate results; submit perf. improvement suggestions; | R9: develop and record performance improvement reports; communicate performance improvement results; | S9: define, record, update, communicate, QPPO's; derive interim objectives to monitor progress; determine and record risks of not achieving; resolve conflicts between objectives; | T9: identify common measures; identify additional measures; select measures to manage processes; specify operational definitions of new measures; identify stat. and quant. techniques; analyse relationship of measures to QPPO's; develop environment to support collection and analysis of measures; record, update and use measures and stat. techniques; | U9: analyse the measures for central tendency and normal variation; record, update and use process performance baselines; review with stakeholders; make available and communicate to org.; revise as needed; | V9: establish process performance models; validate the PPM; calibrate PPM based on results; review with stakeholders; make available and communicate to org.; support the use of PPMs; revise as needed; | W9: analyse the variation and stability of selected processes; address deficiencies and signals; implement actions needed to address deficiencies; use validated PPMs to assess progress toward QPPOs; identify and manage risks; record and communicate results, decisions, and actions; | X9: evaluate and update business objectives to align with business strategies; compare business objectives (BOs) with PP predictions to ensure achievability; prioritise BOs based on criteria; maintain QPPOs to address changes in Bos; revise measures to align with QPPOs; communicate changes to BS, BOs, QPPOs to stakeholders; | Y9: compare QPPOs to current PPBs and PPMs to evaluate and predict org ability to satisfy BOs; identify shortfalls; identify potential improvement areas; communicate results and list improvement proposals; | Z9: use PPMs to predict process performance based on proposed improvements; run pilots; run tests for stat significance of modelled or piloted results; analyse cost / benefit of proposed improvements; identify potential barries and risks; record evaluation results; determine and record validation method; implement selected proposals; validate implemented proposals; deploy throughout;
A10: Standard Questions - explain how / what ? ... | E10: What performance measures do you collect? | F10: How do you identify performance issues? | G10: How do you derive measurement objectives from your business needs? How and how often are they updated? | H10: Do you have op defns? What operational definitions of measures do you have (who to collect, what to collect, when to collect)? How and how often are they updated? | I10: Do you … ? How do you collect measurement data? Who collects …? | J10: Do you … ? How do you analyse the performance and measurement data? | K10: Do you … ? 'How / where do you store the measurement data and analysis results? | L10: Do you … ? What actions to you take on issues identified from performance reports? | M10: How are measurement objectives traced to business objectives? Developed and maintained? | N10: *Please explain how your measurement process functions? *How did you develop your set of measures and how do you update and improve them? | O10: How do you ensure data quality for measurements? What data quality checks do you do? | P10: Do you have a measurement repository? Describe it - how is it set-up? | Q10: How do you analyse organization performance? What measurement reports are used? How do you determine performance improvement needs? | R10: How do you communicate performance results within the organisation? | S10: *How do you use statistical and other quantile techniques to develop, keep updated, and communicate quality and process performance objectives? *How do you set Quantitative Process Performance Objectives (QPPOs), what methods do you use? *How are the QPPO's kept traceable to your business objectives? | T10: *How do you select measures and analytical techniques to quantitively manage performance to achieve quality and process performance objectives? *How do you stay up to date with methods / research / approaches? *Which techniques do you use? *Do you use six sigma? | U10: *How do you make use of statistical and other quantitative techniques to develop and analyse process performance baselines and keep them updated. *What process performance baselines (PPBs) from which methods exist? *How do you develop the baselines? *How often updated? | V10: *How do you make use of statistical and other quantitative techniques to develop and analyse process performance models and keep them updated. *What process performance models (PPMs) exist developed from which methods? *How do you develop the models? | W10: *How do you make use of statistical and other quantitative techniques to determine or predict achievement of quality and process performance objectives. *How do you predict the achievement of the QPPOs? (eg. Monte Carlo simualtion) | X10: *How do you make use of statistical and other quantitative techniques to ensure that business objectives are aligned with business strategy and performance? *Explain how the business objectives (through the QPPOs) are aligned to the business strategy - who is involved, where do you start, what is the process? * Explain how the business objectives are used to check / support the achievement of business strategy and performance? | Y10: How do you analyse performance data using statistical and other quantitative techniques to determine the organization's ability to satisfy selected business objectives and identify potential areas for performance improvement. | Z10: How do you select and implement improvement proposals, based on the statistical and quantitative analysis of the expected effect of proposed improvements on meeting business, quality, and process performance objectives.
A11: Questions | E11: Do you … ? What performance measures do you collect?您收集了哪些性能指标? | G11: 您如何从您的业务需求中获得度量目标? 它们如何更新，多长时间更新一次? | H11: 您对度量有什么操作性定义(谁收集谁收集什么、何时收集)? 它们如何更新，多长时间更新一次? | I11: 如何收集度量数据? | J11: 你如何分析绩效和度量数据? | K11: 如何/在哪里存储度量数据和分析结果?” | L11: 对于从性能报告中发现的问题，你会采取什么行动? | M11: 如何将度量目标跟踪到业务目标? 开发和维护? | N11: 请解释您的度量过程是如何运作的? *你是如何制定你的度量标准的?你是如何更新和改进它们的? | O11: 如何确保度量的数据质量? 你做什么数据质量检查? | P11: 您有度量存储库吗? 描述一下，它是如何建立的? | Q11: 你如何分析组织性能? 使用什么度量报告? 您如何确定性能改进需求? | R11: 你如何在组织内部传达性能结果? | S11: *How do you use statistical and other quantile techniques to develop, keep updated, and communicate quality and process performance objectives? *How do you set Quantitative Process Performance Objectives (QPPOs), what methods do you use? *How are the QPPO's kept traceable to your business objectives? | T11: *How do you select measures and analytical techniques to quantitively manage performance to achieve quality and process performance objectives? *How do you stay up to date with methods / research / approaches? *Which techniques do you use? *Do you use six sigma? | U11: *How do you make use of statistical and other quantitative techniques to develop and analyse process performance baselines and keep them updated. *What process performance baselines (PPBs) from which methods exist? *How do you develop the baselines? *How often updated? | V11: *How do you make use of statistical and other quantitative techniques to develop and analyse process performance models and keep them updated. *What process performance models (PPMs) exist developed from which methods? *How do you develop the models? | W11: *How do you make use of statistical and other quantitative techniques to determine or predict achievement of quality and process performance objectives. *How do you predict the achievement of the QPPOs? (eg. Monte Carlo simualtion) | X11: *How do you make use of statistical and other quantitative techniques to ensure that business objectives are aligned with business strategy and performance? *Explain how the business objectives (through the QPPOs) are aligned to the business strategy - who is involved, where do you start, what is the process? * Explain how the business objectives are used to check / support the achievement of business strategy and performance? | Y11: How do you analyse performance data using statistical and other quantitative techniques to determine the organization's ability to satisfy selected business objectives and identify potential areas for performance improvement. | Z11: How do you select and implement improvement proposals, based on the statistical and quantitative analysis of the expected effect of proposed improvements on meeting business, quality, and process performance objectives.
A15: Name | B15: link | C15: engl | D15: \PAs | E15: MPM 1.1 | F15: MPM 1.2 | G15: MPM 2.1 | H15: MPM 2.2 | I15: MPM 2.3 | J15: MPM 2.4 | K15: MPM 2.5 | L15: MPM 2.6 | M15: MPM 3.1 | N15: MPM 3.2 | O15: MPM 3.3 | P15: MPM 3.4 | Q15: MPM 3.5 | R15: MPM 3.6 | S15: MPM 4.1 | T15: MPM 4.2 | U15: MPM 4.3 | V15: MPM 4.4 | W15: MPM 4.5 | X15: MPM 5.1 | Y15: MPM 5.2 | Z15: MPM 5.3
A16: atm to complete | B16: link | C16: =HYPERLINK("01-组织级\02-组织工作库\06-度量\组织度量表(QCUBIC-SPI-MPM-Tem-datasheet)V1.3-engl.xlsx", "engl") -> engl | E16: x | F16: x | I16: x | J16: x | K16: x | L16: x | M16: x | N16: x | P16: x | Q16: x | R16: x
A17: atm to complete | B17: link | C17: =HYPERLINK("01-组织级\02-组织工作库\06-度量\组织度量计划(QCUBIC-SPI-MPM-Plan)V1.3-engl.xlsx", "engl") -> engl | E17: x | G17: x | H17: x | N17: x
A18: atm to complete | B18: link | C18: =HYPERLINK("01-组织级\01-组织财富库\01-标准过程文件库\03-支持类\03-度量分析\度量分析指南 (QCUBIC-SPI-MPM-Guid-Doc)V1.2-engl.docx", "engl") -> engl | H18: x | O18: x
A19: atm to complete | B19: link | C19: =HYPERLINK("01-组织级\01-组织财富库\01-标准过程文件库\03-支持类\03-度量分析\度量分析过程文件 (QCUBIC-SPI-MPM-Proc-Doc)V1.2-engl.docx", "engl") -> engl | N19: x
A20: atm to complete | B20: link | C20: =HYPERLINK("01-组织级\02-组织工作库\03-PQA活动库\组织级工作产品和过程检查表(QCUBIC-ORG-PQA-Checklist_20200627)V1.0-engl.xlsx", "engl") -> engl | O20: x
A21: atm to complete | B21: link | C21: =HYPERLINK("01-组织级\02-组织工作库\02-EPG活动库\07-EPG跟踪\01-EPG月报\EPG月报2020-06-engl.xlsx", "engl") -> engl | R21: x
A22: atm to complete | B22: link | C22: =HYPERLINK("01-组织级\02-组织工作库\01-会议记录\高层会议记录(QCUBIC-SPI-MeetingRcd-2020-06-03)V1.0-engl.docx", "engl") -> engl | R22: x

Sheet TV_RSK
A1: RSK - RISK AND OPPORTUNITY MANAGEMENT (RSK)
A2: Intent | E2: Identify, record, analyze, and manage potential risks or opportunities.
A3: Value | E3: Mitigate adverse impacts or capitalize on positive impacts to increase the likelihood of meeting objectives.
E4: Level 1 | F4: Level 2 | H4: Level 3
E5: some measurement in place | F5: achieve full intent; use local measures to analyse performance / data stored / actions taken | H5: use organisational standards and tailoring; contribute improvements; set performance objectives; proactive not reactive
E6: RSK 1.1 | F6: RSK 2.1 | G6: RSK 2.2 | H6: RSK 3.1 | I6: RSK 3.2 | J6: RSK 3.3 | K6: RSK 3.4 | L6: RSK 3.5
A7: Practice | E7: Identify and record risks or opportunities and keep them updated. | F7: Analyze identified risks or opportunities. | G7: Monitor identified risks or opportunities and communicate status to affected stakeholders. | H7: Identify and use risk or opportunity categories. | I7: Define and use parameters for risk or opportunity analysis and handling. | J7: Develop and keep updated a risk or opportunity management strategy. | K7: Develop and keep updated risk or opportunity management plans. | L7: Manage risks or opportunities by implementing planned risk or opportunity management activities.
A8: Example Work Products | E8: list of identified risks and opportunities; | F8: identified risks or opportunities; risk or opportunity priorities; risk and opportunity analysis report; | G8: records of risk or opportunity monitoring; updated risks or opportunities; | H8: categories list; categorised risks or opportunities; | I8: risk or opportunity evaluation, categorisation, and prioritisation parameters; list of risks or opportunities and their assigned priority; risk or opportunity assessment results; | J8: risk or opportunity management strategy; | K8: risk management plans; opportunity leveraging plans; updated plans and status; | L8: updated status;
A9: Example Activities | E9: identify the risks associated with the work; record the risks; identify opportunities; identify affected stakeholders; | F9: analyse the identified risks; analyse identified opportunities; review wbs, plan and schedule; identify impact for each; identify probability for each; assign priorities to each; identify cost benefit for opportunities; review with stakeholders; develop risk and opportunity report; | G9: periodically review risks and opportunities; update with additional information; communicate status to stakeholders; | H9: identify risk or opportunity categories; organise risks and opportunities according to categories; | I9: identify relative priority for each based on parameters; define thresholds; prepare and perform assessments; | J9: develop record and keep updated a risk or opportunity management strategy; review strategy with stakeholders; | K9: develop mitigation plans and contingency plans for risks; develop leverage plans for opportunities; review plans with stakeholders; | L9: manage risks or opportunities using management plans;
A10: Standard Questions - explain how / what ? ... | E10: - How do you identify and record risks or opportunities and keep them updated? | F10: - Explain how / what do you analyse the identified risks or opportunities? | G10: - How do you monitor identified risks or opportunities and communicate this status to affected stakeholders? | H10: - Explain how you make use of risk or opportunity categories? - Do you have standard categories of risks and maybe lists of expected possible risks | I10: - What parameters for risk or opportunity analysis is defined and what is it used for? | J10: - Explain the risk and the opportunity management strategies that you have developed and maintain? | K10: - Explain the risk and opportunity management plans that you have developed and maintain? | L10: - Explain how you manage (mitigate) risk or opportunity items?
A11: Questions | E11: ——你如何识别和记录风险或机会，并保持更新? | F11: ——你如何分析已确定的风险或机会? | G11: —您如何监控已发现的风险或机会，并将这一状况告知受影响的干系人? | H11: —解释一下你是如何利用风险或机会类别的? | I11: 定义了风险或机会分析的哪些参数，用于什么用途? | J11: —请解释你可能会建立和维护的任何风险或机会管理策略? | K11: —请解释您可能制定和维护的任何风险或机会管理计划? | L11: —解释一下你是如何管理(减轻)风险或机会项目的?
A15: Name | B15: link | C15: engl | D15: \PAs | E15: RSK 1.1 | F15: RSK 2.1 | G15: RSK 2.2 | H15: RSK 3.1 | I15: RSK 3.2 | J15: RSK 3.3 | K15: RSK 3.4 | L15: RSK 3.5
A16: atm to complete | B16: link | C16: =HYPERLINK("02-项目级\P1-Qcubic数据库管理工具 V1.0\02-全程管理\02-风险和机会管理\03-风险和机会管理一览表(QCUBIC-SJKGL-RSK-chk&tracking)V1.2-engl.xlsx", "engl") -> engl | E16: x | F16: x | G16: x | H16: x | I16: x | J16: x | L16: x
A17: atm to complete | B17: link | C17: =HYPERLINK("02-项目级\P1-Qcubic数据库管理工具 V1.0\02-全程管理\02-风险和机会管理\01-风险和机会检查表(QCUBIC-SJKGL-RSK-rc)V1.0-engl.xlsx", "engl") -> engl | E17: x | F17: x
A18: atm to complete | B18: link | C18: =HYPERLINK("02-项目级\P1-Qcubic数据库管理工具 V1.0\02-全程管理\02-风险和机会管理\02-风险和机会管理计划(QCUBIC-SJKGL-RSK-plan)V1.0-engl.docx", "engl") -> engl | F18: x | K18: x | L18: x
A19: atm to complete | B19: link | C19: =HYPERLINK("01-组织级\01-组织财富库\01-标准过程文件库\01-项目管理规范\05-风险和机会管理\风险和机会管理过程文件(QCUBIC-SPI-RSK-Proc-Doc)V1.2-engl.docx", "engl") -> engl | H19: x | I19: x | J19: x
A20: atm to complete | B20: link | C20: =HYPERLINK("01-组织级\01-组织财富库\01-标准过程文件库\01-项目管理规范\05-风险和机会管理\风险和机会管理指南(QCUBIC-SPI-RSK-Guid-Management)V1.2-engl.docx", "engl") -> engl | H20: x | I20: x | J20: x

Sheet TV_OT
A1: OT - ORGANIZATIONAL TRAINING (OT)
A2: Intent | E2: Develop the skills and knowledge of personnel so they perform their roles efficiently and effectively.
A3: Value | E3: Enhances individuals' skills and knowledge to improve organizational work performance.
E4: Level 1 | F4: Level 2 | H4: Level 3
E5: some measurement in place | F5: achieve full intent; use local measures to analyse performance / data stored / actions taken | H5: use organisational standards and tailoring; contribute improvements; set performance objectives; proactive not reactive
E6: OT 1.1 | F6: OT 2.1 | G6: OT 2.2 | H6: OT 3.1 | I6: OT 3.2 | J6: OT 3.3 | K6: OT 3.4 | L6: OT 3.5 | M6: OT 3.6
A7: Practice | E7: Train people. | F7: Identify training needs. | G7: Train personnel and keep records. | H7: Develop and keep updated the organization's strategic and short-term training needs. | I7: Coordinate training needs and delivery between the projects and the organization. | J7: Develop, keep updated, and follow organizational strategic and short-term training plans. | K7: Develop, keep updated, and use a training capability to address organizational training needs. | L7: Assess the effectiveness of the organization's training program. | M7: Record, keep updated, and use the set of organizational training records.
A8: Example Work Products | E8: completed training; | F8: list of training needs; | G8: records of delivered training; | H8: training needs; | I8: allocated training needs; training delivery responsibilities; | J8: org. training strategic plan; org. training short term plan; recorded commitments; | K8: training materials; list of courses; training records; list of instructors; instruction design standards; training facilities and resources; | L8: training effectiveness surveys; training program assessments; training program analysis results; instructor evaluation forms; training examinatiosn; training measures; | M8: training records;
A9: Example Activities | E9: identify people to receive training; schedule training; deliver the training; | F9: identify skills and knowledge for each role; record and update skills and knowledge of individuals; perform a gap analysis to determine needs; record and communicate training needs; | G9: deliver training based on identified training needs; maintain training records; | H9: determine the roles and skills needed to perform org. standard processes and work; determine training needs; record and update the prioritised strategic and short term org. training needs; review the org. training needs periodically and on an event driven basis and update; | I9: analyse training needs identified by work and support groups; co-ordinate to determinehow training needs will be addressed; record responsibilities among oreg.,project and support groups for delivery; | J9: develop the content of the org. training strategic plan; develop the content of the org. training short term plan; review plans, determine commitments and communicate review results; revise plans and commitments; | K9: select approaches to satisfy org. training needs; decide whether to develop training internally or acquire externally; develop or obtain training materials; identify, train or hire trainers; describe training in org. training curriculum; review training periodically; revise as needed; identify and make resources available; update training and development program; keep training records updated; communicate availability of training; | L9: assess the effectiveness of each training course; assess the effectiveness of the training programs; | M9: keep and use records of participants; keep and use records of all personnel waived; keep and use records of training course and program effectiveness; make training records available for consideration in asignments;
A10: Standard Questions - explain how / what ? ... | F10: Do you … ? How do you identify training needs? | G10: Do you …? What training records do you maintain? | H10: Do you …? How do you identify strategic training needs? How do you identify short-term training needs? | I10: How are training needs between projects co-ordinated with organisational training needs? (and support functions) | J10: How do you execute the strategic and short-term training plans? | K10: How do you establish and maintain a training capability for the organisation? | L10: How do you assess the effectiveness of the organisation training program? | M10: What org. training records do you establish and maintain?
A11: Questions | F11: 如何识别培训需求？ | G11: 有哪些培训记录？ | H11: 如何确定战略和短期培训需求？ | I11: 项目（和支持职能）的培训需求如何与组织培训需求相协调一致？ | J11: 如何执行战略和短期培训计划？ | K11: 如何建立和维护组织的培训能力？ | L11: 如何评估组织培训计划的有效性？ | M11: 需要建立并维护哪些培训记录
A15: Name | B15: link | C15: engl | D15: \PAs | E15: OT 1.1 | F15: OT 2.1 | G15: OT 2.2 | H15: OT 3.1 | I15: OT 3.2 | J15: OT 3.3 | K15: OT 3.4 | L15: OT 3.5 | M15: OT 3.6
A16: atm to complete | B16: link | C16: =HYPERLINK("01-组织级\02-组织工作库\05-OT培训库\01_公司级培训\03_2022年培训计划\02_年度培训计划\2022培训课程表(ORG_OT_TraininCNSchedule)V1.0-engl.xlsx", "engl") -> engl | E16: x | F16: x | H16: x | J16: x
A17: atm to complete | B17: link | E17: x
A18: atm to complete | B18: link | E18: x
A19: atm to complete | B19: link | C19: =HYPERLINK("01-组织级\02-组织工作库\05-OT培训库\01_公司级培训\03_2022年培训计划\01_培训需求调研\培训需求调研表(ORG_OT_TrainingReqDevTable)V1.1-engl.xlsx", "engl") -> engl | F19: x
A20: atm to complete | B20: link | C20: =HYPERLINK("01-组织级\02-组织工作库\05-OT培训库\04_内部培训讲师培训\06_学员考核评价表\培训内部讲师培训(ORG-OT-TrainingEVVuationlist)V1.0-engl.xlsx", "engl") -> engl | G20: x | I20: x | K20: x | L20: x
A21: atm to complete | B21: link | C21: =HYPERLINK("01-组织级\02-组织工作库\05-OT培训库\02_人力资源库\01_员工信息\员工---岗位知识技能矩阵-engl.xlsx", "engl") -> engl | G21: x | I21: x
A22: atm to complete | B22: link | C22: =HYPERLINK("01-组织级\02-组织工作库\05-OT培训库\02_人力资源库\01_员工信息\员工技术及工作经历一览表(ORG_OT_Skills and Experience List)V1.0-engl.xlsx", "engl") -> engl | G22: x | I22: x
A23: atm to complete | B23: link | C23: =HYPERLINK("01-组织级\02-组织工作库\05-OT培训库\02_人力资源库\02_岗位职责\岗位职责说明书(ORG-OT-T01)V1.0-engl.xlsx", "engl") -> engl | G23: x
A24: atm to complete | B24: link | C24: =HYPERLINK("01-组织级\02-组织工作库\05-OT培训库\01_公司级培训\01_公司战略培训规划\公司战略培训规划(ORG_OT_FutureTraining)V1.0-engl.docx", "engl") -> engl | J24: x
A25: atm to complete | B25: link | C25: =HYPERLINK("01-组织级\02-组织工作库\05-OT培训库\01_公司级培训\03_2022年培训计划\02_年度培训计划\OT-组织培训计划评审记录2022-engl.xlsx", "engl") -> engl | L25: x
A26: atm to complete | B26: link | M26: x

Sheet TV_MC
A1: MC - MONITOR AND CONTROL (MC)
A2: Intent | E2: Provide an understanding of the project progress so appropriate corrective actions can be taken when performance deviates significantly from plans.
A3: Value | E3: Increases the probability of meeting objectives by taking early actions to adjust for significant performance deviations.
E4: Level 1 | G4: Level 2 | K4: Level 3
E5: some measurement in place | G5: achieve full intent; use local measures to analyse performance / data stored / actions taken | K5: use organisational standards and tailoring; contribute improvements; set performance objectives; proactive not reactive
E6: MC 1.1 | F6: MC 1.2 | G6: MC 2.1 | H6: MC 2.2 | I6: MC 2.3 | J6: MC 2.4 | K6: MC 3.1 | L6: MC 3.2 | M6: MC 3.3 | N6: MC 3.4
A7: Practice | E7: Record task completions. | F7: Identify and resolve issues. | G7: Track actual results against estimates for size, effort, schedule, resources, knowledge and skills, and budget. | H7: Track the involvement of identified stakeholders and commitments. | I7: Monitor the transition to operations and support. | J7: Take corrective actions when actual results differ significantly from planned results and manage to closure. | K7: Manage the project using the project plan and the project process. | L7: Manage critical dependencies and activities. | M7: Monitor the work environment to identify issues. | N7: Manage and resolve issues with affected stakeholders.
A8: Example Work Products | E8: task list; - Minutes with completed tasks - Plan with completed tasks | F8: issues and action item list; - Minutes with issues identified | G8: records of actuals vs estimates; records of significant deviations; records of status reviews; corrective actions; cost performance reports; schedule performance reports; | H8: records of stakeholder involvement (meeting attendance registers); agendas and schedules for collaborative activities; recorded issues; recommendations for resolving issues; | I8: status reports of transition activities; transition readiness report; record of transition report reviews; lessons learned report; - Release records - Operation and support acceptance records | J8: list of issues requiring corrective action; - reports showing thresholds exceeded (planned versus actual) | K8: results of monitoring; collected measures and status records or reports; project schedule (actual vs planned); | L8: updated critical dependencies; recorded agendas and meeting minutes; recorded issues; | M8: corrections needed to work env.; - minutes of actions to address work env. Issues; | N8: recorded issues; - relevant stakeholder meeting minutes
A9: Example Activities | E9: record task completion; review updated task list with affected stakeholders; | F9: record the issue in the issue and action list; assign responsibility; assign a due date; track issues and actions; | G9: track actual results to plans and estimates; monitor resources provided and used; monitor knowledge and skills of workgroup; monitor commitments against those id. In plan; record significant differences in planned vs actual; monitor progress against schedule; monitor expended effort and costs; | H9: periodically review and record the status of stakeholder involvement; identify and record significant stakeholder issues; develop recommendations and coordinate actions to resolve issues; | I9: monitor the capabilities of ops and support to receive, store, use and maintain new or modified solns; monitor training delivery to stakeholders; review and analyse the results of transition activities; | J9: collect issues for analysis; analyse issues to decide if corrective action is needed; take corrective action on identified issues; manage corrective actions to closure; | K9: manage the project activities using the project process and all related plans; collect and analyse selected measurements to manage the project and support proj. needs; periodically review and align project performance with org., customer, and end user requirements and objectives; resolve causes of issues affecting project objectives; | L9: review and update dependencies; record minutes from reviews and discussions; record issues; | M9: monitor work environment elements that affect safety, health, effectiveness and productivity and identify and record any corrections needed; monitor physical factors in the work environment that could degrade performance and identify and record corrections needed; identify, recordand report potential work env. issues; take reasonable steps to accommodate work env. issues; remove or reduce interruptions that degrade performance; remove or reduce physical factors that degrade performance; monitor progress of work env. issue resolution; resolve interpersonal problems; | N9: identify and record issues; communicate to stakeholders; escalate issues not resolvable; track issues to closure; communicate status and resolution to stakeholders;
A10: Standard Questions - explain how / what ? ... | F10: - How do you identify and resolve issues? | G10: - Explain how you track actual results achieved against planned values (for size, effort, duration, or cost)? | H10: - How do you check that stakeholders are involved as per the plan? | I10: - How do you monitor the transition of solutions to operations and support? | J10: - When and how do you take corrective actions when actual results differ significantly from planned result? | K10: - Explain how you manage the project using the project plan and the project process? - What monitoring results are addressed in what meetings? | L10: - Explain how you manage critical dependencies? | M10: - How do you identify work environment issues? | N10: - Explain how you manage and resolve issues with affected stakeholders?
A11: Questions | F11: —你如何发现问题并解决问题? | G11: —您如何根据计划的值跟踪实际实现的结果(规模、工作量、持续时间或成本)? | H11: —你如何检查干系人是否按照计划参与进来? | I11: —您如何监督解决方案向运营和支持的转移? | J11: —当实际结果与计划结果有显著差异时，你何时以及如何采取纠正措施? | K11: —你如何使用项目计划和项目过程来管理项目? | L11: —如何管理关键依赖关系? | M11: —你如何识别工作环境问题? | N11: —你如何与受影响的干系人管理和解决问题?
A15: Name | B15: link | C15: engl | D15: \PAs | E15: MC 1.1 | F15: MC 1.2 | G15: MC 2.1 | H15: MC 2.2 | I15: MC 2.3 | J15: MC 2.4 | K15: MC 3.1 | L15: MC 3.2 | M15: MC 3.3 | N15: MC 3.4
A16: atm to complete | B16: link | C16: =HYPERLINK("02-项目级\P2-Qcubic to MySQL数据同步工具 V1.0\01-生存周期\03-项目策划\03-项目计划书 (QCUBIC-SJTB-PLAN-Plan)V1.0-engl.docx", "engl") -> engl | E16: x | K16: x
A17: atm to complete | B17: link | C17: =HYPERLINK("02-项目级\P2-Qcubic to MySQL数据同步工具 V1.0\02-全程管理\01-项目监控\02-项目周报(QCUBIC-SJTB-MC-weeklyrpt)v1.1-engl.xlsx", "engl") -> engl | E17: x | G17: x | H17: x | I17: x | J17: x | K17: x | L17: x | M17: x | N17: x
A18: atm to complete | B18: link | C18: =HYPERLINK("02-项目级\P2-Qcubic to MySQL数据同步工具 V1.0\02-全程管理\01-项目监控\04-里程碑状态报告\01-策划里程碑状态报告(QCUBIC-SJTB-MC-PlanMilestoneRpt)V1.0-engl.docx", "engl") -> engl | E18: x | G18: x | H18: x | I18: x | J18: x | K18: x | L18: x | M18: x | N18: x
A19: atm to complete | B19: link | C19: =HYPERLINK("02-项目级\P2-Qcubic to MySQL数据同步工具 V1.0\02-全程管理\01-项目监控\04-里程碑状态报告\02-需求里程碑状态报告(QCUBIC-SJTB-MC-RDMilestoneRpt)V1.1-engl.docx", "engl") -> engl | E19: x | G19: x | H19: x | I19: x | J19: x | K19: x | L19: x | M19: x | N19: x
A20: atm to complete | B20: link | C20: =HYPERLINK("02-项目级\P2-Qcubic to MySQL数据同步工具 V1.0\02-全程管理\01-项目监控\04-里程碑状态报告\03-设计里程碑状态报告(QCUBIC-SJTB-MC-DesMilestoneRpt)V1.0-engl.docx", "engl") -> engl | E20: x | G20: x | H20: x | I20: x | J20: x | K20: x | L20: x | M20: x | N20: x
A21: atm to complete | B21: link | C21: =HYPERLINK("02-项目级\P2-Qcubic to MySQL数据同步工具 V1.0\02-全程管理\01-项目监控\04-里程碑状态报告\04-编码里程碑状态报告(QCUBIC-SJTB-MC-CodingMilestoneRpt)V1.0-engl.docx", "engl") -> engl | E21: x | G21: x | H21: x | I21: x | J21: x | K21: x | L21: x | M21: x | N21: x
A22: atm to complete | B22: link | C22: =HYPERLINK("02-项目级\P2-Qcubic to MySQL数据同步工具 V1.0\02-全程管理\01-项目监控\04-里程碑状态报告\05-测试里程碑状态报告(QCUBIC-SJTB-MC-TestMilestoneRpt)V1.0-engl.docx", "engl") -> engl | E22: x | G22: x | H22: x | I22: x | J22: x | K22: x | L22: x | M22: x | N22: x
A23: atm to complete | B23: link | C23: =HYPERLINK("02-项目级\P2-Qcubic to MySQL数据同步工具 V1.0\02-全程管理\01-项目监控\04-里程碑状态报告\06-验收里程碑状态报告(QCUBIC-SJTB-MC-VVMilestoneRpt)V1.0-engl.docx", "engl") -> engl | E23: x | G23: x | H23: x | I23: x | J23: x | K23: x | L23: x | M23: x | N23: x
A24: atm to complete | B24: link | C24: =HYPERLINK("02-项目级\P2-Qcubic to MySQL数据同步工具 V1.0\02-全程管理\01-项目监控\01-问题管理表(QCUBIC-SJTB-MC-IssueList)V1.1-engl.xlsx", "engl") -> engl | F24: x | J24: x | K24: x | N24: x
A25: atm to complete | B25: link | C25: =HYPERLINK("02-项目级\P2-Qcubic to MySQL数据同步工具 V1.0\02-全程管理\07-质量保证\01-质量保证计划(QCUBIC-SJTB-PQA-Plan)V1.0-engl.docx", "engl") -> engl | F25: x
A26: atm to complete | B26: link | C26: =HYPERLINK("02-项目级\P2-Qcubic to MySQL数据同步工具 V1.0\02-全程管理\08-配置管理\01-项目配置管理计划 (QCUBIC-SJTB-CM-Plan)V1.0-engl.docx", "engl") -> engl | F26: x
A27: atm to complete | B27: link | G27: x | L27: x
A28: atm to complete | B28: link | C28: =HYPERLINK("02-项目级\P2-Qcubic to MySQL数据同步工具 V1.0\01-生存周期\03-项目策划\01-项目定义过程 (QCUBIC-SJTB-PLAN-PDP)V1.0-engl.xlsx", "engl") -> engl | K28: x

Sheet TV_PLAN
A1: PLAN - PLANNING (PLAN)
A2: Intent | E2: Develop plans to describe what is needed to accomplish the work within the standards and constraints of the organization, including the: Budget, Schedule, Resource demand, capacity and availability, Quality, Functionality requirements, Risks and opportunities; Plans also describe: The work to be performed, Applicable organizational set of standard processes, assets, and tailoring guidelines, Dependencies, Who performs the work, Relationships with other plans, Stakeholders and their role
A3: Value | E3: Optimizes cost, functionality, and quality to increase the likelihood of meeting objectives.
E4: Level 1 | G4: Level 2 | O4: Level 3 | S4: Level 4
E5: some measurement in place | G5: achieve full intent; use local measures to analyse performance / data stored / actions taken | O5: use organisational standards and tailoring; contribute improvements; set performance objectives; proactive not reactive | S5: use measurement and analysis to control/ stabilise/ predict/ identify and reduce variance; set QPPOs to meet Bos
E6: PLAN 1.1 | F6: PLAN 1.2 | G6: PLAN 2.1 | H6: PLAN 2.2 | I6: PLAN 2.3 | J6: PLAN 2.4 | K6: PLAN 2.5 | L6: PLAN 2.6 | M6: PLAN 2.7 | N6: PLAN 2.8 | O6: PLAN 3.1 | P6: PLAN 3.2 | Q6: PLAN 3.3 | R6: PLAN 3.4 | S6: PLAN 4.1
A7: Practice | E7: Develop a list of tasks. | F7: Assign people to tasks. | G7: Develop and keep updated the approach for accomplishing the work. | H7: Plan for the knowledge and skills needed to perform the work. | I7: Based on recorded estimates, develop and keep the budget and schedule updated. | J7: Plan the involvement of identified stakeholders. | K7: Plan transition to operations and support. | L7: Ensure plans are feasible by reconciling available and estimated resources. | M7: Develop the project plan, ensure consistency among its elements, and keep it updated. | N7: Review plans and obtain commitments from affected stakeholders. | O7: Use the organization's set of standard processes and tailoring guidelines to develop, keep updated, and follow the project process. | P7: Develop a plan and keep it updated, using the project process, the organization's process assets, and the measurement repository. | Q7: Identify and negotiate critical dependencies. | R7: Plan for the project environment and keep it updated based on the organization's standards. | S7: Use statistical and other quantitative techniques to develop and keep the project processes updated to enable achievement of the quality and process performance objectives.
A8: Example Work Products | E8: task list; | F8: task list with assignments; | G8: recorded approach to achieve objectives; recorded project lifecycle; | H8: inventory of skills needed; | I8: budget; schedule; resource plan; budget and schedule risks; | J8: stakeholder involvement plan; responsible, accountable, support, consulted, informed (RASCI) table; | K8: plan for transition to operations and support; | L8: revised plan and commitments; | M8: overall project plan; | N8: results of plan reviews; recorded commitments; | O8: the project process; | P8: revised project estimates; project plans; integrated plans; | Q8: critical dependencies; | R8: project resources, facilities, and environment plan; equipment and tools for project; health and safety considerations; installation and operation manuals; user surveys and results; support services; | S8: criteria used to evaluate alternatives for the project; alternative processes; selected defined project process; risk assessment of not achieving projects QPPO's;
A9: Example Activities | E9: develop a list of tasks; review task list with stakeholders; revise list as needed; | F9: assign an individual responsible for each task; assign any additional people to the task; review assignments with assigned individuals; record assignments in task list; | G9: identify the objectives of the approach; identify the approach to achieve the objectives; identify requirements; record business considerations; define project lifecycle; identify major resource needs and constraints; identify stakeholders; record agreements with stakeholders; identify risks; identify safety and security approaches; review project approach with stakeholders; revise approach as needed; | H9: identify knowledge and skills needed to perform the work; determine gaps between needed and held; select methods for providing needed knowledge and skills; incorporate methods in plan; | I9: identify major milestones; identify schedule assumptions; identify constraints; identify task dependencies; identify resources; identify and analyse risks; develop the budget and schedule based on estimates; establish corrective action criteria; | J9: develop a list of stakeholders; identify involvement of each; record when involvement is required; | K9: determine transition scope and objectives; determine transition requirements and criteria; determine approach to transition; develop schedule for transition; determine transition responsibilities and resources including post-transition; determine operations and support training needs; | L9: perform resource leveling to adjust scheduling of tasks and resources; ensure commitments are supported by adequate resources; negotiate commitments with affected stakeholders; | M9: record the project plan; review the project plan with stakeholders; revise the plan as necessary; | N9: ensure individuals review the work they are responsible for; record commitments; review and approve project commitments; | O9: select standard processes that best fit the needs of the project; modify according to tailoring guidelines; use other org. artefacts as appropriate; record the project process; review the project process; revise as necessary; | P9: use tasks and work products as a basis for estimating and planning; use the org. measurement repository to estimate the work; integrate or develop plans; incorporate the definitions of measures and measurement activities; establish obj. entry and exit criteria for tasks; identify how conflicts will be resolved; | Q9: identify each critical dependency; integrate schedules; review and negotiate dependencies; record commitments to address each critical dependency; | R9: analyse project and plan for resources, facilities and environment; assign an individual to plan to acquire resources, facilities and environment; develop a contingency plan; plan for support personnel needs; ensure individuals participate in decisions; | S9: identify the criteria to use in evaluating process alternatives; identify or develop alternative processes; analyse and evaluate alt. processes against criteria; select alt. process; evaluate the risk of not achieving project QPPOs;
A10: Standard Questions - explain how / what ? ... | F10: - Do you assign people to the tasks? | G10: - Do you have a specific approach for doing the work? (waterfall, iterative, agile etc) - What is the approach that you use? | H10: - How do you make sure you have the right knowledge and skills for the task to be performed? | I10: - How do you develop the budget and schedule? | J10: - How do you plan for stakeholder involvement? | K10: - Explain how you plan for transition to operations and support? | L10: - Explain how you ensure your plans are feasible in terms of resource availability and work that needs to be performed? | M10: - What information do you keep in your project plan? - How often do you update / When do you update? | N10: - How do you review the plans with stakeholders? - How do you get commitment to the plans? - Where is it documented? | O10: - Explain how you use the organisational standard processes to develop the plan? - How do you make use of tailoring guidelines to plan? | P10: - How do you use the process, the process assets and the measurement repository to keep your plan updated? | Q10: - Explain how you identify and negotiate any critical dependencies? | R10: - Explain how you plan your project environment? - Do you use org. standards to plan the environment? | S10: - How do you make use of statistical and quantitative techniques to develop and keep the project processes updated to enable achievement of the QPPOs for the project or organisation?
A11: Questions | I11: —你是如何制定预算和项目进度的? | J11: —你如何规划干系人的参与? | K11: —您如何计划向运营和支持的转移? | L11: —你如何确保你的计划在可用资源和待执行的工作方面是可行的? | M11: —你在项目计划中记录了哪些信息? | N11: —你如何与干系人一起评估计划的? -你如何得到对计划的承诺? | O11: —解释一下你是如何利用组织的标准流程来制定计划的? -你如何利用裁剪指南来进行计划? | P11: —您如何使用过程、过程资产和度量存储库来更新您的计划? | Q11: —解释一下你是如何识别和协商任何关键的依赖关系的? | R11: —解释你是如何规划你的项目环境的? -你使用组织标准工作环境来策划项目所需的环境吗? | S11: - How do you make use of statistical and quantitative techniques to develop and keep the project processes updated to enable achievement of the QPPOs for the project or organisation?
A15: Name | B15: link | C15: engl | D15: \PAs | E15: PLAN 1.1 | F15: PLAN 1.2 | G15: PLAN 2.1 | H15: PLAN 2.2 | I15: PLAN 2.3 | J15: PLAN 2.4 | K15: PLAN 2.5 | L15: PLAN 2.6 | M15: PLAN 2.7 | N15: PLAN 2.8 | O15: PLAN 3.1 | P15: PLAN 3.2 | Q15: PLAN 3.3 | R15: PLAN 3.4 | S15: PLAN 4.1
A16: atm to complete | B16: link | E16: x | F16: x | I16: x | J16: x | K16: x | L16: x | M16: x | Q16: x
A17: atm to complete | B17: link | C17: =HYPERLINK("02-项目级\P2-Qcubic to MySQL数据同步工具 V1.0\01-生存周期\03-项目策划\03-项目计划书 (QCUBIC-SJTB-PLAN-Plan)V1.0-engl.docx", "engl") -> engl | F17: x | G17: x | H17: x | L17: x | M17: x | P17: x | Q17: x | R17: x
A18: atm to complete | B18: link | C18: =HYPERLINK("02-项目级\P2-Qcubic to MySQL数据同步工具 V1.0\02-全程管理\05-评审管理\03-计划评审\05-评审报告_项目计划(QCUBIC-SJTB-PR-ReviewRpt)V1.1-engl.xlsx", "engl") -> engl | L18: x | N18: x
A19: atm to complete | B19: link | C19: =HYPERLINK("02-项目级\P2-Qcubic to MySQL数据同步工具 V1.0\01-生存周期\03-项目策划\01-项目定义过程 (QCUBIC-SJTB-PLAN-PDP)V1.0-engl.xlsx", "engl") -> engl | O19: x | P19: x
A20: atm to complete | B20: link | C20: =HYPERLINK("01-组织级\01-组织财富库\01-标准过程文件库\04-组织过程类\02-过程资产管理\裁剪指南 (QCUBIC-SPI-OPAL-Guid-Tailor)V1.2-engl.xlsx", "engl") -> engl | O20: x
A21: atm to complete | B21: link | C21: =HYPERLINK("02-项目级\P2-Qcubic to MySQL数据同步工具 V1.0\02-全程管理\03-度量分析\02-项目度量数据表(QCUBIC-SJTB-MPM-datasheet)V1.0-engl.xlsx", "engl") -> engl | P21: x
A22: atm to complete | B22: link | C22: =HYPERLINK("02-项目级\P2-Qcubic to MySQL数据同步工具 V1.0\01-生存周期\03-项目策划\05-关键依赖关系跟踪管理表(QCUBIC-SJTB-Key dependency tracking management table)V1.0-engl.xlsx", "engl") -> engl | Q22: x

Sheet TV_EST
A1: EST - ESTIMATING
A2: Intent | E2: Estimate the size, effort, duration, and cost of the work and resources needed to develop, acquire, or deliver the solution.
A3: Value | E3: Estimation provides a basis for making commitments, planning, and reducing uncertainty, which allows for early corrective actions and increases the likelihood of meeting objectives.
E4: Level 1 | F4: Level 2 | I4: Level 3
E5: some measurement in place | F5: achieve full intent; use local measures to analyse performance / data stored / actions taken | I5: use organisational standards and tailoring; contribute improvements; set performance objectives; proactive not reactive
E6: EST 1.1 | F6: EST 2.1 | G6: EST 2.2 | H6: EST 2.3 | I6: EST 3.1 | J6: EST 3.2
A7: Practice | E7: Develop high-level estimates to perform the work. | F7: Develop, keep updated, and use the scope of what is being estimated. | G7: Develop and keep updated estimates for the size of the solution. | H7: Based on size estimates, develop and record effort, duration, and cost estimates and their rationale for the solution. | I7: Develop and keep updated a recorded estimation method. | J7: Use the organizational measurement repository and process assets for estimating work.
A8: Example Work Products | E8: high level estimates; | F8: list of tasks or activities or WBS; list of needed resources; work flow diagram; | G8: size estimates; | H8: effort estimate; duration estimate; cost estimate; estimating rationale; | I8: recorded estimation methods; | J8: work estimates; updated org. process assets;
A9: Example Activities | E9: review needs and assumptions and determine high level estimates with stakeholders; | F9: review requirements and objectives with stakeholders to determine scope; | G9: estimate size and complexity of solutions and tasks; | H9: collect and use historical data to develop and calibrate models to transform size and complexity into effort, duration, and cost estimates; describe and record rationale for estimates of effort, duration, and cost; include estimates of supporting infrastructure needs; | I9: determine acceptable estimation methods; calibrate and adjust method based on actual results; validate method; | J9: use org. assets and measures for estimation; use estimation methods; contribute results and measures to improve and update repository; analyse org. data;
A10: Standard Questions - explain how / what ? ... | E10: Do you …? What high level estimates do you make? | F10: Explain how you scope the work? (what to estimate - what is included and what is excluded)? | G10: Explain how you estimate the size of work? (FP, LOC, number of UCs, number of workstations, number of network points, number of data records, etc)? | H10: Explain how you use the size estimates to develop effort, duration and cost estimates? How do you use these estimates to schedule the work? | I10: Explain how your estimation method works? Is this estimation method documented? How do you maintain or improve your estimates? What method do you use? What is it called | J10: Explain how you make use of the org. measurement repository to perform your estimating?
A11: Questions | E11: 你做了什么粗略的估算? | F11: “你是怎么确定估算范围的?” (估算什么——包括什么，不包括什么)? | G11: “你如何估算工作的规模?” (FP, LOC, uc的数量，工作站的数量，网络点的数量，数据记录的数量，等等)? | H11: “如何利用规模估算来估算工作量、工期和成本?” 如何使用这些估算来安排工作? | I11: “解释一下你的评估方法是如何工作的?” 这个估算方法是否有文档记录? 您如何维护或改进您的评估? 你用的是什么方法?叫什么名字? | J11: 你如何利用组织度量存储库来执行您的估算?
A15: Name | B15: link | C15: engl | D15: \PAs | E15: EST 1.1 | F15: EST 2.1 | G15: EST 2.2 | H15: EST 2.3 | I15: EST 3.1 | J15: EST 3.2
A16: atm to complete | B16: link | C16: =HYPERLINK("02-项目级\P2-Qcubic to MySQL数据同步工具 V1.0\01-生存周期\03-项目策划\02-估算工作书 (QCUBIC-SJTB-PLAN-Evaluate)V1.2-engl.xlsx", "engl") -> engl | E16: x | G16: x | H16: x
A17: atm to complete | B17: link | C17: =HYPERLINK("02-项目级\P2-Qcubic to MySQL数据同步工具 V1.0\02-全程管理\03-度量分析\02-项目度量数据表(QCUBIC-SJTB-MPM-datasheet)V1.0-engl.xlsx", "engl") -> engl | F17: x
A18: atm to complete | B18: link | C18: =HYPERLINK("02-项目级\P2-Qcubic to MySQL数据同步工具 V1.0\01-生存周期\03-项目策划\03-项目计划书 (QCUBIC-SJTB-PLAN-Plan)V1.0-engl.docx", "engl") -> engl | F18: x
A19: atm to complete | B19: link | C19: =HYPERLINK("02-项目级\P2-Qcubic to MySQL数据同步工具 V1.0\02-全程管理\01-项目监控\03-周会议纪要\01-会议记录(QCUBIC-SJTB-meetingrcd-20220107)V1.0-engl.docx", "engl") -> engl | H19: x
A20: atm to complete | B20: link | C20: =HYPERLINK("01-组织级\01-组织财富库\01-标准过程文件库\01-项目管理规范\03-项目估算\估算指南(QCUBIC-SPI-EST-Guid-Evaluate)V1.2-engl.docx", "engl") -> engl | I20: x
A21: atm to complete | B21: link | C21: =HYPERLINK("01-组织级\02-组织工作库\06-度量\组织度量表(QCUBIC-SPI-MPM-Tem-datasheet)V1.3-engl.xlsx", "engl") -> engl | J21: x
A22: atm to complete | B22: link | J22: x

Sheet TV_CAR
A1: CAR - CAUSAL ANALYSIS AND RESOLUTION (CAR)
A2: Intent | E2: Identify causes of selected outcomes and take action to either prevent recurrence of undesirable outcomes or ensure recurrence of positive outcomes.
A3: Value | E3: Addressing root cause issues eliminates rework and directly improves quality and productivity.
E4: Level 1 | F4: Level 2 | H4: Level 3 | M4: Level 4 | O4: Level 5
E5: some measurement in place | F5: achieve full intent; use local measures to analyse performance / data stored / actions taken | H5: use organisational standards and tailoring; contribute improvements; set performance objectives; proactive not reactive | M5: use measurement and analysis to control/ stabilise/ predict/ identify and reduce variance; set QPPOs to meet Bos | O5: use stat. analysis to optimise performance and improvement to achieve the QPPO's, business objectives and strategy
E6: CAR 1.1 | F6: CAR 2.1 | G6: CAR 2.2 | H6: CAR 3.1 | I6: CAR 3.2 | J6: CAR 3.3 | K6: CAR 3.4 | L6: CAR 3.5 | M6: CAR 4.1 | N6: CAR 4.2 | O6: CAR 5.1
A7: Practice | E7: Identify and address causes of selected outcomes. | F7: Select outcomes for analysis. | G7: Analyse and address causes of outcomes. | H7: Determine root causes of selected outcomes by following an organizational process. | I7: Propose actions to address identified root causes. | J7: Implement selected action proposals. | K7: Record root cause analysis and resolution data. | L7: Submit improvement proposals for changes proven to be effective. | M7: Perform root cause analysis of selected outcomes using statistical and other quantitative techniques. | N7: Evaluate the effect of implemented actions on process performance using statistical and other quantitative techniques. | O7: Use statistical and other quantitative techniques to evaluate other solutions and processes to determine if the resolution should be applied on a broader scale.
A8: Example Work Products | E8: list of investigated outcomes; | F8: analysis results; outcomes selected for further analysis; | G8: list of stakeholders; identified causes; actions to take; | H8: list of root causes; list of affected stakeholders; | I8: action proposals; | J8: selected action proposals; action plans; updated process assets; grouped common causes; | K8: root cause analysis and resolution records; | L8: improvement proposals | M8: process and project performance analyses; identified root causes; identified measures of effectiveness; action plans; updated solns. or processes; | N8: analysis of change in process performance; org. improvement proposals; | O8: identified candidate processes and solns.; results of changes; process control charts before and after proposal;
A9: Example Activities | E9: select outcomes that differed from expectation; investigate causes of outcomes; address causes and record changes made to address causes; | F9: define the scope of the analysis; collect relevant data; determine which outcomes to analyse further; | G9: identify the affected stakeholders and involve them; perform causal analysis; implement actions to address causes; assess the impact of the actions taken; communicate the results; | H9: identify stakeholders; collect data; follow an org. process for root cause analysis; record the root causes; | I9: develop an action proposal; record action proposals; | J9: analyse action proposals and determine their priorities; select action proposals to be implemented; develop action plans for implementation; implement action plans; look for similar root causes and take action; | K9: record root cause analysis data and make available; | L9: submit improvement proposals -> DAR | M9: use control charts to identify signals; perform root cause analysis; identify and analyse potential actions; identify measures of effectiveness; implement selected actions; | N9: measure and analyse the change in process performance of affected processes; determine the impacts of the change on proj. QPPOs; submit process improvement proposals for the org.; | O9: identify similar processes or solutions; analyse to determine candidates for change and prioritise; apply changes to selected processes and communicate results;
A10: Standard Questions - explain how / what ? ... | E10: - Do you have a list of outcomes (opportunities or defects) to investigate? | F10: - Can you provide us with a list of outcomes (opportunity/defects) for analysis? | G10: - Do you have a list of causes (for outcomes) identified in analysis? - Do you have a list of actions to address the causes identified? | H10: - What is the process you follow to determine root causes? | I10: - What actions have you identified to address causes? | J10: - How do you select actions proposals to address identified causes? | K10: - What data is recorded about root cause resolution? | L10: - What root cause improvement proposals have been submitted and implemented? | M10: - What statistical and other quantitative methods are used to perform root cause analysis? | N10: - What process performance measures have been used to demonstrate the causal analysis action proposal(s) where effective in achieving the process performance objectives? | O10: - Have you implemented the action proposal organisationally? If yes, how did you measure if it was effective?
A11: Questions | E11: —你是否有一系列结果(机会或缺陷)需要调查? | F11: —您能提供一份结果(机会/缺陷)列表供我们分析吗? | G11: ’—在分析中，你是否有一份原因(结果)列表? 你是否有一系列针对已确定的原因的行动? | H11: —你是如何确定根本原因的? | I11: ——你确定了哪些行动来解决问题? | J11: —你如何选择行动建议来解决已识别的原因? | K11: ’—记录了关于根本原因解决的哪些数据? | L11: 已提交并实施了哪些根本原因的改进建议? | M11: - What statistical and other quantitative methods are used to perform root cause analysis? | N11: - What process performance measures have been used to demonstrate the causal analysis action proposal(s) where effective in achieving the process performance objectives? | O11: - Have you implemented the action proposal organisationally? If yes, how did you measure if it was effective?
A15: Name | B15: link | C15: engl | D15: \PAs | E15: CAR 1.1 | F15: CAR 2.1 | G15: CAR 2.2 | H15: CAR 3.1 | I15: CAR 3.2 | J15: CAR 3.3 | K15: CAR 3.4 | L15: CAR 3.5 | M15: CAR 4.1 | N15: CAR 4.2 | O15: CAR 5.1
A16: atm to complete | B16: link | C16: =HYPERLINK("01-组织级\02-组织工作库\06-度量\原因分析和解决方案报告(QCUBIC-SPI-CAR_Data quality analysis)V1.0-engl.xlsx", "engl") -> engl | E16: x | F16: x | G16: x | H16: x | I16: x | J16: x | K16: x | L16: x
A17: atm to complete | B17: link | C17: =HYPERLINK("01-组织级\01-组织财富库\01-标准过程文件库\03-支持类\07-原因分析和解决过程\原因分析和解决过程(QCUBIC-SPI-CAR_Pro)V1.2-engl.docx", "engl") -> engl | E17: x | F17: x | G17: x | H17: x | I17: x | J17: x | K17: x | L17: x

Sheet TV_DAR
A1: DAR - DECISION ANALYSIS AND RESOLUTION (DAR)
A2: Intent | E2: Make and record decisions using a recorded process that analyzes alternatives.
A3: Value | E3: Increases the objectivity of decision making and the probability of selecting the optimal solution.
E4: Level 1 | G4: Level 2 | L4: Level 3
E5: some measurement in place | G5: achieve full intent; use local measures to analyse performance / data stored / actions taken | L5: use organisational standards and tailoring; contribute improvements; set performance objectives; proactive not reactive
E6: DAR 1.1 | F6: DAR 1.2 | G6: DAR 2.1 | H6: DAR 2.2 | I6: DAR 2.3 | J6: DAR 2.4 | K6: DAR 2.5 | L6: DAR 3.1
A7: Practices | E7: Define and record the alternatives. | F7: Make and record the decision. | G7: Develop, keep updated, and use rules to determine when to follow a recorded process for criteria-based decisions. | H7: Develop criteria for evaluating alternatives. | I7: Identify alternative solutions. | J7: Select evaluation methods. | K7: Evaluate and select solutions using criteria and methods. | L7: Develop, keep updated, and use a description of role-based decision authority.
A8: Example Work Products | E8: statement of the alternatives; | F8: record of decisions; | G8: rules and guidelines for cbdm (DAR guidelines); list of recorded criteria based decisions; (DAR points can be specified within a process); | H8: recorded evaluation criteria; | I8: recorded alternatives; | J8: selected evaluation methods; | K8: evaluation results; assessed risks; recommended solutions; | L8: list of roles and decision-making authority and responsibilities (SODA?); list of decision authority levels;
A9: Example Activities | E9: define the alternatives; involve stakeholders in defining alternatives; | F9: make and record the decision; | G9: develop and record rules and guidelines for when to use criteria based decision making (cbdm); follow rules and guidelines for cbdm; communicate rules and guidelines; | H9: define criteria for evaluating alternative solutions; define, use, and update the range and weighting for evaluation criteria; | I9: research information about similar decisions (internal or external); identify additional alternatives; record selected alternatives; | J9: select evaluation methods; | K9: evaluate alternatives using the cbdm process; record results; assess risks of implementation; record and communicate results for recommended solution; | L9: identify, record, update and communicate the roles and levels of decision making authority;
A10: Standard Questions - explain how / what ? ... | E10: - Do you define and record alternative options (in the process he/she execute)? | F10: - Do you make and record the decisions on options selected (in the process he/she executes)? | G10: - Do you have a set of rules that determine when to follow a recorded process for criteria-based decision making? | H10: - At these DAR decision points of your process, how do you develop criteria for evaluating alternatives? | I10: - At these DAR decision points, what alternatives have you identified? | J10: - At these DAR decision points, what evaluation methods for making a decision have been used? | K10: - At these DAR decision points, what decision have you made? Was this based on the alternatives, criteria and decision methods specified previously? | L10: - Explain role-based decision authority in your organisation?
A11: Questions | E11: 你是否(在执行的过程中)定义并记录其他备选方案? | F11: “-（在执行的过程中），你是否对所选择的选项做出决定并记录下来?” | G11: —你是否有一套规则来决定什么时候应该遵循基于标准的决策过程? | H11: ’—在你们流程的DAR决策点，你们如何制定评估备选方案的标准? | I11: ’—在DAR决策点，你们确定了哪些备选方案? | J11: “在DAR决策点，采用了哪些评估方法来做决策?” | K11: 在DAR决策点，你做了什么决定?这是基于上述的备选方案、标准和决策方法吗? | L11: —解释一下你的组织中基于角色的决策主体?
A15: Name | B15: link | C15: engl | D15: \PAs | E15: DAR 1.1 | F15: DAR 1.2 | G15: DAR 2.1 | H15: DAR 2.2 | I15: DAR 2.3 | J15: DAR 2.4 | K15: DAR 2.5 | L15: DAR 3.1
A16: atm to complete | B16: link | C16: =HYPERLINK("01-组织级\02-组织工作库\02-EPG活动库\08-决策分析\01-决策分析报告（QCUBIC-SPI-dar-evaluaterpt)V1.0-engl.xlsx", "engl") -> engl | E16: x | F16: x | G16: x | H16: x | I16: x | J16: x | K16: x | L16: x
A17: atm to complete | B17: link | C17: =HYPERLINK("01-组织级\01-组织财富库\01-标准过程文件库\03-支持类\04-决策分析\决策分析和解决方案(QCUBIC-SPI-OPAL-Tem-Proc)V1.2-engl.docx", "engl") -> engl | G17: x | H17: x | L17: x

Sheet TV_CM
A1: CM - CONFIGURATION MANAGEMENT (CM)
A2: Intent | E2: Manage the integrity of work products using configuration identification, version control, change control, and audits.
A3: Value | E3: Reduces loss of work and increases the ability to deliver the correct version of the solution to the customer.
E4: Level 1 | F4: Level 2
E5: some measurement in place | F5: achieve full intent; use local measures to analyse performance / data stored / actions taken
E6: CM 1.1 | F6: CM 2.1 | G6: CM 2.2 | H6: CM 2.3 | I6: CM 2.4 | J6: CM 2.5 | K6: CM 2.6
A7: Practice | E7: Perform version control. | F7: Identify items to be placed under configuration management. | G7: Develop, keep updated, and use a configuration and change management system. | H7: Develop or release baselines for internal use or for delivery to the customer. | I7: Manage changes to the items under configuration management. | J7: Develop, keep updated, and use records describing items under configuration management. | K7: Perform configuration audits to maintain the integrity of configuration baselines, changes, and content of the configuration management system.
A8: Example Work Products | E8: list of work products and their versions; | F8: identified Configuration Items (with details) | G8: configuration mgt (CM) system; change mgt system; updated CIs; | H8: baseline; software releases; authorisations; | I8: change requests; results of change impact analysis; approval board record - CCB minutes; revision history of CIs; results of reviews or tests; revised work products and baselines; | J8: revision history or change log of CIs; change request records; status of CIs; differences between baselines; | K8: configuration audit or review reports; action items;
A9: Example Activities | E9: list work products to be place under version control, update; control the versions; | F9: assign unique identifiers to CIs; describe important characteristics for each CI; specify when each item is placed under CM; | G9: describe how CIs and changes are controlled and managed; establish methods to manage multiple levels of control; provide access control to CM system; store and retrieve CIs in the CM system; preserve the contents of the CM system; update the CM system as necessary; | H9: obtain approval before developing or releasing CI baselines; develop or release CI baselines in the system; record the set of CI s in a baseline; make the CI baselines available; | I9: initiate and record change requests; analyse the impact of change requests; categorise and prioritise CRs; review and get agreement on CRs; track the status of CRs; incorporate changes; perform reviews or testing; record changes; | J9: record CM actions in sufficient detail; ensure stakeholders have access to status of CIs; specify differences previous, related and latest baselines; identify the version of CI that constitutes a specific baseline; revise status and history of CIs; establish and maintain configuration change histories on CIs; | K9: assess the integrity of baselines and generate actions to address issues; confirm integrity of CM records; review structure and integrity of CIs; record and track actions;
A10: Standard Questions - explain how / what ? ... | E10: - Describe how you perform version control. | F10: - What items are put under configuration management? - How do you identify what items to put under configuration management? | G10: - What configuration management system(s) do you have? | H10: - Explain how you establish software baselines for further development? What authorisations are required before release? - Explain how you establish software releases that form the basis for further development? What baselines do they develop and release - software, project work products, process … ? | I10: - How do you manage changes to items under configuration management? | J10: - What records do you maintain on configuration items? | K10: - How do you ensure the integrity of items under configuration management? - How do you ensure the integrity of baselines and the integrity of releases? How do you conduct audits, what audits are conducted?
A11: Questions | F11: —配置管理下有哪些配置项? —如何识别需要进行配置管理的配置项? | G11: 你有什么配置管理系统? | H11: —解释一下你是如何为进一步的开发建立软件基线的? 解释一下你是如何建立软件发行版的，这些发行版是进一步开发的基础? | I11: —如何在配置管理下管理对配置项的更改? | J11: —就配置项，您记录了哪些记录 | K11: —如何确保配置管理下配置项的完整性? -你如何确保基线和发布版本的完整性?
A15: Name | B15: link | C15: engl | D15: \PAs | E15: CM 1.1 | F15: CM 2.1 | G15: CM 2.2 | H15: CM 2.3 | I15: CM 2.4 | J15: CM 2.5 | K15: CM 2.6
A16: atm to complete | B16: link | C16: =HYPERLINK("01-组织级\02-组织工作库\04-CM活动库\组织级配置管理计划(QCUBIC-SPI-CM-OCMPlan)V1.2-engl.xlsx", "engl") -> engl | E16: x | F16: x | G16: x | I16: x | J16: x
A17: atm to complete | B17: link | C17: =HYPERLINK("01-组织级\02-组织工作库\04-CM活动库\组织配置库内容列表(ORG_-CM-TEM-PALList)V1.2-engl.xlsx", "engl") -> engl | E17: x | J17: x
A18: atm to complete | B18: link | C18: =HYPERLINK("01-组织级\01-组织财富库\01-标准过程文件库\03-支持类\02-配置管理\配置管理过程文件(QCUBIC-SPI-CM-Proc-Doc)V1.2-engl.docx", "engl") -> engl | G18: x | I18: x
A19: atm to complete | B19: link | C19: =HYPERLINK("01-组织级\02-组织工作库\04-CM活动库\基线发布报告 (QCUBIC-spi-cm-release)V1.1-engl.xlsx", "engl") -> engl | H19: x
A20: atm to complete | B20: link | C20: =HYPERLINK("01-组织级\02-组织工作库\04-CM活动库\组织级配置审计报告(QCUBIC-SPI-CM-Organization-level configuration audit report)V1.3-engl.xlsx", "engl") -> engl | K20: x

Sheet TV_II
A1: II - IMPLEMENTATION INFRASTRUCTURE (II)
A2: Intent | E2: Ensure that the processes important to an organization are persistently and habitually used and improved.
A3: Value | E3: Sustains the ability to consistently achieve goals and objectives efficiently and effectively.
E4: Level 1 | F4: Level 2 | H4: Level 3
E5: some measurement in place | F5: achieve full intent; use local measures to analyse performance / data stored / actions taken | H5: use organisational standards and tailoring; contribute improvements; set performance objectives; proactive not reactive
E6: II 1.1 | F6: II 2.1 | G6: II 2.2 | H6: II 3.1 | I6: II 3.2 | J6: II 3.3
A7: Practice | E7: Perform processes that address the intent of the Level 1 practices. | F7: Provide sufficient resources, funding, and training for developing and performing processes. | G7: Develop and keep processes updated, and verify they are being followed. | H7: Use organizational processes and process assets to plan, manage, and perform the work. | I7: Evaluate the adherence to and effectiveness of the organizational processes. | J7: Contribute process-related information or process assets to the organization.
A8: Example Work Products | E8: outputs of processes; process compliance check; | F8: budget for resources; training materials, records; list of people, roles, skills; Process Group (EPG); tools; | G8: process documentation; process verification results; | H8: tailored process; organisational process assets; tailoring guidelines; | I8: evaluation results; analysis results; improvement proposals; process compliance audit | J8: examples, best practices, lessons learned; tailoring records; process improvements registered;
A9: Example Activities | E9: processes are performed (can be ad-hoc); | F9: make budget available for a process group; establish a process group structure; | G9: identify process purpose; determine format; describe process; perform process; validate process is followed; review and update processes; communicate and make available; | H9: plan work using org. processes (includes tailoring); manage work using org. processes; perform work using org. processes; | I9: evaluate processes for effectiveness and usefulness; analyse process pereformance; examine results of evaluations, appraisals, audits; record and communicate results; submit improvements; | J9: collect and record best practice, lessons learned, and tailoring info.; submit assets for inclusion in the PAL; propose improvements;
A10: Standard Questions - explain how / what ? ... | E10: -Do you follow a process? - How can this be shown? | F10: -What resources are made available for developing process? (people, budget, tools) -How do you find out about the processes in the process library? -What happens if there are new processes or process updates? -Is refresher training provided on the processes? (there may be small changes that have been put in place over a period of time)? How often have you received refresher training? | G10: - What process(es) do you follow? - Are they all documented? - Who checks that the processes are followed correctly? and templates are filled in correctly? | H10: - Do you have a standard process for doing your work? - How do you apply the process in your work? Escalation rules? | I10: - How is compliance to the processes checked? | J10: - Do you submit process improvements to the processes that you follow? - If so how? - How do you know what process improvement suggestions have been submitted to the processes that you follow? Lessons learned?
A11: Questions | F11: 开发过程中可用的资源是什么?(人、预算工具) 你如何找到过程库中的过程? 如果有新的过程或过程更新怎么办? 是否提供有关过程的进修培训?(在一段时间内可能会有一些小的改变)? 你多久接受一次进修训练? | G11: 你遵循什么流程? 都得到了记录吗？ 谁来检查您是否正确遵守了流程、正确使用了模板？ | H11: —你是否有一个标准的工作流程? 在工作中你是如何运用这个过程的? 升级规则? | I11: —如何检查流程的合规性? | J11: —您是否向您所遵循的流程提交流程改进? 是的话，怎么提交的？ 你如何知道哪些过程改进建议已经提交给你所遵循的过程? 经验教训呢？
F12: What training on writing / developing new processes? | H12: How easy is it to find the processes? | J12: Do you know what the process is to submit process improvement suggestions?
F13: Are you trained on the concepts / requirements of high maturity? SPC
A15: Name | B15: link | C15: engl | D15: \PAs | E15: II 1.1 | F15: II 2.1 | G15: II 2.2 | H15: II 3.1 | I15: II 3.2 | J15: II 3.3
A16: atm to complete | B16: link | E16: x | G16: x | H16: x | J16: x
A17: atm to complete | B17: link | C17: =HYPERLINK("02-项目级\P3-主从数据库复制及性能提升项目\01-生存周期\03-项目策划\03-项目计划书 (QCUBIC-XNTS-PLAN-Plan)V1.1-engl.docx", "engl") -> engl | E17: x | F17: x
A18: atm to complete | B18: link | C18: =HYPERLINK("02-项目级\P1-Qcubic数据库管理工具 V1.0\01-生存周期\03-项目策划\03-项目计划书 (QCUBIC-SJKGL-PLAN-Plan)V1.1-engl.docx", "engl") -> engl | E18: x | F18: x
A19: atm to complete | B19: link | C19: =HYPERLINK("02-项目级\P2-Qcubic to MySQL数据同步工具 V1.0\01-生存周期\03-项目策划\03-项目计划书 (QCUBIC-SJTB-PLAN-Plan)V1.0-engl.docx", "engl") -> engl | E19: x | F19: x
A20: atm to complete | B20: link | C20: =HYPERLINK("01-组织级\02-组织工作库\02-EPG活动库\03-过程改进计划\过程改进计划(QCUBIC-SPI-PIM-PIPlan)V1.2-engl.docx", "engl") -> engl | F20: x
A21: atm to complete | B21: link | C21: =HYPERLINK("01-组织级\02-组织工作库\03-PQA活动库\组织级不符合项管理表(QCUBIC-SPI-PQA-NCList)V1.2-engl.xlsx", "engl") -> engl | G21: x | I21: x
A22: atm to complete | B22: link | C22: =HYPERLINK("01-组织级\02-组织工作库\06-度量\组织度量表(QCUBIC-SPI-MPM-Tem-datasheet)V1.3-engl.xlsx", "engl") -> engl | I22: x
A23: atm to complete | B23: link | C23: =HYPERLINK("01-组织级\02-组织工作库\02-EPG活动库\过程改进总结报告-engl.pptx", "engl") -> engl | I23: x
A24: atm to complete | B24: link | C24: =HYPERLINK("01-组织级\02-组织工作库\02-EPG活动库\07-EPG跟踪\05-过程改进建议表\过程改进建议表(QCUBIC-SPI-PIM-SPIAdvic)V1.2-engl.xlsx", "engl") -> engl | J24: x

Sheet TV_GOV
A1: GOV - GOVERNANCE (GOV)
A2: Intent | E2: Provides guidance to senior management on their role in the sponsorship and governance of process activities.
A3: Value | E3: Minimizes the cost of process implementation, increases the likelihood of meeting objectives, and ensures that the implemented processes support and contribute to the success of the business.
E4: Level 1 | F4: Level 2 | J4: Level 3 | L4: Level 4
E5: some measurement in place | F5: achieve full intent; use local measures to analyse performance / data stored / actions taken | J5: use organisational standards and tailoring; contribute improvements; set performance objectives; proactive not reactive | L5: use measurement and analysis to control/ stabilise/ predict/ identify and reduce variance; set QPPOs to meet Bos
E6: GOV 1.1 | F6: GOV 2.1 | G6: GOV 2.2 | H6: GOV 2.3 | I6: GOV 2.4 | J6: GOV 3.1 | K6: GOV 3.2 | L6: GOV 4.1
A7: Practice | E7: Senior management identifies what is important for doing the work and defines the approach needed to accomplish the objectives of the organization. | F7: Senior management defines, keeps updated, and communicates organizational directives for process implementation and improvement based on organization needs and objectives. | G7: Senior management ensures resources and training are provided for developing, supporting, performing, improving, and evaluating adherence to expected processes. | H7: Senior management identifies their information needs, and uses the collected information to provide governance and oversight of effective process implementation and improvement. | I7: Senior management holds people accountable for adhering to organization directives and achieving process implementation and improvement objectives. | J7: Senior management ensures that measures supporting objectives throughout the organization are collected, analysed, and used. | K7: Senior management ensures that competencies and processes are aligned with the objectives of the organization. | L7: Senior management ensures that selected decisions are driven by statistical and quantitative analysis related to performance and achievement of quality and process performance objectives.
A8: Example Work Products | E8: identification of importance of and approach to improvement; records of review and communications (improvement approach/strategy); (improvement targets); | F8: org. improvement directives; records of communication; | G8: recorded allocation of needed funding and resources approved by snr mgt.; records of reviews of communications; | H8: snr. mgt. information needs; standard reporting format or agenda for review with snr mgt; list of measures; review results; | I8: action items related to accountability; rewards, recognitions, and incentives; consequences; | J8: updated organisation measurement repository; status reports, actions and decisions; updated org. directives and objectives; | K8: results of strategy and process reviews and discussions; reviews and comparisons between the organisations competencies and processes to be executed; | L8: results of strategy, process performance, and progress reviews and decision analyses; communicated results;
A9: Example Activities | E9: determine how the organisation will improve; set the approach for improvement; 'communicate the results of improvement; | F9: define org. directives based on guiding principles; review and refine process implementation and improvement objectives to ensure alignment with guiding principles; communicates improvement directives; reviews and updates improvement directives on a periodic basis; | G9: approves and provides funding and resources needed to develop, perform, improve and monitor the process; reviews, revises, communicates, assignment of needed funding, personnel, and resources to develop, perform, improve and monitor the process; review and refine the allocation of budget and resources; | H9: identifies and updates their information needs realted to process capability, improvement, and perf. Objectives; ensure that measures supporting the org. objectives are defined; reviews activities, accomplishments, status, and results of process implementation and improvement activities; oversee updates to the process; implementation and improvement plans; oversees the appropriate integration of measurement and analysis activities into all org. processes; | I9: reviews issues and trends related to deploying and improving org. processes; directs corrective actions when - org. obj. not met, issues identified, implementation and improvement progress deviates from plan; provides incentives for improvement; | J9: ensures measures are collected, analysed and used; directs corrective actions relating to collecting, analysing, and using measures; | K9: review the status of competencies, objectives and processes (alignment); record and communicate results; | L9: review and discuss strategy, process performance, decisions and progress; record and communicate results;
A10: Standard Questions - explain how / what ? ... | E10: * How does senior management identify what is important for doing work? * How does senior management define the approach needed to accomplish the objectives of the organisation? | F10: *How do senior management communicate organisational process improvement objectives to you? * What organisational objectives have senior management defined and communicated? - QPPOs *Are these objectives to be achieved through process improvements? | G10: * What resources and training have you (senior management) provided for 1) developing, supporting, 2) performing, 3) improving and 4) evaluating adherence to expected processes? * How do you/they assess what is needed? * How do you/they provide resources and training? | H10: *How do senior management provide governance and oversight of the implementation of effective process improvements? * How do senior management obtain oversight of effective process implementation and improvement and provide governance? | I10: * How do senior management hold people/you accountable for the achievement of process improvement objectives? * cash bonus driven - to what level? * what level of decision authority does a PM normally have? eg. resourcing, hardware, budget and spend * Is this information stored somewhere? authority levels set at certain cost amounts | J10: * How do senior management ensure that measures supporting objectives are collected, analysed and used? * How do senior management ensure that the measures supporting organisational objectives are collected and used? *what role does SM play in ensuring alignment between business strategy, business objectives and process performance objctives * What process performance objective measurements do you collect for senior management? | K10: *How do senior management ensure that competencies and processes align with the goals of the organisation? * How do senior management ensure that competencies and processes align with the goals of the organisation? - technical - behavioural *do senior management have kpis that directly reflect the process performance and improvement targets? *If so, can you describe one or more functions and their targets? *what accountability does senior management have for the performance and improvement of key processes | L10: *How do senior management ensure that selected (key or important business) decisions are driven by statistical and quantitative analysis? *to what extent do you use statistical analysis to set objectives? and *to measure achievement of objectives? - How do you use the statistical analysis provided to senior management to set your objectives? and *to measure the achievement of your objectives? '*what process performance measurement and analysis is reported at an executive level? And how often?
A11: Questions | E11: “*高级管理层如何确定工作中什么是重要的?” *高级管理层如何定义实现组织目标所需的方法? | F11: “*高层管理人员如何向你传达组织过程改进目标?” *高级管理层确定并传达了哪些组织目标? *这些目标是通过过程改进来实现的吗? | G11: 你(高级管理层)提供了什么资源和培训 1)开发、支持、 2)执行, 3)改善和 4)评估对预期过程的坚持? 你/他们如何评估需要什么? 你/他们如何提供资源和培训? | H11: *高级管理层如何提供治理和监督有效流程改进的实施? *高级管理层如何监督有效的过程实施和改进，并提供治理? | I11: *高级管理层如何让员工/你对过程改进目标的实现负责?” 现金奖金驱动-到什么水平? *项目经理通常拥有什么样的决策权? 如资源，硬件，预算和支出 *这些信息是否存储在某个地方? 权力级别按一定的成本数额设定 | J11: “*高级管理层如何确保收集、分析和使用支持目标的度量项? “*高级管理层如何确保收集、分析和使用支持组织目标的度量项? 高层在确保业务战略、业务目标和过程性能目标之间的一致方面扮演什么角色 *您为高级管理层收集了哪些过程绩效目标度量数据? | K11: “*高级管理层如何确保能力和流程与组织的目标相一致?” *高级管理层如何确保能力和流程与组织的目标相一致? ——技术 ——行为 *高级管理层是否有直接反映过程绩效和改进目标的kpi ? *如果有，你能描述一个或多个功能及其目标吗? *高级管理层对关键流程的绩效和改进负有什么责任 | L11: *How do senior management ensure that selected (key or important business) decisions are driven by statistical and quantitative analysis? *to what extent do you use statistical analysis to set objectives? and *to measure achievement of objectives? - How do you use the statistical analysis provided to senior management to set your objectives? and *to measure the achievement of your objectives? '*what process performance measurement and analysis is reported at an executive level? And how often?
A15: Name | B15: link | C15: engl | D15: \PAs | E15: GOV 1.1 | F15: GOV 2.1 | G15: GOV 2.2 | H15: GOV 2.3 | I15: GOV 2.4 | J15: GOV 3.1 | K15: GOV 3.2 | L15: GOV 4.1
A16: atm to complete | B16: link | C16: =HYPERLINK("01-组织级\01-组织财富库\01-标准过程文件库\04-组织过程类\02-过程资产管理\组织方针 (QCUBIC-SPI-OPAL-Ply-Doc)V1.2-engl.docx", "engl") -> engl | E16: x | F16: x
A17: atm to complete | B17: link | C17: =HYPERLINK("01-组织级\02-组织工作库\02-EPG活动库\03-过程改进计划\过程改进计划(QCUBIC-SPI-PIM-PIPlan)V1.2-engl.docx", "engl") -> engl | G17: x
A18: atm to complete | B18: link | C18: =HYPERLINK("01-组织级\02-组织工作库\05-OT培训库\01_公司级培训\03_2022年培训计划\02_年度培训计划\2022培训课程表(ORG_OT_TraininCNSchedule)V1.0-engl.xlsx", "engl") -> engl | G18: x
A19: atm to complete | B19: link | G19: x
A20: atm to complete | B20: link | G20: x
A21: atm to complete | B21: link | H21: x | I21: x
A22: atm to complete | B22: link | C22: =HYPERLINK("01-组织级\02-组织工作库\02-EPG活动库\过程改进总结报告-engl.pptx", "engl") -> engl | H22: x | I22: x | K22: x
A23: atm to complete | B23: link | C23: =HYPERLINK("01-组织级\02-组织工作库\02-EPG活动库\07-EPG跟踪\06-过程改进里程碑\过程改进里程碑报告(ORG_PCM_Milestone_20220628)V1.0-engl.docx", "engl") -> engl | H23: x | I23: x
A24: atm to complete | B24: link | C24: =HYPERLINK("01-组织级\02-组织工作库\06-度量\组织度量表(QCUBIC-SPI-MPM-Tem-datasheet)V1.3-engl.xlsx", "engl") -> engl | H24: x | I24: x | J24: x | K24: x
A25: atm to complete | B25: link | C25: =HYPERLINK("01-组织级\02-组织工作库\06-度量\组织度量计划(QCUBIC-SPI-MPM-Plan)V1.3-engl.xlsx", "engl") -> engl | H25: x | I25: x | J25: x | K25: x
A26: atm to complete | B26: link | C26: =HYPERLINK("01-组织级\02-组织工作库\03-PQA活动库\组织级的质量保证计划(QCUBIC-SPI-PQA-OQAPlan)V1.4-engl.xlsx", "engl") -> engl | I26: x

Sheet Tables
B2: FM | C2: Fully Meets | E2: Adequate OE is judged sufficient to demonstrate that the intent and value of the practice is met, and no weaknesses are identified.
B3: LM | C3: Largely Meets | E3: Adequate OE is judged sufficient to demonstrate that the intent and value of the practice is met, and one or more weaknesses are identified.
B4: PM | C4: Partially Meets | E4: Some or all OE are absent or judged to be inadequate, but other OE suggests that limited aspects of the intent and value of the practice are met, and one or more weaknesses are identified. || Conflicts are identified in the OE, and one or more weaknesses are identified.
B5: DM | C5: Does Not Meet | E5: Some or all OE are absent or judged to be inadequate to demonstrate that the intent and value of the practice is met, and one or more weaknesses are identified.
B6: NY | C6: Not Yet | E6: OE for the sampled projects and organizational support functions indicates that the planned sequence of work has not been reached yet, to have implemented processes that meet the intent and value of the practice.
B9: Y | C9: Yes
B10: N | C10: No
B11: NR
A16: 1 | B16: None | D16: =_xlfn.CONCAT(A16, ". ", B16) -> 1. None | E16: 1 | F16: None | H16: =_xlfn.CONCAT(E16, ". ", F16) -> 1. None | I16: 1 | J16: None | L16: =_xlfn.CONCAT(I16, ". ", J16) -> 1. None | M16: 1 | N16: None | P16: =_xlfn.CONCAT(M16, ". ", N16) -> 1. None
A17: 2 | B17: Pieter van Zyl | D17: =_xlfn.CONCAT(A17, ". ", B17) -> 2. Pieter van Zyl | E17: 2 | F17: ATL | H17: =_xlfn.CONCAT(E17, ". ", F17) -> 2. ATL | I17: 2 | J17: 30p | L17: =_xlfn.CONCAT(I17, ". ", J17) -> 2. 30p | M17: 2 | N17: Not started | P17: =_xlfn.CONCAT(M17, ". ", N17) -> 2. Not started
A18: 3 | B18: Joan van Zyl | D18: =_xlfn.CONCAT(A18, ". ", B18) -> 3. Joan van Zyl | E18: 3 | F18: ATL Coordinator | H18: =_xlfn.CONCAT(E18, ". ", F18) -> 3. ATL Coordinator | I18: 3 | J18: 50p | L18: =_xlfn.CONCAT(I18, ". ", J18) -> 3. 50p | M18: 3 | N18: WIP | P18: =_xlfn.CONCAT(M18, ". ", N18) -> 3. WIP
A19: 4 | B19: Jared Twigg | D19: =_xlfn.CONCAT(A19, ". ", B19) -> 4. Jared Twigg | E19: 4 | F19: Sponsor | H19: =_xlfn.CONCAT(E19, ". ", F19) -> 4. Sponsor | I19: 4 | J19: 90p | L19: =_xlfn.CONCAT(I19, ". ", J19) -> 4. 90p | M19: 4 | N19: Done | P19: =_xlfn.CONCAT(M19, ". ", N19) -> 4. Done
A20: 5 | B20: Marike Matthee | D20: =_xlfn.CONCAT(A20, ". ", B20) -> 5. Marike Matthee | E20: 5 | F20: Scheduler | H20: =_xlfn.CONCAT(E20, ". ", F20) -> 5. Scheduler | I20: 5 | J20: 100p | L20: =_xlfn.CONCAT(I20, ". ", J20) -> 5. 100p
A21: 6 | B21: Melanie van Zyl | D21: =_xlfn.CONCAT(A21, ". ", B21) -> 6. Melanie van Zyl | E21: 6 | F21: BPOC | H21: =_xlfn.CONCAT(E21, ". ", F21) -> 6. BPOC | I21: 6 | J21: 60d b4 p2 | L21: =_xlfn.CONCAT(I21, ". ", J21) -> 6. 60d b4 p2
A22: 7 | B22: Bianca Coetzee | D22: =_xlfn.CONCAT(A22, ". ", B22) -> 7. Bianca Coetzee | E22: 7 | F22: Translator | H22: =_xlfn.CONCAT(E22, ". ", F22) -> 7. Translator | I22: 7 | J22: 40d b4 p2 | L22: =_xlfn.CONCAT(I22, ". ", J22) -> 7. 40d b4 p2
A23: 9 | B23: Francois van Niekerk | D23: =_xlfn.CONCAT(A23, ". ", B23) -> 9. Francois van Niekerk | E23: 8 | F23: ATM | H23: =_xlfn.CONCAT(E23, ". ", F23) -> 8. ATM | I23: 8 | J23: Scope approval | L23: =_xlfn.CONCAT(I23, ". ", J23) -> 8. Scope approval
A24: 11 | B24: Andries vd Walt | D24: =_xlfn.CONCAT(A24, ". ", B24) -> 11. Andries vd Walt | E24: 9 | F24: IPOC | H24: =_xlfn.CONCAT(E24, ". ", F24) -> 9. IPOC | I24: 9 | J24: Tech Test | L24: =_xlfn.CONCAT(I24, ". ", J24) -> 9. Tech Test
A25: 12 | B25: Francina Botha | D25: =_xlfn.CONCAT(A25, ". ", B25) -> 12. Francina Botha | E25: 10 | F25: ATLC Leader | H25: =_xlfn.CONCAT(E25, ". ", F25) -> 10. ATLC Leader | I25: 10 | J25: Final RR | L25: =_xlfn.CONCAT(I25, ". ", J25) -> 10. Final RR
A26: 14 | B26: Tony Gardiner | D26: =_xlfn.CONCAT(A26, ". ", B26) -> 14. Tony Gardiner
A27: 15 | B27: Elmo Scheffer | D27: =_xlfn.CONCAT(A27, ". ", B27) -> 15. Elmo Scheffer
A28: 16 | B28: Pieter Roos | D28: =_xlfn.CONCAT(A28, ". ", B28) -> 16. Pieter Roos
A29: 17 | B29: Barry Headland | D29: =_xlfn.CONCAT(A29, ". ", B29) -> 17. Barry Headland
A30: 18 | B30: Nigel Owen | D30: =_xlfn.CONCAT(A30, ". ", B30) -> 18. Nigel Owen
A31: 19 | B31: Ria Fouche | D31: =_xlfn.CONCAT(A31, ". ", B31) -> 19. Ria Fouche
A32: 20 | B32: Elsabie Koster | D32: =_xlfn.CONCAT(A32, ". ", B32) -> 20. Elsabie Koster
A33: 21 | B33: Lizwin Jacobs | D33: =_xlfn.CONCAT(A33, ". ", B33) -> 21. Lizwin Jacobs
A34: 22 | B34: Michael | D34: =_xlfn.CONCAT(A34, ". ", B34) -> 22. Michael
A35: 23 | B35: Alice Erasmus | D35: =_xlfn.CONCAT(A35, ". ", B35) -> 23. Alice Erasmus
A36: 24 | B36: Sasha | D36: =_xlfn.CONCAT(A36, ". ", B36) -> 24. Sasha
A37: 25 | B37: Tembeka | D37: =_xlfn.CONCAT(A37, ". ", B37) -> 25. Tembeka

Sheet Tasks
F5: Work Task Status
C6: 2. 30p | E6: 3. Not started | F6: 3. Frans Joubert | G6: 2. ATL
A7: Id | B7: ProjectCode | C7: WorkTaskCode | D7: Task | E7: WorkTaskStatus | F7: Staff | G7: StaffRole | H7: AssignDate | I7: DueDate | J7: CompletionDate | K7: cmd | M7: AppraisalId | N7: WorkTaskCodeId | O7: WorkTaskStatusId | P7: StaffId | Q7: StafRoleId | R7: End
A8: 1 | B8: CAS321 | C8: =VLOOKUP(N8,tbl_TaskCodeX,4,FALSE) -> 3. 50p | D8: Task 1 | E8: =VLOOKUP(O8,tbl_TaskStatusX,4,FALSE) -> 3. WIP | F8: =VLOOKUP(P8,tbl_StaffX,4,FALSE) -> 3. Joan van Zyl | G8: =VLOOKUP(Q8,tbl_StaffRoleX,4,FALSE) -> 2. ATL | H8: 44768 | I8: 44782 | J8: 44796 | N8: 3 | O8: 3 | P8: 3 | Q8: 2
A9: 2 | B9: CAS0123 | C9: =VLOOKUP(N9,tbl_TaskCodeX,4,FALSE) -> 2. 30p | D9: Task 2 | E9: =VLOOKUP(O9,tbl_TaskStatusX,4,FALSE) -> 3. WIP | F9: =VLOOKUP(P9,tbl_StaffX,4,FALSE) -> 2. Pieter van Zyl | G9: =VLOOKUP(Q9,tbl_StaffRoleX,4,FALSE) -> 1. None | H9: 44775 | I9: 44775 | J9: 44775 | N9: 2 | O9: 3 | P9: 2 | Q9: 1
A10: 3 | B10: CAS0123 | C10: =VLOOKUP(N10,tbl_TaskCodeX,4,FALSE) -> 2. 30p | D10: Task 3 | E10: =VLOOKUP(O10,tbl_TaskStatusX,4,FALSE) -> 3. WIP | F10: =VLOOKUP(P10,tbl_StaffX,4,FALSE) -> 2. Pieter van Zyl | G10: =VLOOKUP(Q10,tbl_StaffRoleX,4,FALSE) -> 1. None | H10: 44775 | I10: 44775 | N10: 2 | O10: 3 | P10: 2 | Q10: 1
A11: 4 | B11: CAS01234 | C11: =VLOOKUP(N11,tbl_TaskCodeX,4,FALSE) -> 2. 30p | D11: Task 4 | E11: =VLOOKUP(O11,tbl_TaskStatusX,4,FALSE) -> 2. Not started | F11: =VLOOKUP(P11,tbl_StaffX,4,FALSE) -> 2. Pieter van Zyl | G11: =VLOOKUP(Q11,tbl_StaffRoleX,4,FALSE) -> 2. ATL | H11: 44775 | I11: 44782 | N11: 2 | O11: 2 | P11: 2 | Q11: 2

Sheet FindingsDB
D2: Search string >>
A4: ID | B4: PAxy | C4: FindingType | D4: FindingEnglish | E4: FindingChinese | F4: ReviewedBy | G4: Update/Add/Delete

Sheet QuestionsDB
F2: Search string >>
A4: ID | B4: PAxy | C4: FirstSort | D4: SecondSort | E4: QuestionEnglish | F4: QuestionChinese | G4: ExpectedAnswerEnglish | H4: ReviewedBy | I4: Update/Add/Delete

Sheet Working

Sheet OpenClose
B2: Standard interview
C3: Introduce appraisal team
C4: Explain purpose of interview and appraisal
C5: Ask for Govement issued ID (if virtual appraisal)
C6: Go over appraisal activities to date
C7: Go over confidentiality rules
C8: Explain interview process briefly
C9: Ask if the interviewee has any questions for the team
C10: Move to first question
C11: Tell us what you do
B13: Close the interview
C14: Ask transition questions.
C15: Did we miss anything?
C16: Was there something you expected us to ask you that we missed?
C17: Ask summary questions:
C18: If you could change anything, other than your boss or paycheck, what would it be?
C19: What has improved the most over the last year?
C20: Review list of artifacts requested.
C21: Remind them of the preliminary and final findings schedule.
C22: Remind them of the confidentiality and non-attribution of the interview.
B25: Online document translator
C26: https://www.onlinedoctranslator.com/en/translationform
C27: https://translate.google.com/?sl=auto&tl=en&op=translate

Sheet tmp
A2: Practice Group | B2: Practice Number | C2: Sustaining Habit and Persistence Capability | E2: Engineering and Developing Products | G2: Ensuring Quality | K2: Improving Performance | N2: Managing Business Resilience | O2: Managing the Workforce | P2: Planning and Managing Work | S2: Supporting Implementation | V2: Selecting and Managing Suppliers
C3: GOV | D3: II | E3: TS | F3: PI | G3: PR | H3: VV | I3: PQA | J3: RDM | K3: PCM | L3: PAD | M3: MPM | N3: RSK | O3: OT | P3: MC | Q3: PLAN | R3: EST | S3: CAR | T3: DAR | U3: CM | V3: SAM
A4: Level 1 | B4: Level 1 | C4: - | D4: - | E4: - | F4: - | G4: - | H4: - | I4: - | J4: - | K4: - | L4: - | M4: - | N4: - | O4: - | P4: - | Q4: - | R4: - | S4: - | T4: - | U4: - | V4: U
B5: 1.1 | C5: OoS | D5: OoS | E5: OoS | F5: OoS | G5: OoS | H5: OoS | I5: OoS | J5: OoS | K5: OoS | L5: OoS | M5: OoS | N5: OoS | O5: OoS | P5: OoS | Q5: OoS | R5: OoS | S5: OoS | T5: OoS | U5: OoS | V5: DM
B6: 1.2 | H6: OoS | K6: OoS | M6: OoS | P6: OoS | Q6: OoS | T6: OoS | V6: PM
B7: 1.3 | K7: OoS | V7: LM
A8: Level 2 | B8: Level 2 | C8: - | D8: - | E8: - | F8: - | G8: - | H8: - | I8: - | J8: - | K8: - | L8: - | M8: - | N8: - | O8: - | P8: - | Q8: - | R8: - | S8: - | T8: - | U8: -
B9: 2.1 | C9: OoS | D9: OoS | E9: OoS | F9: OoS | G9: OoS | H9: OoS | I9: OoS | J9: OoS | K9: OoS | L9: OoS | M9: OoS | N9: OoS | O9: OoS | P9: OoS | Q9: OoS | R9: OoS | S9: OoS | T9: OoS | U9: OoS | V9: DM
B10: 2.2 | C10: OoS | D10: OoS | E10: OoS | F10: OoS | G10: OoS | H10: OoS | I10: OoS | J10: OoS | K10: OoS | L10: OoS | M10: OoS | N10: OoS | O10: OoS | P10: OoS | Q10: OoS | R10: OoS | S10: OoS | T10: OoS | U10: OoS | V10: DM
B11: 2.3 | C11: OoS | E11: OoS | F11: OoS | G11: OoS | H11: OoS | I11: OoS | J11: OoS | L11: OoS | M11: OoS | P11: OoS | Q11: OoS | R11: OoS | T11: OoS | U11: OoS | V11: FM
B12: 2.4 | C12: OoS | F12: OoS | G12: OoS | I12: OoS | J12: OoS | M12: OoS | P12: OoS | Q12: OoS | T12: OoS | U12: OoS | V12: LM
B13: 2.5 | F13: OoS | J13: OoS | M13: OoS | Q13: OoS | T13: OoS | U13: OoS
B14: 2.6 | F14: OoS | M14: OoS | Q14: OoS | U14: OoS
B15: 2.7 | Q15: OoS
B16: 2.8 | Q16: OoS
A17: Level 3 | B17: Level 3 | C17: - | D17: - | E17: - | F17: - | G17: - | H17: - | I17: - | J17: - | K17: - | L17: - | M17: - | N17: - | O17: - | P17: - | Q17: - | R17: - | S17: - | T17: -
B18: 3.1 | C18: OoS | D18: OoS | E18: OoS | F18: OoS | G18: OoS | H18: OoS | I18: OoS | J18: OoS | K18: OoS | L18: OoS | M18: OoS | N18: OoS | O18: OoS | P18: OoS | Q18: OoS | R18: OoS | S18: OoS | T18: OoS | V18: DM
B19: 3.2 | C19: OoS | D19: OoS | E19: OoS | F19: OoS | H19: OoS | J19: OoS | K19: OoS | L19: OoS | M19: OoS | N19: OoS | O19: OoS | P19: OoS | Q19: OoS | R19: OoS | S19: OoS | V19: DM
B20: 3.3 | D20: OoS | E20: OoS | F20: OoS | J20: OoS | K20: OoS | L20: OoS | M20: OoS | N20: OoS | O20: OoS | P20: OoS | Q20: OoS | S20: OoS
B21: 3.4 | E21: OoS | J21: OoS | K21: OoS | L21: OoS | M21: OoS | N21: OoS | O21: OoS | P21: OoS | Q21: OoS | S21: OoS
B22: 3.5 | E22: OoS | J22: OoS | K22: OoS | L22: OoS | M22: OoS | N22: OoS | O22: OoS | S22: OoS
B23: 3.6 | E23: OoS | J23: OoS | K23: OoS | L23: OoS | M23: OoS | O23: OoS
B24: 3.7 | J24: OoS
A25: Level 4 | B25: Level 4 | C25: - | D25: - | K25: - | M25: - | Q25: - | S25: -
B26: 4.1 | C26: OoS | D26: OoS | K26: OoS | M26: OoS | Q26: OoS | S26: OoS | V26: DM
B27: 4.2 | M27: OoS | S27: OoS
B28: 4.3 | M28: OoS
B29: 4.4 | M29: OoS
B30: 4.5 | M30: OoS
A31: Level 5 | B31: Level 5 | M31: - | S31: -
B32: 5.1 | M32: OoS | S32: OoS
B33: 5.2 | M33: OoS
B34: 5.3 | M34: OoS

Sheet ou
A1: OU Level Characterisation and Practice Area Level Rating
A2: Practice Group | B2: Practice Number | C2: Sustaining Habit and Persistence Capability | E2: Engineering and Developing Products | G2: Ensuring Quality | K2: Improving Performance | N2: Managing Business Resilience | O2: Managing the Workforce | P2: Planning and Managing Work | S2: Supporting Implementation | V2: Selecting and Managing Suppliers
C3: GOV | D3: II | E3: TS | F3: PI | G3: PR | H3: VV | I3: PQA | J3: RDM | K3: PCM | L3: PAD | M3: MPM | N3: RSK | O3: OT | P3: MC | Q3: PLAN | R3: EST | S3: CAR | T3: DAR | U3: CM | V3: SAM
A4: Level 1 | B4: Level 1 | C4: ='ou-gov&ii'!C4 -> S | D4: ='ou-gov&ii'!K4 -> S | V4: U
B5: 1.1 | C5: ='ou-gov&ii'!C5 -> FM | D5: ='ou-gov&ii'!K5 -> FM | V5: DM
B6: 1.2 | V6: PM
B7: 1.3 | V7: LM
A8: Level 2 | B8: Level 2 | C8: ='ou-gov&ii'!C8 -> S | D8: ='ou-gov&ii'!K8 -> S
B9: 2.1 | C9: ='ou-gov&ii'!C9 -> FM | D9: ='ou-gov&ii'!K9 -> FM | V9: DM
B10: 2.2 | C10: ='ou-gov&ii'!C10 -> FM | D10: ='ou-gov&ii'!K10 -> FM | V10: DM
B11: 2.3 | C11: ='ou-gov&ii'!C11 -> FM | V11: FM
B12: 2.4 | C12: ='ou-gov&ii'!C12 -> FM | V12: LM
B13: 2.5
B14: 2.6
B15: 2.7
B16: 2.8
A17: Level 3 | B17: Level 3 | C17: ='ou-gov&ii'!C17 -> S | D17: ='ou-gov&ii'!K17 -> S
B18: 3.1 | C18: ='ou-gov&ii'!C18 -> FM | D18: ='ou-gov&ii'!K18 -> FM | V18: DM
B19: 3.2 | C19: ='ou-gov&ii'!C19 -> FM | D19: ='ou-gov&ii'!K19 -> FM | V19: DM
B20: 3.3 | D20: ='ou-gov&ii'!K20 -> FM
B21: 3.4
B22: 3.5
B23: 3.6
B24: 3.7
A25: Level 4 | B25: Level 4 | C25: ='ou-gov&ii'!C25 -> S | D25: ='ou-gov&ii'!K25 -> S
B26: 4.1 | C26: ='ou-gov&ii'!C26 -> FM | D26: ='ou-gov&ii'!K26 -> FM | V26: DM
B27: 4.2
B28: 4.3
B29: 4.4
B30: 4.5
A31: Level 5 | B31: Level 5
B32: 5.1
B33: 5.2
B34: 5.3
C36: GOV | D36: II | E36: TS | F36: PI | G36: PR | H36: VV | I36: PQA | J36: RDM | K36: PCM | L36: PAD | M36: MPM | N36: RSK | O36: OT | P36: MC | Q36: PLAN | R36: EST | S36: CAR | T36: DAR | U36: CM | V36: SAM
A37: Level | C37: 4 | D37: 4 | E37: 3 | F37: 3 | G37: 3 | H37: 3 | I37: 3 | J37: 3 | K37: 4 | L37: 3 | M37: 5 | N37: 3 | O37: 3 | P37: 3 | Q37: 4 | R37: 3 | S37: 5 | T37: 3 | U37: 2 | V37: 4
A42: GOV and II should still be manually link to tab:ou-gov&ii after the appraisal. It is not yet done automatically.
C44: CAR | D44: CM | E44: DAR | F44: EST | G44: GOV | H44: II | I44: MC | J44: MPM | K44: OT | L44: PAD | M44: PCM | N44: PI | O44: PLAN | P44: PQA | Q44: PR | R44: RDM | S44: RSK | T44: TS | U44: VV | V44: SAM
A45: Level 1 | B45: Level 1 | C45: =S4 -> 0 | D45: =U4 -> 0 | E45: =T4 -> 0 | F45: =R4 -> 0 | G45: =C4 -> S | H45: =D4 -> S | I45: =P4 -> 0 | J45: =M4 -> 0 | K45: =O4 -> 0 | L45: =L4 -> 0 | M45: =K4 -> 0 | N45: =F4 -> 0 | O45: =Q4 -> 0 | P45: =I4 -> 0 | Q45: =G4 -> 0 | R45: =J4 -> 0 | S45: =N4 -> 0 | T45: =E4 -> 0 | U45: =H4 -> 0 | V45: =V4 -> U
B46: 1.1 | C46: =S5 -> 0 | D46: =U5 -> 0 | E46: =T5 -> 0 | F46: =R5 -> 0 | G46: =C5 -> FM | H46: =D5 -> FM | I46: =P5 -> 0 | J46: =M5 -> 0 | K46: =O5 -> 0 | L46: =L5 -> 0 | M46: =K5 -> 0 | N46: =F5 -> 0 | O46: =Q5 -> 0 | P46: =I5 -> 0 | Q46: =G5 -> 0 | R46: =J5 -> 0 | S46: =N5 -> 0 | T46: =E5 -> 0 | U46: =H5 -> 0 | V46: =V5 -> DM
B47: 1.2 | E47: =T6 -> 0 | I47: =P6 -> 0 | J47: =M6 -> 0 | M47: =K6 -> 0 | O47: =Q6 -> 0 | U47: =H6 -> 0 | V47: =V6 -> PM
B48: 1.3 | M48: =K7 -> 0 | V48: =#REF! -> #REF!
A49: Level 2 | B49: Level 2 | C49: =S8 -> 0 | D49: =U8 -> 0 | E49: =T8 -> 0 | F49: =R8 -> 0 | G49: =C8 -> S | H49: =D8 -> S | I49: =P8 -> 0 | J49: =M8 -> 0 | K49: =O8 -> 0 | L49: =L8 -> 0 | M49: =K8 -> 0 | N49: =F8 -> 0 | O49: =Q8 -> 0 | P49: =I8 -> 0 | Q49: =G8 -> 0 | R49: =J8 -> 0 | S49: =N8 -> 0 | T49: =E8 -> 0 | U49: =H8 -> 0
B50: 2.1 | C50: =S9 -> 0 | D50: =U9 -> 0 | E50: =T9 -> 0 | F50: =R9 -> 0 | G50: =C9 -> FM | H50: =D9 -> FM | I50: =P9 -> 0 | J50: =M9 -> 0 | K50: =O9 -> 0 | L50: =L9 -> 0 | M50: =K9 -> 0 | N50: =F9 -> 0 | O50: =Q9 -> 0 | P50: =I9 -> 0 | Q50: =G9 -> 0 | R50: =J9 -> 0 | S50: =N9 -> 0 | T50: =E9 -> 0 | U50: =H9 -> 0 | V50: =V9 -> DM
B51: 2.2 | C51: =S10 -> 0 | D51: =U10 -> 0 | E51: =T10 -> 0 | F51: =R10 -> 0 | G51: =C10 -> FM | H51: =D10 -> FM | I51: =P10 -> 0 | J51: =M10 -> 0 | K51: =O10 -> 0 | L51: =L10 -> 0 | M51: =K10 -> 0 | N51: =F10 -> 0 | O51: =Q10 -> 0 | P51: =I10 -> 0 | Q51: =G10 -> 0 | R51: =J10 -> 0 | S51: =N10 -> 0 | T51: =E10 -> 0 | U51: =H10 -> 0 | V51: =V10 -> DM
B52: 2.3 | D52: =U11 -> 0 | E52: =T11 -> 0 | F52: =R11 -> 0 | G52: =C11 -> FM | I52: =P11 -> 0 | J52: =M11 -> 0 | L52: =L11 -> 0 | N52: =F11 -> 0 | O52: =Q11 -> 0 | P52: =I11 -> 0 | Q52: =G11 -> 0 | R52: =J11 -> 0 | T52: =E11 -> 0 | U52: =H11 -> 0 | V52: =V11 -> FM
B53: 2.4 | D53: =U12 -> 0 | E53: =T12 -> 0 | G53: =C12 -> FM | I53: =P12 -> 0 | J53: =M12 -> 0 | N53: =F12 -> 0 | O53: =Q12 -> 0 | P53: =I12 -> 0 | Q53: =G12 -> 0 | R53: =J12 -> 0 | V53: =V12 -> LM
B54: 2.5 | D54: =U13 -> 0 | E54: =T13 -> 0 | J54: =M13 -> 0 | N54: =F13 -> 0 | O54: =Q13 -> 0 | R54: =J13 -> 0
B55: 2.6 | D55: =U14 -> 0 | J55: =M14 -> 0 | N55: =F14 -> 0 | O55: =Q14 -> 0 | R55: =J14 -> 0
B56: 2.7 | O56: =Q15 -> 0
B57: 2.8 | O57: =Q16 -> 0
A58: Level 3 | B58: Level 3 | C58: =S17 -> 0 | E58: =T17 -> 0 | F58: =R17 -> 0 | G58: =C17 -> S | H58: =D17 -> S | I58: =P17 -> 0 | J58: =M17 -> 0 | K58: =O17 -> 0 | L58: =L17 -> 0 | M58: =K17 -> 0 | N58: =F17 -> 0 | O58: =Q17 -> 0 | P58: =I17 -> 0 | Q58: =G17 -> 0 | R58: =J17 -> 0 | S58: =N17 -> 0 | T58: =E17 -> 0 | U58: =H17 -> 0 | V58: =V17 -> 0
B59: 3.1 | C59: =S18 -> 0 | E59: =T18 -> 0 | F59: =R18 -> 0 | G59: =C18 -> FM | H59: =D18 -> FM | I59: =P18 -> 0 | J59: =M18 -> 0 | K59: =O18 -> 0 | L59: =L18 -> 0 | M59: =K18 -> 0 | N59: =F18 -> 0 | O59: =Q18 -> 0 | P59: =I18 -> 0 | Q59: =G18 -> 0 | R59: =J18 -> 0 | S59: =N18 -> 0 | T59: =E18 -> 0 | U59: =H18 -> 0 | V59: =V18 -> DM
B60: 3.2 | C60: =S19 -> 0 | F60: =R19 -> 0 | G60: =C19 -> FM | H60: =D19 -> FM | I60: =P19 -> 0 | J60: =M19 -> 0 | K60: =O19 -> 0 | L60: =L19 -> 0 | M60: =K19 -> 0 | N60: =F19 -> 0 | O60: =Q19 -> 0 | R60: =J19 -> 0 | S60: =N19 -> 0 | T60: =E19 -> 0 | U60: =H19 -> 0 | V60: =V19 -> DM
B61: 3.3 | C61: =S20 -> 0 | H61: =D20 -> FM | I61: =P20 -> 0 | J61: =M20 -> 0 | K61: =O20 -> 0 | L61: =L20 -> 0 | M61: =K20 -> 0 | N61: =F20 -> 0 | O61: =Q20 -> 0 | R61: =J20 -> 0 | S61: =N20 -> 0 | T61: =E20 -> 0
B62: 3.4 | C62: =S21 -> 0 | I62: =P21 -> 0 | J62: =M21 -> 0 | K62: =O21 -> 0 | L62: =L21 -> 0 | M62: =K21 -> 0 | O62: =Q21 -> 0 | R62: =J21 -> 0 | S62: =N21 -> 0 | T62: =E21 -> 0
B63: 3.5 | C63: =S22 -> 0 | J63: =M22 -> 0 | K63: =O22 -> 0 | L63: =L22 -> 0 | M63: =K22 -> 0 | R63: =J22 -> 0 | S63: =N22 -> 0 | T63: =E22 -> 0
B64: 3.6 | J64: =M23 -> 0 | K64: =O23 -> 0 | L64: =L23 -> 0 | M64: =K23 -> 0 | R64: =J23 -> 0 | T64: =E23 -> 0
B65: 3.7 | R65: =J24 -> 0
A66: Level 4 | B66: Level 4 | C66: =S25 -> 0 | G66: =C25 -> S | H66: =D25 -> S | J66: =M25 -> 0 | M66: =K25 -> 0 | O66: =Q25 -> 0
B67: 4.1 | C67: =S26 -> 0 | G67: =C26 -> FM | H67: =D26 -> FM | J67: =M26 -> 0 | M67: =K26 -> 0 | O67: =Q26 -> 0 | V67: =V26 -> DM
B68: 4.2 | C68: =S27 -> 0 | J68: =M27 -> 0
B69: 4.3 | J69: =M28 -> 0
B70: 4.4 | J70: =M29 -> 0
B71: 4.5 | J71: =M30 -> 0
A72: Level 5 | B72: Level 5 | C72: =S31 -> 0 | J72: =M31 -> 0
B73: 5.1 | C73: =S32 -> 0 | J73: =M32 -> 0
B74: 5.2 | J74: =M33 -> 0
B75: 5.3 | J75: =M34 -> 0

Sheet ou-gov&ii
A1: GOV and II OU and Process Level Characterisation
A2: Practice Group | B2: Practice Number | C2: OU | D2: Engineering | E2: Project Management | F2: Configuraiton Management | G2: Process Management | H2: Organisatinal Training | I2: Process Quality Assurance | K2: OU | L2: Engineering | M2: Project Management | N2: Configuraiton Management | O2: Process Management | P2: Measurement Management | Q2: Organisatinal Training | R2: Process Quality Assurance
C3: GOV | D3: GOV | E3: GOV | F3: GOV | G3: GOV | H3: GOV | I3: GOV | K3: II | L3: II | M3: II | N3: II | O3: II | P3: II | Q3: II | R3: II
A4: Level 1 | B4: Level 1 | C4: S | K4: S
B5: 1.1 | C5: FM | D5: FM | E5: FM | F5: FM | G5: FM | H5: FM | I5: FM | K5: FM | L5: FM | M5: FM | N5: FM | O5: FM | P5: FM | Q5: FM | R5: FM
B6: 1.2
B7: 1.3
A8: Level 2 | B8: Level 2 | C8: S | K8: S
B9: 2.1 | C9: FM | D9: FM | E9: FM | F9: FM | G9: FM | H9: FM | I9: FM | K9: FM | L9: FM | M9: FM | N9: FM | O9: FM | P9: FM | Q9: FM | R9: FM
B10: 2.2 | C10: FM | D10: FM | E10: FM | F10: FM | G10: FM | H10: FM | I10: FM | K10: FM | L10: FM | M10: FM | N10: FM | O10: FM | P10: FM | Q10: FM | R10: FM
B11: 2.3 | C11: FM | D11: FM | E11: FM | F11: FM | G11: FM | H11: FM | I11: FM
B12: 2.4 | C12: FM | D12: FM | E12: FM | F12: FM | G12: FM | H12: FM | I12: FM
B13: 2.5
B14: 2.6
B15: 2.7
B16: 2.8
A17: Level 3 | B17: Level 3 | C17: S | K17: S
B18: 3.1 | C18: FM | D18: FM | E18: FM | F18: FM | G18: FM | H18: FM | I18: FM | K18: FM | L18: FM | M18: FM | N18: FM | O18: FM | P18: FM | Q18: FM | R18: FM
B19: 3.2 | C19: FM | D19: FM | E19: FM | F19: FM | G19: FM | H19: FM | I19: FM | K19: FM | L19: FM | M19: FM | N19: FM | O19: FM | P19: FM | Q19: FM | R19: FM
B20: 3.3 | K20: FM | L20: FM | M20: FM | N20: FM | O20: FM | P20: FM | Q20: FM | R20: FM
B21: 3.4
B22: 3.5
B23: 3.6
B24: 3.7
A25: Level 4 | B25: Level 4 | C25: S | K25: S
B26: 4.1 | C26: FM | D26: FM | E26: FM | F26: FM | G26: FM | H26: FM | I26: FM | K26: FM | L26: FM | M26: FM | N26: FM | O26: FM | P26: FM | Q26: FM | R26: FM
B27: 4.2
B28: 4.3
B29: 4.4
B30: 4.5
A31: Level 5 | B31: Level 5
B32: 5.1
B33: 5.2
B34: 5.3
A38: The above rating should still be manually link into II and GOV after the appraisal. This is not yet done automatically.
A39: The processes must be checked against what is in the CAS plan tab:Project&Support. It is not yet done automatically.

Sheet Findings
A1: PA | B1: Strength/Weakness/Improvement | C1: Description

Sheet Template1
A2: Heading | B2: Level Practice Project OE Source | C2: OE reference | D2: URL | E2: Engl | F2: OE Type | G2: OE Source | H2: Affirmation Source (Session and Person) | I2: Suff. Artifact Yes | No | J2: Affirm. Yes | No | K2: Questions | L2: Weakness | M2: Strength | N2: Recommendations | O2: Rating/ Char | P2: Notes | Q2: Update Y
A3: 1 Prac_Group | B3: Level 1
A4: 2 Prac_OU | B4: GOV 1.1 | C4: Senior management identifies what is important for doing the work and defines the approach needed to accomplish the objectives of the organization. 高级管理层识别对工作执行重要地因素，并定义实现组织目标所需地方法 | I4: Example Work products | J4: Example Activities | K4: Questions
A5: 3 Process | B5: GOV 1.1 | C5: Engineering process
A6: 4 Prac_Instan | B6: GOV 1.1 | C6: Project A | H6: [Project management] (ABC)
A7: 5 OE | B7: Project A | C7: Evidence name | D7: link | E7: engl | F7: none | G7: OE DB
A19: 2 Prac_OU2 | B19: GOV 1.1 | C19: Senior management identifies what is important for doing the work and defines the approach needed to accomplish the objectives of the organization. 高级管理层识别对工作执行重要地因素，并定义实现组织目标所需地方法 | I19: Example Work products | J19: Example Activities | K19: Questions

Sheet Sheet1

Sheet Template2
A1: GOV - GOVERNANCE (GOV)
A2: 治理
A3: Intent | B3: Provides guidance to senior management on their role in the sponsorship and governance of process activities.
A4: 目的 | B4: 指导高级管理层履行其在过程活动的发起和治理中的职责
A5: Value | B5: Minimizes the cost of process implementation, increases the likelihood of meeting objectives, and ensures that the implemented processes support and contribute to the success of the business.
A6: 价值 | B6: 最大限度地降低过程实施成本，提高实现目标地可能性，并确保实施地过程支持并促成业务成功
A8: Heading | B8: Level Practice Project OE Source | C8: OE reference | D8: URL | E8: Engl | F8: OE Type | G8: OE Source | H8: Affirmation Source (Session and Person) | I8: Suff. Artifact Yes | No | J8: Affirm. Yes | No | K8: Questions | L8: Weakness | M8: Strength | N8: Recommendations | O8: Rating/ Char | P8: Notes | Q8: Update Y

Sheet ATM
A1: ATM | C1: email | E1: PI | F1: TS | G1: PQA | H1: PR | I1: RDM | J1: VV | K1: MPM | L1: PAD | M1: PCM | N1: RSK | O1: OT | P1: EST | Q1: MC | R1: PLAN | S1: CAR | T1: CM | U1: DAR | V1: SAM | W1: GOV | X1: II
A2: Sponsor detail
A3: OU Coordinator
A4: Registered Interpreter
A6: Lead appraiser
A8: Appraisal team member | D8: =COUNTIF(E8:Y8,"x") -> 0
A9: Appraisal team member | D9: =COUNTIF(E9:Y9,"x") -> 0
A10: Appraisal team member | D10: =COUNTIF(E10:Y10,"x") -> 0
A11: Appraisal team member | D11: =COUNTIF(E11:Y11,"x") -> 0
A12: Appraisal team member | D12: =COUNTIF(E12:Y12,"x") -> 0
A13: Appraisal team member | D13: =COUNTIF(E13:Y13,"x") -> 0
A14: Appraisal team member | D14: =COUNTIF(E14:Y14,"x") -> 0
E15: =COUNTIF(E6:E14,"x") -> 0 | F15: =COUNTIF(F6:F14,"x") -> 0 | G15: =COUNTIF(G6:G14,"x") -> 0 | H15: =COUNTIF(H6:H14,"x") -> 0 | I15: =COUNTIF(I6:I14,"x") -> 0 | J15: =COUNTIF(J6:J14,"x") -> 0 | K15: =COUNTIF(K6:K14,"x") -> 0 | L15: =COUNTIF(L6:L14,"x") -> 0 | ... X15: =COUNTIF(X6:X14,"x") -> 0
C17: Objective evidence done
C18: Affirmation done
C19: Characterisation
C20: OU Characterisation done

Sheet Processes

Sheet PI
A1: PRODUCT INTEGRATION
A2: 产品集成
A3: Intent | B3: Integrates and delivers the solution that addresses functionality, performance, and quality requirements.
A4: 目的 | B4: 集成并交付满足功能和质量需求地解决方案
A5: Value | B5: Increases customers' satisfaction by giving them a solution that meets or exceeds their functionality and quality requirements.
A6: 价值 | B6: 通过提供达到或超过其功能和质量要求地解决方案来提高客户地满意度
A8: Heading | B8: Level Practice Project OE Source | C8: OE reference | D8: URL | E8: Engl | F8: OE Type | G8: OE Source | H8: Affirmation Source (Session and Person) | I8: Suff. Artifact Yes | No | J8: Affirm. Yes | No | K8: Questions | L8: Weakness | M8: Strength | N8: Recommendations | O8: Rating/ Char | P8: Notes | Q8: Update Y
A9: 1 Prac_Group | B9: Level 1
A10: 2 Prac_OU | B10: PI 1.1 | C10: Assemble solutions and deliver to the customer. (Enables customer satisfaction by delivering a usable solution.) 组装解决方案并交付给客户。 （通过提供可用的解决方案来提高客户满意度。） | I10: - Customer satisfaction feedback. | J10: - Packaging the solution for delivery. | K10: - 你能描述一下如何组装解决方案并交付给客户吗？
A11: 4 Prac_Instan | B11: PI 1.1 | C11: p2RRE | H11: [4] Engineering(Surname, Developer2)
A12: 5 OE | B12: p2RRE | C12: Evidence name | D12: link | E12: engl | F12: none | G12: OE DB
A13: 5 OE | B13: p2RRE | C13: Evidence name | D13: link | E13: engl | F13: none | G13: OE DB
A14: 1 Prac_Group | B14: Level 2
A15: 2 Prac_OU | B15: PI 2.1 | C15: Develop, keep updated, and follow an integration strategy. (Ensures that the product will meet customer requirements given available resources.) 制定、保持更新并遵循集成策略。 （确保产品在可用资源的情况下满足客户的要求。） | I15: - Reports on strategy effectiveness. | J15: - Ensuring adherence to the strategy throughout the integration process. | K15: - 你们的整合策略是什么，你们如何确保它保持更新并得到遵循？
A16: 4 Prac_Instan | B16: PI 2.1 | C16: p2RRE | H16: [4] Engineering(Surname, Developer2)
A17: 5 OE | B17: p2RRE | C17: Evidence name | D17: link | E17: engl | F17: none | G17: OE DB
A18: 5 OE | B18: p2RRE | C18: Evidence name | D18: link | E18: engl | F18: none | G18: OE DB
A19: 2 Prac_OU | B19: PI 2.2 | C19: Develop, keep updated, and use the integration environment. (Provides an effective risk mitigation technique to ensure that the solution and components are integrated correctly.) 开发、保持更新和使用集成环境。 （提供有效的风险缓解技术，以确保解决方案和组件正确集成。） | I19: - Test results and validation reports. | J19: - Conducting testing and validation within the environment. | K19: - 你能解释一下你们是如何开发和维护整合环境的吗？
A20: 4 Prac_Instan | B20: PI 2.2 | C20: p2RRE | H20: [4] Engineering(Surname, Developer2)
A21: 5 OE | B21: p2RRE | C21: Evidence name | D21: link | E21: engl | F21: none | G21: OE DB
A22: 5 OE | B22: p2RRE | C22: Evidence name | D22: link | E22: engl | F22: none | G22: OE DB
A23: 2 Prac_OU | B23: PI 2.3 | C23: Develop, keep updated, and follow procedures and criteria for integrating solutions and components. (Improves the likelihood of producing a solution that works correctly and meets the customer's requirements.) 开发、保持更新并遵循集成解决方案和组件的程序和标准。 （提高生成正确工作并满足客户要求的解决方案的可能性。） | I23: - Records of procedure updates and revisions. | J23: - Reviewing and updating procedures based on feedback and lessons learned. | K23: - 你们是如何为整合解决方案和组件制定和更新程序和标准的，你们如何确保它们保持更新？
A24: 4 Prac_Instan | B24: PI 2.3 | C24: p2RRE | H24: [4] Engineering(Surname, Developer2)
A25: 5 OE | B25: p2RRE | C25: Evidence name | D25: link | E25: engl | F25: none | G25: OE DB
A26: 5 OE | B26: p2RRE | C26: Evidence name | D26: link | E26: engl | F26: none | G26: OE DB
A27: 2 Prac_OU | B27: PI 2.4 | C27: Confirm, prior to integration, that each component has been properly identified and operates according to its requirements and design. (Reduces total development cost, integration cycle time, and rework.) 在集成之前，确认每个组件均已根据其要求和设计正确识别并运行。 （减少总开发成本、集成周期时间和返工。） | I27: - integration testing results. | J27: - integration testing on individual components. | K27: - 在整合之前，你们是如何确认每个组件是否已经正确识别并根据其要求和设计进行操作的？
A28: 4 Prac_Instan | B28: PI 2.4 | C28: p2RRE | H28: [4] Engineering(Surname, Developer2)
A29: 5 OE | B29: p2RRE | C29: Evidence name | D29: link | E29: engl | F29: none | G29: OE DB
A30: 5 OE | B30: p2RRE | C30: Evidence name | D30: link | E30: engl | F30: none | G30: OE DB
A31: 2 Prac_OU | B31: PI 2.5 | C31: Evaluate integrated components to ensure conformance to the solution's requirements and design. (Helps to ensure customer requirements are correctly implemented.) 评估集成组件以确保符合解决方案的要求和设计。 （有助于确保客户要求得到正确实施。） | I31: - Compliance certificate for the solution. | J31: - Identifying and resolving discrepancies or issues. | K31: - 你们是如何评估整合组件以确保其符合解决方案的要求和设计的？
A32: 4 Prac_Instan | B32: PI 2.5 | C32: p2RRE | H32: [4] Engineering(Surname, Developer2)
A33: 5 OE | B33: p2RRE | C33: Evidence name | D33: link | E33: engl | F33: none | G33: OE DB
A34: 5 OE | B34: p2RRE | C34: Evidence name | D34: link | E34: engl | F34: none | G34: OE DB
A35: 2 Prac_OU | B35: PI 2.6 | C35: Integrate solutions and components according to the integration strategy. (Ensures that the customer receives a solution that meets requirements and design.) 根据集成策略集成解决方案和组件。 （确保客户收到满足要求和设计的解决方案。） | I35: - Integration completion checklist. | J35: - Monitoring progress and adjusting as necessary to meet strategy objectives. | K35: - 你能向我介绍一下你们是如何根据整合策略整合解决方案和组件的吗？
A36: 4 Prac_Instan | B36: PI 2.6 | C36: p2RRE | H36: [4] Engineering(Surname, Developer2)
A37: 5 OE | B37: p2RRE | C37: Evidence name | D37: link | E37: engl | F37: none | G37: OE DB
A38: 5 OE | B38: p2RRE | C38: Evidence name | D38: link | E38: engl | F38: none | G38: OE DB
A39: 1 Prac_Group | B39: Level 3
A40: 2 Prac_OU | B40: PI 3.1 | C40: Review and keep updated interface or connection descriptions for coverage, completeness, and consistency throughout the solution's life. (Reduces rework and missed project objectives caused by incompatible or inconsistent interfaces or connections.) 检查并保持更新的接口或连接描述，以确保整个解决方案生命周期的覆盖范围、完整性和一致性。 （减少因接口或连接不兼容或不一致而导致的返工和错过项目目标。） | I40: - Compliance report on consistency. | J40: - Ensuring consistency across all interfaces or connections. | K40: - 你们如何审查和保持接口或连接描述的覆盖范围、完整性和一致性，以确保其在整个解决方案生命周期中的更新？
A41: 4 Prac_Instan | B41: PI 3.1 | C41: p2RRE | H41: [4] Engineering(Surname, Developer2)
A42: 5 OE | B42: p2RRE | C42: Evidence name | D42: link | E42: engl | F42: none | G42: OE DB
A43: 5 OE | B43: p2RRE | C43: Evidence name | D43: link | E43: engl | F43: none | G43: OE DB
A44: 2 Prac_OU | B44: PI 3.2 | C44: Confirm, prior to integration, that component interfaces or connections comply with interface or connection descriptions. (Reduces the amount of rework due to interface or connection incompatibility.) 在集成之前确认组件接口或连接符合接口或连接描述。 （减少因接口或连接不兼容而导致的返工量。） | I44: - Verification logs. | J44: - Documenting any deviations and resolving them before integration. | K44: - 在整合之前，你们如何确认组件接口或连接是否符合接口或连接描述？
A45: 4 Prac_Instan | B45: PI 3.2 | C45: p2RRE | H45: [4] Engineering(Surname, Developer2)
A46: 5 OE | B46: p2RRE | C46: Evidence name | D46: link | E46: engl | F46: none | G46: OE DB
A47: 5 OE | B47: p2RRE | C47: Evidence name | D47: link | E47: engl | F47: none | G47: OE DB
A48: 2 Prac_OU | B48: PI 3.3 | C48: Evaluate integrated components for interface or connection compatibility. (Reduces the risk of interface or connection failure within integrated components.) 评估集成组件的接口或连接兼容性。 （降低集成组件内接口或连接故障的风险。） | I48: - Updated interface/connection compatibility matrix. | J48: - Resolving any identified compatibility issues. | K48: - 你们如何评估整合组件的接口或连接兼容性？
A49: 4 Prac_Instan | B49: PI 3.3 | C49: p2RRE | H49: [4] Engineering(Surname, Developer2)
A50: 5 OE | B50: p2RRE | C50: Evidence name | D50: link | E50: engl | F50: none | G50: OE DB
A51: 5 OE | B51: p2RRE | C51: Evidence name | D51: link | E51: engl | F51: none | G51: OE DB

Sheet TS
A1: TECHNICAL SOLUTION
A2: 技术解决方案
A3: Intent | B3: Designs and builds solutions that meet requirements.
A4: 目的 | B4: 设计和构建满足客户需求的解决方案
A5: Value | B5: Provides a cost-effective design and solution that meets customer requirements and reduces rework.
A6: 价值 | B6: 提供高效的设计和解决方案，以满足客户需求并且减少返工
A8: Heading | B8: Level Practice Project OE Source | C8: OE reference | D8: URL | E8: Engl | F8: OE Type | G8: OE Source | H8: Affirmation Source (Session and Person) | I8: Suff. Artifact Yes | No | J8: Affirm. Yes | No | K8: Questions | L8: Weakness | M8: Strength | N8: Recommendations | O8: Rating/ Char | P8: Notes | Q8: Update Y
A9: 1 Prac_Group | B9: Level 1
A10: 2 Prac_OU | B10: TS 1.1 | C10: Build a solution to meet requirements. (Provides the customer with a solution that implements the requirements and reduces the cost of rework.) 构建满足要求的解决方案。 （为客户提供实现需求并降低返工成本的解决方案。） | I10: - Implemented solution. | J10: - Implementing the solution based on the prototype. | K10: - 你如何确保构建的解决方案符合规定的要求？
A11: 4 Prac_Instan | B11: TS 1.1 | C11: p2RRE | H11: [4] Engineering(Surname, Designer2)
A12: 5 OE | B12: p2RRE | C12: Evidence name | D12: link | E12: engl | F12: none | G12: OE DB
A13: 5 OE | B13: p2RRE | C13: Evidence name | D13: link | E13: engl | F13: none | G13: OE DB
A14: 1 Prac_Group | B14: Level 2
A15: 2 Prac_OU | B15: TS 2.1 | C15: Design and build a solution to meet requirements. (Provides a structure to guide the implementation of a cost | I15: - Implemented solution with corresponding documentation. | J15: - Implementing the solution based on the design. | K15: - 你能描述一下你设计和构建解决方案以满足特定要求的过程吗？
A16: 4 Prac_Instan | B16: TS 2.1 | C16: p2RRE | H16: [4] Engineering(Surname, Designer2)
A17: 5 OE | B17: p2RRE | C17: Evidence name | D17: link | E17: engl | F17: none | G17: OE DB
A18: 5 OE | B18: p2RRE | C18: Evidence name | D18: link | E18: engl | F18: none | G18: OE DB
A19: 2 Prac_OU | B19: TS 2.2 | C19: Evaluate the design and address identified issues. (Reduces cost by minimizing defects and ensuring that the solution meets requirements.) 评估设计并解决已发现的问题。 （通过最大限度地减少缺陷并确保解决方案满足要求来降低成本。） | I19: - Updated design documentation reflecting changes. | J19: - Iteratively refining the design based on feedback. | K19: - 你如何评估设计的有效性，以及如何解决在此过程中出现的任何问题？
A20: 4 Prac_Instan | B20: TS 2.2 | C20: p2RRE | H20: [4] Engineering(Surname, Designer2)
A21: 5 OE | B21: p2RRE | C21: Evidence name | D21: link | E21: engl | F21: none | G21: OE DB
A22: 5 OE | B22: p2RRE | C22: Evidence name | D22: link | E22: engl | F22: none | G22: OE DB
A23: 2 Prac_OU | B23: TS 2.3 | C23: Provide guidance on use of the solution. (Supports usability and maintainability of the solution.) 提供解决方案的使用指导。 （支持解决方案的可用性和可维护性。） | I23: - Support tickets and resolutions log. | J23: - Providing ongoing support and troubleshooting assistance. | K23: - 你采取了哪些措施来确保用户在使用你提供的解决方案时能够得到有效的指导？
A24: 4 Prac_Instan | B24: TS 2.3 | C24: p2RRE | H24: [4] Engineering(Surname, Designer2)
A25: 5 OE | B25: p2RRE | C25: Evidence name | D25: link | E25: engl | F25: none | G25: OE DB
A26: 5 OE | B26: p2RRE | C26: Evidence name | D26: link | E26: engl | F26: none | G26: OE DB
A27: 1 Prac_Group | B27: Level 3
A28: 2 Prac_OU | B28: TS 3.1 | C28: Develop criteria for design decisions. (Increases the likelihood of producing a robust design that meets customer requirements and constraints.) 制定设计决策的标准。 （增加了生产满足客户要求和约束的稳健设计的可能性。） | I28: - Decision matrices and analysis reports. | J28: - Creating decision matrices to evaluate design options. | K28: - 你是如何确立指导你设计决策的标准？
A29: 4 Prac_Instan | B29: TS 3.1 | C29: p2RRE | H29: [4] Engineering(Surname, Designer2)
A30: 5 OE | B30: p2RRE | C30: Evidence name | D30: link | E30: engl | F30: none | G30: OE DB
A31: 5 OE | B31: p2RRE | C31: Evidence name | D31: link | E31: engl | F31: none | G31: OE DB
A32: 2 Prac_OU | B32: TS 3.2 | C32: Develop alternative solutions for selected components. (Ensures that the most beneficial solution is identified and selected.) 为选定的组件开发替代解决方案。 （确保确定并选择最有益的解决方案。） | I32: - Feasibility study reports outlining pros and cons. | J32: - Conducting feasibility studies to assess alternative solutions. | K32: - 你如何制定针对特定组件的替代解决方案的方法？
A33: 4 Prac_Instan | B33: TS 3.2 | C33: p2RRE | H33: [4] Engineering(Surname, Designer2)
A34: 5 OE | B34: p2RRE | C34: Evidence name | D34: link | E34: engl | F34: none | G34: OE DB
A35: 5 OE | B35: p2RRE | C35: Evidence name | D35: link | E35: engl | F35: none | G35: OE DB
A36: 2 Prac_OU | B36: TS 3.3 | C36: Perform a build, buy, or reuse analysis. (Ensures that the most effective way to implement the design has been chosen.) 执行构建、购买或重用分析。 （确保选择了最有效的方法来实现设计。） | I36: - Vendor/product evaluations. | J36: - Assessing the feasibility of reusing components from previous projects. | K36: - 在考虑解决方案时，你如何确定是建立、购买还是重用某些组件？
A37: 4 Prac_Instan | B37: TS 3.3 | C37: p2RRE | H37: [4] Engineering(Surname, Designer2)
A38: 5 OE | B38: p2RRE | C38: Evidence name | D38: link | E38: engl | F38: none | G38: OE DB
A39: 5 OE | B39: p2RRE | C39: Evidence name | D39: link | E39: engl | F39: none | G39: OE DB
A40: 2 Prac_OU | B40: TS 3.4 | C40: Select solutions based on design criteria. (Ensures the most efficient and effective solution is selected to meet the customer's requirements within cost, schedule, and performance constraints.) 根据设计标准选择解决方案。 （确保选择最高效、最有效的解决方案，在成本、进度和性能限制内满足客户的要求。） | I40: - Stakeholder approval records. | J40: - Making recommendations based on criteria alignment and stakeholder input. | K40: - 当根据你建立的设计标准选择解决方案时，你考虑了哪些因素？
A41: 4 Prac_Instan | B41: TS 3.4 | C41: p2RRE | H41: [4] Engineering(Surname, Designer2)
A42: 5 OE | B42: p2RRE | C42: Evidence name | D42: link | E42: engl | F42: none | G42: OE DB
A43: 5 OE | B43: p2RRE | C43: Evidence name | D43: link | E43: engl | F43: none | G43: OE DB
A44: 2 Prac_OU | B44: TS 3.5 | C44: Develop, keep updated, and use information needed to implement the design. (Avoids rework by ensuring that solution implementers have the information they need to develop a solution that meets the customer's requirements.) 开发、保持更新和使用实现设计所需的信息。 （通过确保解决方案实施者拥有开发满足客户要求的解决方案所需的信息来避免返工。） | I44: - Documentation access policies and procedures. | J44: - Providing access to relevant documentation for team members. | K44: - 你如何确保实施设计所需的信息既得到更新又得到有效利用？
A45: 4 Prac_Instan | B45: TS 3.5 | C45: p2RRE | H45: [4] Engineering(Surname, Designer2)
A46: 5 OE | B46: p2RRE | C46: Evidence name | D46: link | E46: engl | F46: none | G46: OE DB
A47: 5 OE | B47: p2RRE | C47: Evidence name | D47: link | E47: engl | F47: none | G47: OE DB
A48: 2 Prac_OU | B48: TS 3.6 | C48: Design solution interfaces or connections using established criteria. (Reduces the likelihood of failures and rework during testing and operations and maximizes performance.) 使用既定标准设计解决方案接口或连接。 （减少测试和操作期间发生故障和返工的可能性，并最大限度地提高性能。） | I48: - Interface documentation for integration partners. | J48: - Prototyping and testing interface implementations. | K48: - 你在设计解决方案接口或连接时所使用的标准是什么？
A49: 4 Prac_Instan | B49: TS 3.6 | C49: p2RRE | H49: [4] Engineering(Surname, Designer2)
A50: 5 OE | B50: p2RRE | C50: Evidence name | D50: link | E50: engl | F50: none | G50: OE DB
A51: 5 OE | B51: p2RRE | C51: Evidence name | D51: link | E51: engl | F51: none | G51: OE DB

Sheet PQA
A1: PROCESS QUALITY ASSURANCE
A2: 过程质量保证
A3: Intent | B3: Verifies and enables improvement of the quality of the processes performed and resulting work products.
A4: 目的 | B4: 验证并改进已执行的过程和所产生的工作产品的质量
A5: Value | B5: Increases the consistent use and improvement of the processes to maximize business benefit and customer satisfaction.
A6: 价值 | B6: 增强过程使用和改进的一致性，以最大限度地提高业务效益和客户满意度
A8: Heading | B8: Level Practice Project OE Source | C8: OE reference | D8: URL | E8: Engl | F8: OE Type | G8: OE Source | H8: Affirmation Source (Session and Person) | I8: Suff. Artifact Yes | No | J8: Affirm. Yes | No | K8: Questions | L8: Weakness | M8: Strength | N8: Recommendations | O8: Rating/ Char | P8: Notes | Q8: Update Y
A9: 1 Prac_Group | B9: Level 1
A10: 2 Prac_OU | B10: PQA 1.1 | C10: Identify and address process and work product issues. (Increases customer satisfaction through improved quality and performance.) 识别并解决流程和工作产品问题。 （通过改进质量和性能提高客户满意度。） | I10: - PQA results | J10: - Perform process or product quality assurance | K10: - How do you identify work products and processes for process quality assurance? '如何识别工作产品和过程以保证过程质量？
A11: 4 Prac_Instan | B11: PQA 1.1 | C11: s4PPQA | H11: [8] Process Quality Assurance(Surname, Process Assurance Manager4)
A12: 5 OE | B12: s4PPQA | C12: Evidence name | D12: link | E12: engl | F12: none | G12: OE DB
A13: 5 OE | B13: s4PPQA | C13: Evidence name | D13: link | E13: engl | F13: none | G13: OE DB
A14: 1 Prac_Group | B14: Level 2
A15: 2 Prac_OU | B15: PQA 2.1 | C15: Develop, keep updated, and follow a quality assurance approach and plan based on historical quality data. (Reduces cost and increases quality by focusing on recurring problem areas.) 根据历史质量数据制定、保持更新并遵循质量保证方法和计划。 （通过关注重复出现的问题领域来降低成本并提高质量。） | I15: - Improvement proposals | J15: - Develop and keep updated checklists based on process descriptions, standards, and procedures. | K15: - How do you plan for quality assurance? '您如何为质量保证做计划？
A16: 4 Prac_Instan | B16: PQA 2.1 | C16: s4PPQA | H16: [8] Process Quality Assurance(Surname, Process Assurance Manager4)
A17: 5 OE | B17: s4PPQA | C17: Evidence name | D17: link | E17: engl | F17: none | G17: OE DB
A18: 5 OE | B18: s4PPQA | C18: Evidence name | D18: link | E18: engl | F18: none | G18: OE DB
A19: 2 Prac_OU | B19: PQA 2.2 | C19: Objectively evaluate selected performed processes and work products against the recorded process and applicable standards. (Delivers high | I19: - PQA work product compliance records | J19: - Objective value work products against applicable standards | K19: - How do you objectively evaluate process and work products? '如何客观评价过程和工作产品？
A20: 4 Prac_Instan | B20: PQA 2.2 | C20: s4PPQA | H20: [8] Process Quality Assurance(Surname, Process Assurance Manager4)
A21: 5 OE | B21: s4PPQA | C21: Evidence name | D21: link | E21: engl | F21: none | G21: OE DB
A22: 5 OE | B22: s4PPQA | C22: Evidence name | D22: link | E22: engl | F22: none | G22: OE DB
A23: 2 Prac_OU | B23: PQA 2.3 | C23: Communicate quality and non | I23: - Resolution status report tracking the status of issue resolution efforts. | J23: - Escale noncompliance issues that cannot be resolved | K23: - How to you communicate and address noncompliance issues? '您如何沟通和解决不符合项问题？
A24: 4 Prac_Instan | B24: PQA 2.3 | C24: s4PPQA | H24: [8] Process Quality Assurance(Surname, Process Assurance Manager4)
A25: 5 OE | B25: s4PPQA | C25: Evidence name | D25: link | E25: engl | F25: none | G25: OE DB
A26: 5 OE | B26: s4PPQA | C26: Evidence name | D26: link | E26: engl | F26: none | G26: OE DB
A27: 2 Prac_OU | B27: PQA 2.4 | C27: Record and use results of quality assurance activities. (Optimizes future quality assurance activities and reduces the cost of future work.) 记录和使用质量保证活动的结果。 （优化未来的质量保证活动并降低未来工作的成本。） | I27: - Updated quality assurance plan integrating insights from past activities. | J27: - Incorporating lessons learned into future quality assurance plans and processes. | K27: - Where do you record the results of quality assurance activities? '将记录质量保证活动的结果记录在哪里
A28: 4 Prac_Instan | B28: PQA 2.4 | C28: s4PPQA | H28: [8] Process Quality Assurance(Surname, Process Assurance Manager4)
A29: 5 OE | B29: s4PPQA | C29: Evidence name | D29: link | E29: engl | F29: none | G29: OE DB
A30: 5 OE | B30: s4PPQA | C30: Evidence name | D30: link | E30: engl | F30: none | G30: OE DB
A31: 1 Prac_Group | B31: Level 3
A32: 2 Prac_OU | B32: PQA 3.1 | C32: Identify and record opportunities for improvement during quality assurance activities. (Improves the organization's capability to meet its goals and objectives.) 识别并记录质量保证活动期间的改进机会。 （提高组织实现其目标的能力。） | I32: - Stakeholder feedback records capturing responses and decisions regarding improvement opportunities. | J32: - Sharing improvement suggestions with relevant stakeholders for consideration. | K32: - How do you record and use the results of quality assurance activities? '如何记录和使用质量保证活动的结果？
A33: 4 Prac_Instan | B33: PQA 3.1 | C33: s4PPQA | H33: [8] Process Quality Assurance(Surname, Process Assurance Manager4)
A34: 5 OE | B34: s4PPQA | C34: Evidence name | D34: link | E34: engl | F34: none | G34: OE DB
A35: 5 OE | B35: s4PPQA | C35: Evidence name | D35: link | E35: engl | F35: none | G35: OE DB

Sheet PR
A1: PEER REVIEWS
A2: 同行评审
A3: Intent | B3: Identifies and addresses process performance and work product issues through reviews by the producer's peers or Subject Matter Experts (SMEs).
A4: 目的 | B4: 通过生产者同行或主体专家（SME）的评审来识别并解决工作产品的问题
A5: Value | B5: Reduces cost and rework by uncovering issues or defects early.
A6: 价值 | B6: 及早发现问题或缺陷，降低成本和返工
A8: Heading | B8: Level Practice Project OE Source | C8: OE reference | D8: URL | E8: Engl | F8: OE Type | G8: OE Source | H8: Affirmation Source (Session and Person) | I8: Suff. Artifact Yes | No | J8: Affirm. Yes | No | K8: Questions | L8: Weakness | M8: Strength | N8: Recommendations | O8: Rating/ Char | P8: Notes | Q8: Update Y
A9: 1 Prac_Group | B9: Level 1
A10: 2 Prac_OU | B10: PR 1.1 | C10: Perform reviews of work products and record issues. (Improves work product quality and reduces cost and rework by uncovering issues early.) 对工作产品进行审查并记录问题。 （通过及早发现问题来提高工作产品质量并降低成本和返工。） | I10: - Corrective action plans outlining steps to resolve issues and prevent recurrence. | J10: - Implementing corrective actions to address issues and improve work product quality. | K10: - What peer reviews do you (process actor) perform or are performed on your work products? 对哪些工作产品进行同行评审
A11: 4 Prac_Instan | B11: PR 1.1 | C11: p2RRE | H11: [4] Engineering(Surname, Analyst2)
A12: 5 OE | B12: p2RRE | C12: Evidence name | D12: link | E12: engl | F12: none | G12: OE DB
A13: 5 OE | B13: p2RRE | C13: Evidence name | D13: link | E13: engl | F13: none | G13: OE DB
A14: 1 Prac_Group | B14: Level 2
A15: 2 Prac_OU | B15: PR 2.1 | C15: Develop and keep updated procedures and supporting materials used to prepare for and perform peer reviews. (Maximizes efficiency and effectiveness of finding issues in peer reviews.) 制定并保持更新的程序和支持材料，用于准备和执行同行评审。 （最大限度地提高在同行评审中发现问题的效率和效果。） | I15: - Training materials such as presentations or manuals explaining peer review processes and techniques. | J15: - Providing training sessions to familiarize team members with review processes and tools. | K15: - What procedures do you use to prepare and perform peer reviews? 准备和执行同行评审的步骤有哪些
A16: 4 Prac_Instan | B16: PR 2.1 | C16: p2RRE | H16: [4] Engineering(Surname, Analyst2)
A17: 5 OE | B17: p2RRE | C17: Evidence name | D17: link | E17: engl | F17: none | G17: OE DB
A18: 5 OE | B18: p2RRE | C18: Evidence name | D18: link | E18: engl | F18: none | G18: OE DB
A19: 2 Prac_OU | B19: PR 2.2 | C19: Select work products to be peer reviewed. (Manages cost by targeting critical work products for peer review.) 选择要进行同行评审的工作产品。 （通过针对关键工作产品进行同行评审来管理成本。） | I19: - Peer review schedule indicating the timeline for reviewing selected work products. | J19: - Establishing a peer review schedule to ensure timely assessment of selected work products. | K19: - How does choosing critical work products for peer review help manage costs effectively? 选择关键工作产品进行同行评审如何有效地管理成本？
A20: 4 Prac_Instan | B20: PR 2.2 | C20: p2RRE | H20: [4] Engineering(Surname, Analyst2)
A21: 5 OE | B21: p2RRE | C21: Evidence name | D21: link | E21: engl | F21: none | G21: OE DB
A22: 5 OE | B22: p2RRE | C22: Evidence name | D22: link | E22: engl | F22: none | G22: OE DB
A23: 2 Prac_OU | B23: PR 2.3 | C23: Prepare and perform peer reviews on selected work products using established procedures. (Reduces cost by thorough and consistent review to detect work product issues.) 使用既定程序对选定的工作产品进行准备和执行同行评审。 （通过彻底、一致的审查来检测工作产品问题，从而降低成本。） | I23: - Peer review feedback report summarizing the identified issues and recommendations for improvement. | J23: - Conducting thorough and consistent reviews according to the established guidelines. | K23: - Can you describe the peer review process, how is it performed from preparation to end? 同行评审的既定程序有哪些？请描述
A24: 4 Prac_Instan | B24: PR 2.3 | C24: p2RRE | H24: [4] Engineering(Surname, Analyst2)
A25: 5 OE | B25: p2RRE | C25: Evidence name | D25: link | E25: engl | F25: none | G25: OE DB
A26: 5 OE | B26: p2RRE | C26: Evidence name | D26: link | E26: engl | F26: none | G26: OE DB
A27: 2 Prac_OU | B27: PR 2.4 | C27: Resolve issues identified in peer reviews. (Reduces rework, costs, and increases quality.) 解决同行评审中发现的问题。 （减少返工、成本并提高质量。） | I27: - Issue closure reports summarizing the outcomes of resolved issues and lessons learned. | J27: - Tracking the progress of issue resolution and ensuring timely closure. | K27: - What do you do with issues identified during peer reviews? 如何解决同行评审中发现的问题
A28: 4 Prac_Instan | B28: PR 2.4 | C28: p2RRE | H28: [4] Engineering(Surname, Analyst2)
A29: 5 OE | B29: p2RRE | C29: Evidence name | D29: link | E29: engl | F29: none | G29: OE DB
A30: 5 OE | B30: p2RRE | C30: Evidence name | D30: link | E30: engl | F30: none | G30: OE DB
A31: 1 Prac_Group | B31: Level 3
A32: 2 Prac_OU | B32: PR 3.1 | C32: Analyze results and data from peer reviews. (Increases the efficiency and effectiveness of the process for performing peer reviews.) 分析同行评审的结果和数据。 （提高同行评审流程的效率和有效性。） | I32: - Action plans outlining steps to implement changes based on the analysis of peer review data. | J32: - Monitor the performance of processes for possible signals from peer review data | K32: - How does analyzing results and data from peer reviews contribute to increasing the efficiency and effectiveness of the peer review process? 分析同行评审的结果和数据如何提高同行评审流程的效率和有效性？
A33: 4 Prac_Instan | B33: PR 3.1 | C33: p2RRE | H33: [4] Engineering(Surname, Analyst2)
A34: 5 OE | B34: p2RRE | C34: Evidence name | D34: link | E34: engl | F34: none | G34: OE DB
A35: 5 OE | B35: p2RRE | C35: Evidence name | D35: link | E35: engl | F35: none | G35: OE DB

Sheet RDM
A1: REQUIREMENTS DEVELOPMENT AND MANAGEMENT
A2: 需求开发和管理
A3: Intent | B3: Elicits requirements, confirms common understanding by stakeholders, and aligns requirements, plans, and work products.
A4: 目的 | B4: 抽取需求，确保利益相关方取得一致理解，并调整需求、计划和工作产品
A5: Value | B5: Increases likelihood that the solution meets or exceeds customer expectations and needs.
A6: 价值 | B6: 确保客户地需求和期望得到满足
A8: Heading | B8: Level Practice Project OE Source | C8: OE reference | D8: URL | E8: Engl | F8: OE Type | G8: OE Source | H8: Affirmation Source (Session and Person) | I8: Suff. Artifact Yes | No | J8: Affirm. Yes | No | K8: Questions | L8: Weakness | M8: Strength | N8: Recommendations | O8: Rating/ Char | P8: Notes | Q8: Update Y
A9: 1 Prac_Group | B9: Level 1
