Workbook

Sheet Read Me
A1: The intent of this workbook is to accelerate the capture of appraisal information necessary to generate the RGS.
A3: The [CAS] worksheet provides nearly all the Benchmark Phase 1 data entry fields in CAS through RGS generation. However, the [CAS] worksheet allows the lead appraiser to filter the data entry fields to focus on only those necessary for RGS generation. The CAS Kit, as distributed, has the filter set to only display the critical path fields on the [CAS] worksheet, and has hidden the columns of the non-critical path fields on the other worksheets as well.
A5: Filtering is applied by the filter code in Column A as follows: 1: Required to be provided prior to generating the RGS; 2: Required to be provided, but not until after the RGS has been generated; 3: Optional information which need not be input into CAS at all; MM: Data fields required for multiple model appraisals (the CAS Kit still needs to be enhanced for multiple model appraisals).
A7: The fields in the workbook are named as they are in CAS, and are provided in the same order, as those in CAS. I might suggest that the lead appraiser populate as much of the [CAS] worksheet information as possible prior to sending it to the Site Coordinator to get the balance of the critical path information.
A9: Some of the CAS-exportable Excel worksheets have been included. Note that the CMMI Institute can change the CAS downloadable worksheets at any time, but the informational content of critical path information is unlikely to be as volatile. This workbook will be kept as up-to-date as possible. Note that the tabs in this workbook are a bit more "user friendly" than those in the CAS-downloaded worksheets, but that means you cannot import CAS Kit worksheets directly into CAS. When using the CAS Kit, information from the worksheets is input into CAS by: 1. Download the "official" Excel workbooks from CAS; 2. Cut and paste data from the CAS Kit worksheet into the CAS downloaded workbook; 3. Import the populated CAS downloaded workbook back into CAS.
A11: The prefix for the names of the spreadsheet in this CAS Kit workbook are: - "T#" - "T" for "CAS Template" and the # indicates the iteration number of the CAS template. E.g., T3 is the 3rd CAS downloadable template (the first two deal with ATM training and experience - non-critical path data elements). - "X" - indicates a useful template that is not downloaded from (or uploadable to) CAS.
A13: The "X" worksheets include: 1. X-CLs - used to indicate the Capability Levels to be evaluated for non-benchmark views 2. X-Sampling Factors - used to gather initial information on Sampling Factors and Sampling Factor Values 3. X-Support Function Exceptions - used to indicate which PAs apply for each Support Function 4. X-Project Exceptions - used to indicate which PAs do not apply for each project. 5. X-Appraisal Team - used to capture ATM data that can be imported through 2 CAS downloadable spreadsheets.
A15: Useful Information related to some of the worksheets included in this "CAS Kit" workbook is provided below.
A18: T3-Support Functions
A19: 1. Fields required to generate RGS
A20: B. Function Name
A21: D. Size (FTEs)
... A108: Finally, any PA that is changed from "In-Scope" for a Project should be accompanied by an explanation as to why that PA is not in scope.. A column has been provided to document that explanation. Some examples, which are still likely to result in Quality Flags during the pre-RGS generation Quality Review, are: 1. "This early-in-the-lifecycle project has not yet had the need or opportunity to conduct a formal decision-making process." 2. "The project is in the requirements elicitation phase and has not yet performed any VV-related activities." 3. "For this project, RDM is deemed Out-of-Scope as the customer has contracted with a 3rd party to generated the Requirements Specification and to process all requirement changes."

Sheet CAS
A2: 1 | B2: Filter code for Column A | F2: 1: Required to be provided prior to generating the RGS
A3: 2 | F3: 2: Required to be provided, but not until after the RGS has been generated
A4: 3 | F4: 3: Optional information which need not be input into CAS at all
A5: MM | F5: MM: Data fields required for multiple model appraisals
A6: 1 | B6: CAS Section
A7: 1 | C7: Subsection
A8: 1 | D8: Entry Field Section
A9: 1 | E9: CAS Entry Field
A10: 1 | F10: Entry Fields | G10: Notes
A11: 1 | B11: New Appraisal
A12: 1 | E12: Appraisal Type | F12: Benchmark
A13: 1
A14: 1 | B14: New Benchmark Appraisal | G14: Note that this will hereafter be displayed as "Appraisal Setup" / "Appraisal Name and Type"
A15: 1 | E15: Appraisal Name | F15: CAS Kit Example #2 Multiple Model Benchmark Appraisal
A16: 1 | E16: Time Zone | F16: India time zone | G16: <Pull down menu in CAS>
A17: 1 | E17: Partner | F17: PACT | G17: <Pull down menu in CAS>
A18: 1 | E18: Business and Appraisal Objectives | F18: TBD
A19: 2 | E19: ATM Signature Required | G19: <Yes/No>, defaults to No
A20: 2 | E20: Appraisal Virtually Delivered | G20: <Yes/No>, defaults to No
A21: 2 | E21: 1. Entire appraisal virtual? | G21: <Yes/No>, defaults to No
A22: 3 | E22: 2. Any part of the appraisal virtual? | G22: <Yes/No>, defaults to No
A23: 2 | E23: 3. Virtual Technique Description | G23: MDD Phase 1, MDD 2.1 (Collect and Examine OE), MDD 3.1 (Deliver Appraisal Results), MDD 4.1.1, MDD 4.1.2
A24: 1 | B24: [Click "Add Appraisal"]
A25: 1
A26: 1 | B26: Organization
A27: 1 | C27: Organizational Info
A28: 1 | D28: New Organization
A29: 1 | E29: Name | F29: ACME Software Inc. | G29: Enter legal name of company being appraised.
A30: 3 | E30: Native Language Name | G30: Legal name of the organization in native language. If native language is English, leave blank.
A31: 3 | E31: Address Line 1 | G31: Street address, PO Box, Company name c/o (care/of)
A32: 3 | E32: Address Line 2 | G32: Apartment, suite, unit, building, floor, etc.
A33: 3 | E33: City
A34: 3 | E34: State/Province/Region
A35: 3 | E35: Zip/Postal Code
A36: 3 | E36: Country | G36: <Pull down menu in CAS>
A37: 3 | E37: Website Address/URL
A38: 3 | E38: Rationale for Projects Excluded from OU
A39: 3 | E39: ISIC Section - Division | G39: <Pull down menu in CAS>
A40: 1 | D40: [Click "Add Organization"]
A41: 1
A42: 1 | C42: Organizational Units (OU)
A43: 1 | D43: New Organizational Unit
A44: 1 | E44: Name | F44: Software Engineering Group | G44: Enter a name for the OU. It cannot be the same as the organization's name.
A45: 3 | E45: Native Language Name | G45: Name of the OU in native language. If native language is English, leave blank.
A46: 1 | E46: Description | F46: TBD
A47: 3 | E47: Organizational Structure Description
A48: 1 | E48: Organizations | F48: ACME Software Inc. | G48: <Pull down menu in CAS> There will only be 1 Organization to choose from unless it's a multiple OU appraisal.
A49: 2 | E49: Number of Sr. Management (FTEs) | G49: "FTE" = "Full Time Equivalents"; This field is required even though the field does not indicate it in CAS
A50: 2 | E50: Number of Sr. Management Talked To | G50: This field is required even though the field does not indicate it in CAS
A51: 2 | E51: Has the OU been in any prior appraisals | G51: <Yes/No>, defaults to No
A52: 2 | E52: Enter Appraisal Number | G52: If this OU has multiple prior appraisals, enter numbers separated by commas (e.g., 1001, 2140)
A53: 1 | D53: [Click "Add Organizational Unit"]
A54: 1
A55: 1 | B55: Timeline and Scheduling
A56: 1 | C56: Appraisal Timeline
A57: 1 | D57: Phase 1: Plan Appraisal
A58: 1 | D58: [Click "Edit"]
A59: 1 | E59: Plan Appraisal Start Date | F59: 44141 | G59: Date for the start of the plan appraisal phase (YYYY/MM/DD)
A60: 1 | E60: Plan Appraisal End Date | F60: 44197 | G60: Date for the end of the plan appraisal phase (YYYY/MM/DD)
A61: 1 | D61: [Click "Save"]
A62: 1 | D62: Readiness Review | G62: Note that you can enter multiple Readiness Reviews
A63: 1 | D63: [Click "Edit"]
A64: 1 | E64: Readiness Review Name | F64: Readiness Review | G64: If only one Readiness Review, I typically call this "Readiness Review"
A65: 1 | E65: Readiness Review Start Date | F65: 44193 | G65: Note: Readiness review End Date must be prior to Phase 2 Start Date
A66: 1 | E66: Readiness Review End Date | F66: 44196
A67: 1 | D67: [Click "Save"]
A68: 1 | D68: Phase 2: Conduct Appraisal
A69: 1 | D69: [Click "Edit"]
A70: 1 | E70: Conduct Appraisal Start Date | F70: 44198 | G70: Note that this is the start of Phase 2 date, which may be earlier than the start of the "Onsite Period."
A71: 1 | E71: Conduct Appraisal End Date | F71: 44206
A72: 2 | E72: Days On Site
A73: 1 | D73: [Click "Save"]
A74: 2 | D74: Phase 3: Report Results
A75: 2 | D75: [Click "Edit"]
A76: 2 | E76: Report Results Start Date
A77: 2 | E77: Report Results End Date
A78: 2 | D78: [Click "Save"]
A79: 1
A80: 1 | B80: Appraisal Scope
A81: 1 | C81: Target Level | G81: NOTE: If you are selecting Capability Areas, but also want the appraisal to result in a Maturity Level rating, you MUST select the Maturity Level first, and then supplement that view with the additional PA/Capability Level combination. If you don't select the Maturity Level NOW, you will not be able to award a maturity level for this appraisal, even if the CL profile warrants it! Listen to the Section Help audio file associated with this webpage!
A82: 1 | C82: New Target
A83: 1 | D83: Target Type | G83: Select ML or CL option and define a target level per PA in the Target Level Detail step. If the sponsor wants both an ML and a CL profile, read the note in red above (and be prepared to pay 2 $900/appraisal fees).
A84: 1 | D84: Maturity Level
A85: 1 | E85: Maturity Level 2, 3, 4, 5 | F85: ML3 | G85: Radio buttons for <Maturity Level 2, Maturity Level 3, Maturity Level 4, Maturity Level 5>
A86: 1 | D86: Capability Level
A87: 1 | E87: Capability Level | G87: For maturity level-only appraisals, leave this radio button unchecked.
A88: 1 | D88: <Click "Next">
A89: 1 | D89: New Target
A90: 1 | E90: Maturity Level | G90: This is pre-filled (and unchangeable) based on the previous page
A91: 1 | E91: Model View | F91: CMMI-DEV without SAM V2.0 | G91: Pull down menu (CMMI-DEV w/ SAM, CMMI-DEV w/o SAM, CMMI-SVC w/ SAM, CMMI-SVC w/o SAM, CMMI-SPM)
A92: 1 | E92: Explain PA Exclusions | F92: The appraised organization does not use supplier to provide components or services for the products and services they produce for their clients. | G92: Explain why SAM is not applicable
A93: 1 | D93: <Click "Add Target">
A94: MM
A95: MM | D95: If multiple model view, fill in New Target info
A96: MM | D96: and fill in next 3 rows in the spreadsheet
A97: MM | D97: otherwise, skip to next section
A98: MM | D98: Maturity Level
A99: MM | E99: Maturity Level 2, 3, 4, 5 | F99: ML3 | G99: <ML2 - ML5>
A100: MM | D100: Capability Level
A101: MM | E101: Capability Level | G101: For maturity level-only appraisals, leave this radio button unchecked.
...

Sheet X-CLs
A1: CMMI-DEV Appraisal | T1: CMMI-SVC Appraisal
A2: PI Product Integration | B2: TS Technical Solution | C2: PQA Process Quality Assurance | D2: PR Peer Reviews | E2: RDM Requirements Development and Management | F2: VV Verification and Validation | G2: MPM Managing Performance and Measurement | H2: PAD Process Asset Development | I2: PCM Process Management | J2: RSK Risk and Opportunity Management | K2: OT Organizational Training | L2: EST Estimating | M2: MC Monitor and Control | N2: PLAN Planning | O2: CAR Causal Analysis and Resolution | P2: CM Configuration Management | Q2: DAR Decision Analysis and Resolution | R2: SAM Supplier Agreement Management | T2: SDM Service Delivery Management | U2: STSM Strategic Service Management | V2: PQA Process Quality Assurance | W2: PR Peer Reviews | X2: RDM Requirements Development and Management | Y2: VV Verification and Validation | Z2: MPM Managing Performance and Measurement | AA2: PAD Process Asset Development | AB2: PCM Process Management | AC2: CONT Continuity | AD2: IRP Incident Resolution and Prevention | AE2: RSK Risk and Opportunity Management | AF2: OT Organizational Training | AG2: EST Estimating | AH2: MC Monitor and Control | AI2: PLAN Planning | AJ2: CAR Causal Analysis and Resolution | AK2: CM Configuration Management | AL2: DAR Decision Analysis and Resolution | AM2: SAM Supplier Agreement Management
A3: CL0 | B3: CL0 | C3: CL0 | D3: CL0 | E3: CL0 | F3: CL0 | G3: CL0 | H3: CL0 | I3: CL0 | J3: CL0 | K3: CL0 | L3: CL0 | M3: CL0 | N3: CL0 | O3: CL0 | P3: CL0 | Q3: CL0 | R3: CL0 | T3: CL0 | U3: CL0 | V3: CL0 | W3: CL0 | X3: CL0 | Y3: CL0 | Z3: CL0 | AA3: CL0 | AB3: CL0 | AC3: CL0 | AD3: CL0 | AE3: CL0 | AF3: CL0 | AG3: CL0 | AH3: CL0 | AI3: CL0 | AJ3: CL0 | AK3: CL0 | AL3: CL0 | AM3: CL0
A50: CL0
A51: CL1
A52: CL2
A53: CL3

Sheet T3-Support Functions
A1: Database ID (blank for new records) | B1: Org Support Function Name (required) | C1: Project Type | D1: Size (FTEs) (required) | E1: Brief Function Description | F1: Is this function sensitive? (required) | G1: Point of Contact (required if project marked sensitive) | H1: Point of Contact's email address (required if project marked sensitive) | I1: Function Solution Domain | J1: Function Uses Suppliers (required) | K1: Current Function Manager's Name(s) | L1: Address Line 1 | M1: Address Line 2 | N1: City | O1: State/Province/Region | P1: ZIP/Postal Code | Q1: Country | R1: Additional Function Information
B2: EPG | D2: 5 | E2: Group primarily responsible for performance improvement. | F2: No | I2: All projects | J2: No | K2: Ed Pareto Gamma | N2: Beijing | Q2: China
B3: Training Group | D3: 3 | E3: Group primarily responsible for enhancing skills and knowledge. | F3: No | I3: All projects | J3: No | K3: Olivia Tetrus | N3: Moscow | Q3: Russia
B4: Configuration Management Group | D4: 4 | E4: Group that facilitates CM activities | F4: No | I4: All projects | J4: No | K4: Charles Munson | N4: Paris | Q4: France
B5: Process Assurance Group | D5: 3 | E5: Group that ensure compliance to work product standards and processes. | F5: No | I5: All projects | J5: No | K5: Processo Grupa | N5: Madrid | Q5: Spain

Sheet T4-Projects
A1: Database ID (blank for new records) | B1: Project Name (Not Updatable) | C1: Project Type | D1: Size (FTEs) (required) | E1: Brief Project Description (required) | F1: Is this project sensitive? (required) | G1: Point of Contact (required if project marked sensitive) | H1: Point of Contact's email address (required if project marked sensitive) | I1: Project Solution Domain (required) | J1: Business and Performance Objectives (required for Org Unit Projects only) | K1: Current Life Cycle Phase (required for Org Unit Projects only) | L1: Project Start Date (required for Org Unit Projects only) | M1: Project Projected End Date (required for Org Unit Projects only) | N1: Project Uses Suppliers (required) | O1: Current Project Manager's Name(s) (required) | P1: Address Line 1 (required) | Q1: Address Line 2 | R1: City (required) | S1: State/ Province/ Region | T1: ZIP/Postal Code | U1: Country (required) | V1: Additional Project Information
B2: Arizona Project | D2: 37 | F2: No | L2: 2020/2/6 | M2: 2021/10/19 | N2: No | O2: John Adams
B3: Florida Project | D3: 53 | F3: No | L3: 2020/6/25 | M3: 2021/11/13 | N3: No | O3: Thomas Jefferson
B4: South Carolina Project | D4: 42 | F4: No | L4: 2019/1/9 | M4: 2021/1/24 | N4: No | O4: Aaron Burr
B5: West Virginia Project | D5: 35 | F5: No | L5: 2018/6/26 | M5: 2021/9/20 | N5: No | O5: George Clinton
B6: Massachusetts Project | D6: 52 | F6: No | L6: 2020/1/19 | M6: 2022/5/25 | N6: No | O6: George Clinton
B7: Mississippi Project | D7: 50 | F7: No | L7: 2018/1/17 | M7: 2021/4/18 | N7: No | O7: Elbridge Gerry
B8: Delaware Project | D8: 17 | F8: No | L8: 2019/10/22 | M8: 2022/10/26 | N8: No | O8: Daniel Tompkins
B9: Hawaii Project | D9: 40 | F9: Yes | G9: Honolulu Jack | H9: Honolulu.Jack@ACME.com | L9: 2018/9/13 | M9: 2021/7/18 | N9: No | O9: John C. Calhoun
B10: Louisiana Project | D10: 11 | F10: No | L10: 2020/1/12 | M10: 2021/8/3 | N10: No | O10: John C. Calhoun
B11: PennsylvaniaRhode Island Project | D11: 42 | F11: No | L11: 2020/3/5 | M11: 2023/3/7 | N11: No | O11: Martin Van Buren
B12: Oregon Project | D12: 47 | F12: No | L12: 2018/9/5 | M12: 2021/7/16 | N12: No | O12: Richard M. Johnson
B13: New Hampshire Project | D13: 20 | F13: No | L13: 2020/6/13 | M13: 2022/10/21 | N13: No | O13: John Tyler
B14: IllinoisIndiana Project | D14: 43 | F14: No | L14: 2020/2/8 | M14: 2021/5/8 | N14: No | O14: George M. Dallas
B15: New Mexico Project | D15: 32 | F15: No | L15: 2019/2/2 | M15: 2020/6/7 | N15: No | O15: Millard Fillmore
B16: Kentucky Project | D16: 18 | F16: No | L16: 2019/10/13 | M16: 2021/2/13 | N16: No | O16: William R. King
B17: MontanaNebraska Project | D17: 26 | F17: No | L17: 2018/3/30 | M17: 2021/1/23 | N17: No | O17: John C. Breckinridge
B18: Arkansas Project | D18: 23 | F18: No | L18: 2019/5/7 | M18: 2021/9/28 | N18: No | O18: Hannibal Hamlin
B19: Alabama Project | D19: 39 | F19: No | L19: 2020/3/8 | M19: 2023/5/11 | N19: No | O19: Andrew Johnson
B20: North Carolina Project | D20: 18 | F20: No | L20: 2020/6/16 | M20: 2021/8/28 | N20: No | O20: Schuyler Colfax
B21: Washington Project | D21: 10 | F21: Yes | G21: Seattle Sam | H21: Seattle.Sam@ACME.com | L21: 2019/10/19 | M21: 2020/1/8 | N21: No | O21: Henry Wilson
B22: Missouri Project | D22: 45 | F22: No | L22: 2020/6/8 | M22: 2023/2/27 | N22: No | O22: William Wheeler
B23: North Dakota Project | D23: 14 | F23: No | L23: 2019/12/5 | M23: 2022/6/4 | N23: No | O23: Chester Arthur
B24: Kansas Project | D24: 46 | F24: No | L24: 2019/12/9 | M24: 2021/6/26 | N24: No | O24: Thomas A. Hendricks
B25: South Dakota Project | D25: 26 | F25: No | L25: 2018/7/16 | M25: 2020/11/20 | N25: No | O25: Levi P. Morton
B26: California Project | D26: 38 | F26: No | L26: 2019/8/17 | M26: 2020/8/6 | N26: No | O26: Adlai E. Stevenson
B27: Oklahoma Project | D27: 30 | F27: No | L27: 2020/4/17 | M27: 2022/5/27 | N27: No | O27: Garret A. Hobart
B28: Georgia Project | D28: 26 | F28: No | L28: 2019/12/23 | M28: 2020/5/30 | N28: No | O28: Theodore Roosevelt
B29: Connecticut Project | D29: 47 | F29: No | L29: 2018/9/30 | M29: 2022/9/6 | N29: No | O29: Charles Fairbanks
B30: Ohio Project | D30: 10 | F30: No | L30: 2019/4/21 | M30: 2022/5/8 | N30: No | O30: James Sherman
B31: New Jersey Project | D31: 54 | F31: No | L31: 2019/3/1 | M31: 2022/7/17 | N31: No | O31: Thomas R. Marshall
B32: Tennessee Project | D32: 19 | F32: No | L32: 2019/9/13 | M32: 2021/6/20 | N32: No | O32: Calvin Coolidge
B33: Virginia Project | D33: 37 | F33: No | L33: 2019/12/29 | M33: 2020/10/12 | N33: No | O33: Charles Dawes
... B38: Maryland Project | D38: 18 | F38: No | L38: 2020/3/22 | M38: 2023/8/15 | N38: No | O38: Alben Barkley

Sheet X-Sampling Factors
A1: Notes:
A2: 1. Sampling factors are "relevant" if they lead to process being performed in fundamentally different ways.
A3: A. For example, if the org has Waterfall projects and Agile projects, "Type of Work" would be a relevant sampling factor.
A4: 2. If this is a re-appraisal, the lead appraiser should populate the table below with the values from the previous appraisal.
A7: Candidate Sampling Factor | B7: Relevant? (Y/N) | C7: Sampling Factor Values | D7: Explanation
A8: Location | B8: N
A9: Size | B9: N
A10: Customer | B10: N
A11: Organizational Structure | B11: N
A12: Type of Work | B12: Y | C12: Development vs. Aplication Management & Support (AMS)
A13: Life Cycle | B13: Y | C13: Waterfall, Agile, Kanban
A14: <Other #2>
A16: Subgroups are combinations of sampling factors that represent one or more projects.
A17: (See example below and then list populated Subgroups here)
A19: Development/Waterfall
A20: Development/Agile
A21: AMS/Kanban
A27: EXAMPLE:
A29: Candidate Sampling Factor | B29: Relevant? (Y/N) | C29: Sampling Factor Values | D29: Explanation
A30: Location | B30: Y | C30: Chicago, Mumbai, Beijing | D30: Work is performed differently in each location.
A31: Size | B31: N | D31: Project processes are not affected by the size of the project.
A32: Customer | B32: Y | C32: Government, Commercial | D32: Work is performed differently depending on the type of customer.
A33: Organizational Structure | B33: N | D33: There is only 1 org structure in the appraisal scope.
A34: Type of Work | B34: Y | C34: Waterfall, Agile | D34: Two fundamentally different life cycles are used to perform the work.
A35: <Other #1>
A36: <Other #2>
A39: Possible subgroups are:
A40: Chicago, Government, Waterfall
A41: Chicago, Government, Agile
A42: Chicago, Commercial, Waterfall
A43: Chicago, Commercial, Agile
A44: Mumbai, Government, Waterfall
A45: Mumbai, Government, Agile
A46: Mumbai, Commercial, Waterfall
A47: Mumbai, Commercial, Agile
A48: Beijing, Government, Waterfall
... A58: Essentially, they are unique combinations of the key project attributes that need to be sampled to get a proper portfolio view of development/service activites.

Sheet T5-Subgroup Assignments
A1: Project (Copy list of projects from [T-4 Projects]) | B1: Subgroup | E1: Note: Download the Excel template from CAS and then indicate the subgroup associated with
A2: Alabama Project | B2: 2503 - Development/Agile (Development/Agile)
A3: Arizona Project | B3: 2503 - Development/Agile (Development/Agile) | E3: each project.
A4: Arkansas Project | B4: 2502 - Development/Waterfall (Development/Waterfall)
A5: California Project | B5: 2503 - Development/Agile (Development/Agile)
A6: Connecticut Project | B6: 2502 - Development/Waterfall (Development/Waterfall)
A7: Delaware Project | B7: 2502 - Development/Waterfall (Development/Waterfall)
A8: Florida Project | B8: 2503 - Development/Agile (Development/Agile)
A9: Georgia Project | B9: 2503 - Development/Agile (Development/Agile)
A10: Hawaii Project | B10: 2503 - Development/Agile (Development/Agile)
A11: IllinoisIndiana Project | B11: 2502 - Development/Waterfall (Development/Waterfall)
A12: Kansas Project | B12: 2502 - Development/Waterfall (Development/Waterfall)
A13: Kentucky Project | B13: 2503 - Development/Agile (Development/Agile)
A14: Louisiana Project | B14: 2503 - Development/Agile (Development/Agile)
A15: Maryland Project | B15: 2504 - AMS/Kanban (AMS/Kanban)
... A38: Wisconsin Project | B38: 2503 - Development/Agile (Development/Agile)

Sheet X-Support Function Exceptions
B1: CMMI-DEV Appraisal | V1: CMMI-SVC Appraisal
A2: Support Function (Copy list of support functions from [T-3 Support Functions]) | B2: PI Product Integration | C2: TS Technical Solution | D2: PQA Process Quality Assurance | E2: PR Peer Reviews | F2: RDM Requirements Development and Management | G2: VV Verification and Validation | H2: MPM Managing Performance and Measurement | I2: PAD Process Asset Development | J2: PCM Process Management | K2: RSK Risk and Opportunity Management | L2: OT Organizational Training | M2: EST Estimating | N2: MC Monitor and Control | O2: PLAN Planning | P2: CAR Causal Analysis and Resolution | Q2: CM Configuration Management | R2: DAR Decision Analysis and Resolution | S2: SAM Supplier Agreement Management | T2: Explanation for "In-Scope" and "In-Scope(Exclusive)" Practice Areas | V2: SDM Service Delivery Management | W2: STSM Strategic Service Management | X2: PQA Process Quality Assurance | Y2: PR Peer Reviews | Z2: RDM Requirements Development and Management | AA2: VV Verification and Validation | AB2: MPM Managing Performance and Measurement | AC2: PAD Process Asset Development | AD2: PCM Process Management | AE2: CONT Continuity | AF2: IRP Incident Resolution and Prevention | AG2: RSK Risk and Opportunity Management | AH2: OT Organizational Training | AI2: EST Estimating | AJ2: MC Monitor and Control | AK2: PLAN Planning | AL2: CAR Causal Analysis and Resolution | AM2: CM Configuration Management | AN2: DAR Decision Analysis and Resolution | AO2: SAM Supplier Agreement Management | AP2: Explanation for "In-Scope" and "In-Scope(Exclusive)" Practice Areas
A3: EPG | B3: =IF($A3="","","Out-of-Scope") -> Out-of-Scope | C3: =IF($A3="","","Out-of-Scope") -> Out-of-Scope | D3: =IF($A3="","","Out-of-Scope") -> Out-of-Scope | E3: =IF($A3="","","Out-of-Scope") -> Out-of-Scope | F3: =IF($A3="","","Out-of-Scope") -> Out-of-Scope | G3: =IF($A3="","","Out-of-Scope") -> Out-of-Scope | H3: =IF($A3="","","Out-of-Scope") -> Out-of-Scope | I3: In-Scope(Exclusive) | J3: In-Scope(Exclusive) | K3: =IF($A3="","","Out-of-Scope") -> Out-of-Scope | L3: =IF($A3="","","Out-of-Scope") -> Out-of-Scope | M3: =IF($A3="","","Out-of-Scope") -> Out-of-Scope | N3: =IF($A3="","","Out-of-Scope") -> Out-of-Scope | O3: =IF($A3="","","Out-of-Scope") -> Out-of-Scope | P3: In-Scope | Q3: =IF($A3="","","Out-of-Scope") -> Out-of-Scope | R3: In-Scope | S3: =IF($A3="","","Out-of-Scope") -> Out-of-Scope | T3: The EPG is the only group that does these PAD/PCM-related activities. The EPG uses DAR to prioritize candidate improvements The EPG uses CAR to analyze systemic issues. | V3: =IF($A3="","","Out-of-Scope") -> Out-of-Scope | W3: =IF($A3="","","Out-of-Scope") -> Out-of-Scope | X3: =IF($A3="","","Out-of-Scope") -> Out-of-Scope | Y3: =IF($A3="","","Out-of-Scope") -> Out-of-Scope | Z3: =IF($A3="","","Out-of-Scope") -> Out-of-Scope | AA3: =IF($A3="","","Out-of-Scope") -> Out-of-Scope | AB3: =IF($A3="","","Out-of-Scope") -> Out-of-Scope | AC3: =IF($A3="","","Out-of-Scope") -> Out-of-Scope | ... AO3: =IF($A3="","","Out-of-Scope") -> Out-of-Scope
A4: Training Group | B4: =IF($A4="","","Out-of-Scope") -> Out-of-Scope | C4: =IF($A4="","","Out-of-Scope") -> Out-of-Scope | D4: =IF($A4="","","Out-of-Scope") -> Out-of-Scope | E4: =IF($A4="","","Out-of-Scope") -> Out-of-Scope | F4: =IF($A4="","","Out-of-Scope") -> Out-of-Scope | G4: =IF($A4="","","Out-of-Scope") -> Out-of-Scope | H4: =IF($A4="","","Out-of-Scope") -> Out-of-Scope | I4: =IF($A4="","","Out-of-Scope") -> Out-of-Scope | ... K4: =IF($A4="","","Out-of-Scope") -> Out-of-Scope | L4: In-Scope(Exclusive) | M4: =IF($A4="","","Out-of-Scope") -> Out-of-Scope | N4: =IF($A4="","","Out-of-Scope") -> Out-of-Scope | O4: =IF($A4="","","Out-of-Scope") -> Out-of-Scope | P4: =IF($A4="","","Out-of-Scope") -> Out-of-Scope | Q4: =IF($A4="","","Out-of-Scope") -> Out-of-Scope | R4: =IF($A4="","","Out-of-Scope") -> Out-of-Scope | S4: =IF($A4="","","Out-of-Scope") -> Out-of-Scope | T4: Training Group is the only group thar facilitates OT-related activities. | V4: =IF($A4="","","Out-of-Scope") -> Out-of-Scope | W4: =IF($A4="","","Out-of-Scope") -> Out-of-Scope | X4: =IF($A4="","","Out-of-Scope") -> Out-of-Scope | Y4: =IF($A4="","","Out-of-Scope") -> Out-of-Scope | Z4: =IF($A4="","","Out-of-Scope") -> Out-of-Scope | AA4: =IF($A4="","","Out-of-Scope") -> Out-of-Scope | AB4: =IF($A4="","","Out-of-Scope") -> Out-of-Scope | AC4: =IF($A4="","","Out-of-Scope") -> Out-of-Scope | ... AO4: =IF($A4="","","Out-of-Scope") -> Out-of-Scope
A5: Configuration Management Group | B5: =IF($A5="","","Out-of-Scope") -> Out-of-Scope | C5: =IF($A5="","","Out-of-Scope") -> Out-of-Scope | D5: =IF($A5="","","Out-of-Scope") -> Out-of-Scope | E5: =IF($A5="","","Out-of-Scope") -> Out-of-Scope | F5: =IF($A5="","","Out-of-Scope") -> Out-of-Scope | G5: =IF($A5="","","Out-of-Scope") -> Out-of-Scope | H5: =IF($A5="","","Out-of-Scope") -> Out-of-Scope | I5: =IF($A5="","","Out-of-Scope") -> Out-of-Scope | ... P5: =IF($A5="","","Out-of-Scope") -> Out-of-Scope | Q5: In-Scope | R5: =IF($A5="","","Out-of-Scope") -> Out-of-Scope | S5: =IF($A5="","","Out-of-Scope") -> Out-of-Scope | T5: CM facilitates many of the CM-related activities. | V5: =IF($A5="","","Out-of-Scope") -> Out-of-Scope | W5: =IF($A5="","","Out-of-Scope") -> Out-of-Scope | X5: =IF($A5="","","Out-of-Scope") -> Out-of-Scope | Y5: =IF($A5="","","Out-of-Scope") -> Out-of-Scope | Z5: =IF($A5="","","Out-of-Scope") -> Out-of-Scope | AA5: =IF($A5="","","Out-of-Scope") -> Out-of-Scope | AB5: =IF($A5="","","Out-of-Scope") -> Out-of-Scope | AC5: =IF($A5="","","Out-of-Scope") -> Out-of-Scope | ... AL5: =IF($A5="","","Out-of-Scope") -> Out-of-Scope | AO5: =IF($A5="","","Out-of-Scope") -> Out-of-Scope
A6: Process Assurance Group | B6: =IF($A6="","","Out-of-Scope") -> Out-of-Scope | C6: =IF($A6="","","Out-of-Scope") -> Out-of-Scope | D6: In-Scope | E6: =IF($A6="","","Out-of-Scope") -> Out-of-Scope | F6: =IF($A6="","","Out-of-Scope") -> Out-of-Scope | G6: =IF($A6="","","Out-of-Scope") -> Out-of-Scope | H6: In-Scope | I6: =IF($A6="","","Out-of-Scope") -> Out-of-Scope | J6: =IF($A6="","","Out-of-Scope") -> Out-of-Scope | K6: =IF($A6="","","Out-of-Scope") -> Out-of-Scope | L6: =IF($A6="","","Out-of-Scope") -> Out-of-Scope | M6: =IF($A6="","","Out-of-Scope") -> Out-of-Scope | N6: =IF($A6="","","Out-of-Scope") -> Out-of-Scope | O6: =IF($A6="","","Out-of-Scope") -> Out-of-Scope | P6: =IF($A6="","","Out-of-Scope") -> Out-of-Scope | ... S6: =IF($A6="","","Out-of-Scope") -> Out-of-Scope | T6: PAG performs many of the PQA-related activities. PAG uses MPM-related activities to conduct trend analysis. | V6: =IF($A6="","","Out-of-Scope") -> Out-of-Scope | W6: =IF($A6="","","Out-of-Scope") -> Out-of-Scope | X6: =IF($A6="","","Out-of-Scope") -> Out-of-Scope | Y6: =IF($A6="","","Out-of-Scope") -> Out-of-Scope | Z6: =IF($A6="","","Out-of-Scope") -> Out-of-Scope | AA6: =IF($A6="","","Out-of-Scope") -> Out-of-Scope | AB6: =IF($A6="","","Out-of-Scope") -> Out-of-Scope | AC6: =IF($A6="","","Out-of-Scope") -> Out-of-Scope | ... AL6: =IF($A6="","","Out-of-Scope") -> Out-of-Scope | AO6: =IF($A6="","","Out-of-Scope") -> Out-of-Scope
B7: =IF($A7="","","Out-of-Scope") | C7: =IF($A7="","","Out-of-Scope") | D7: =IF($A7="","","Out-of-Scope") | E7: =IF($A7="","","Out-of-Scope") | F7: =IF($A7="","","Out-of-Scope") | G7: =IF($A7="","","Out-of-Scope") | H7: =IF($A7="","","Out-of-Scope") | I7: =IF($A7="","","Out-of-Scope") | ... S7: =IF($A7="","","Out-of-Scope") | V7: =IF($A7="","","Out-of-Scope") | W7: =IF($A7="","","Out-of-Scope") | X7: =IF($A7="","","Out-of-Scope") | Y7: =IF($A7="","","Out-of-Scope") | Z7: =IF($A7="","","Out-of-Scope") | AA7: =IF($A7="","","Out-of-Scope") | AB7: =IF($A7="","","Out-of-Scope") | AC7: =IF($A7="","","Out-of-Scope") | ... AL7: =IF($A7="","","Out-of-Scope") | AO7: =IF($A7="","","Out-of-Scope")
B8: =IF($A8="","","Out-of-Scope") | C8: =IF($A8="","","Out-of-Scope") | D8: =IF($A8="","","Out-of-Scope") | E8: =IF($A8="","","Out-of-Scope") | F8: =IF($A8="","","Out-of-Scope") | G8: =IF($A8="","","Out-of-Scope") | H8: =IF($A8="","","Out-of-Scope") | I8: =IF($A8="","","Out-of-Scope") | ... S8: =IF($A8="","","Out-of-Scope") | V8: =IF($A8="","","Out-of-Scope") | W8: =IF($A8="","","Out-of-Scope") | X8: =IF($A8="","","Out-of-Scope") | Y8: =IF($A8="","","Out-of-Scope") | Z8: =IF($A8="","","Out-of-Scope") | AA8: =IF($A8="","","Out-of-Scope") | AB8: =IF($A8="","","Out-of-Scope") | AC8: =IF($A8="","","Out-of-Scope") | ... AL8: =IF($A8="","","Out-of-Scope") | AO8: =IF($A8="","","Out-of-Scope")
B9: =IF($A9="","","Out-of-Scope") | C9: =IF($A9="","","Out-of-Scope") | D9: =IF($A9="","","Out-of-Scope") | E9: =IF($A9="","","Out-of-Scope") | F9: =IF($A9="","","Out-of-Scope") | G9: =IF($A9="","","Out-of-Scope") | H9: =IF($A9="","","Out-of-Scope") | I9: =IF($A9="","","Out-of-Scope") | ... S9: =IF($A9="","","Out-of-Scope") | V9: =IF($A9="","","Out-of-Scope") | W9: =IF($A9="","","Out-of-Scope") | X9: =IF($A9="","","Out-of-Scope") | Y9: =IF($A9="","","Out-of-Scope") | Z9: =IF($A9="","","Out-of-Scope") | AA9: =IF($A9="","","Out-of-Scope") | AB9: =IF($A9="","","Out-of-Scope") | AC9: =IF($A9="","","Out-of-Scope") | ... AL9: =IF($A9="","","Out-of-Scope") | AO9: =IF($A9="","","Out-of-Scope")
B10: =IF($A10="","","Out-of-Scope") | C10: =IF($A10="","","Out-of-Scope") | D10: =IF($A10="","","Out-of-Scope") | E10: =IF($A10="","","Out-of-Scope") | F10: =IF($A10="","","Out-of-Scope") | G10: =IF($A10="","","Out-of-Scope") | H10: =IF($A10="","","Out-of-Scope") | I10: =IF($A10="","","Out-of-Scope") | ... S10: =IF($A10="","","Out-of-Scope") | V10: =IF($A10="","","Out-of-Scope") | W10: =IF($A10="","","Out-of-Scope") | X10: =IF($A10="","","Out-of-Scope") | Y10: =IF($A10="","","Out-of-Scope") | Z10: =IF($A10="","","Out-of-Scope") | AA10: =IF($A10="","","Out-of-Scope") | AB10: =IF($A10="","","Out-of-Scope") | AC10: =IF($A10="","","Out-of-Scope") | ... AL10: =IF($A10="","","Out-of-Scope") | AO10: =IF($A10="","","Out-of-Scope")
B11: =IF($A11="","","Out-of-Scope") | C11: =IF($A11="","","Out-of-Scope") | D11: =IF($A11="","","Out-of-Scope") | E11: =IF($A11="","","Out-of-Scope") | F11: =IF($A11="","","Out-of-Scope") | G11: =IF($A11="","","Out-of-Scope") | H11: =IF($A11="","","Out-of-Scope") | I11: =IF($A11="","","Out-of-Scope") | ... S11: =IF($A11="","","Out-of-Scope") | V11: =IF($A11="","","Out-of-Scope") | W11: =IF($A11="","","Out-of-Scope") | X11: =IF($A11="","","Out-of-Scope") | Y11: =IF($A11="","","Out-of-Scope") | Z11: =IF($A11="","","Out-of-Scope") | AA11: =IF($A11="","","Out-of-Scope") | AB11: =IF($A11="","","Out-of-Scope") | AC11: =IF($A11="","","Out-of-Scope") | ... AL11: =IF($A11="","","Out-of-Scope") | AO11: =IF($A11="","","Out-of-Scope")
B12: =IF($A12="","","Out-of-Scope") | C12: =IF($A12="","","Out-of-Scope") | D12: =IF($A12="","","Out-of-Scope") | E12: =IF($A12="","","Out-of-Scope") | F12: =IF($A12="","","Out-of-Scope") | G12: =IF($A12="","","Out-of-Scope") | H12: =IF($A12="","","Out-of-Scope") | I12: =IF($A12="","","Out-of-Scope") | ... S12: =IF($A12="","","Out-of-Scope") | V12: =IF($A12="","","Out-of-Scope") | W12: =IF($A12="","","Out-of-Scope") | X12: =IF($A12="","","Out-of-Scope") | Y12: =IF($A12="","","Out-of-Scope") | Z12: =IF($A12="","","Out-of-Scope") | AA12: =IF($A12="","","Out-of-Scope") | AB12: =IF($A12="","","Out-of-Scope") | AC12: =IF($A12="","","Out-of-Scope") | ... AL12: =IF($A12="","","Out-of-Scope") | AO12: =IF($A12="","","Out-of-Scope")
B13: =IF($A13="","","Out-of-Scope") | C13: =IF($A13="","","Out-of-Scope") | D13: =IF($A13="","","Out-of-Scope") | E13: =IF($A13="","","Out-of-Scope") | F13: =IF($A13="","","Out-of-Scope") | G13: =IF($A13="","","Out-of-Scope") | H13: =IF($A13="","","Out-of-Scope") | I13: =IF($A13="","","Out-of-Scope") | ... S13: =IF($A13="","","Out-of-Scope") | V13: =IF($A13="","","Out-of-Scope") | W13: =IF($A13="","","Out-of-Scope") | X13: =IF($A13="","","Out-of-Scope") | Y13: =IF($A13="","","Out-of-Scope") | Z13: =IF($A13="","","Out-of-Scope") | AA13: =IF($A13="","","Out-of-Scope") | AB13: =IF($A13="","","Out-of-Scope") | AC13: =IF($A13="","","Out-of-Scope") | ... AL13: =IF($A13="","","Out-of-Scope") | AO13: =IF($A13="","","Out-of-Scope")
B14: =IF($A14="","","Out-of-Scope") | C14: =IF($A14="","","Out-of-Scope") | D14: =IF($A14="","","Out-of-Scope") | E14: =IF($A14="","","Out-of-Scope") | F14: =IF($A14="","","Out-of-Scope") | G14: =IF($A14="","","Out-of-Scope") | H14: =IF($A14="","","Out-of-Scope") | I14: =IF($A14="","","Out-of-Scope") | ... S14: =IF($A14="","","Out-of-Scope") | V14: =IF($A14="","","Out-of-Scope") | W14: =IF($A14="","","Out-of-Scope") | X14: =IF($A14="","","Out-of-Scope") | Y14: =IF($A14="","","Out-of-Scope") | Z14: =IF($A14="","","Out-of-Scope") | AA14: =IF($A14="","","Out-of-Scope") | AB14: =IF($A14="","","Out-of-Scope") | AC14: =IF($A14="","","Out-of-Scope") | ... AL14: =IF($A14="","","Out-of-Scope") | AO14: =IF($A14="","","Out-of-Scope")
B15: =IF($A15="","","Out-of-Scope") | C15: =IF($A15="","","Out-of-Scope") | D15: =IF($A15="","","Out-of-Scope") | E15: =IF($A15="","","Out-of-Scope") | F15: =IF($A15="","","Out-of-Scope") | G15: =IF($A15="","","Out-of-Scope") | H15: =IF($A15="","","Out-of-Scope") | I15: =IF($A15="","","Out-of-Scope") | ... S15: =IF($A15="","","Out-of-Scope") | V15: =IF($A15="","","Out-of-Scope") | W15: =IF($A15="","","Out-of-Scope") | X15: =IF($A15="","","Out-of-Scope") | Y15: =IF($A15="","","Out-of-Scope") | Z15: =IF($A15="","","Out-of-Scope") | AA15: =IF($A15="","","Out-of-Scope") | AB15: =IF($A15="","","Out-of-Scope") | AC15: =IF($A15="","","Out-of-Scope") | ... AL15: =IF($A15="","","Out-of-Scope") | AO15: =IF($A15="","","Out-of-Scope")
B16: =IF($A16="","","Out-of-Scope") | C16: =IF($A16="","","Out-of-Scope") | D16: =IF($A16="","","Out-of-Scope") | E16: =IF($A16="","","Out-of-Scope") | F16: =IF($A16="","","Out-of-Scope") | G16: =IF($A16="","","Out-of-Scope") | H16: =IF($A16="","","Out-of-Scope") | I16: =IF($A16="","","Out-of-Scope") | ... S16: =IF($A16="","","Out-of-Scope") | V16: =IF($A16="","","Out-of-Scope") | W16: =IF($A16="","","Out-of-Scope") | X16: =IF($A16="","","Out-of-Scope") | Y16: =IF($A16="","","Out-of-Scope") | Z16: =IF($A16="","","Out-of-Scope") | AA16: =IF($A16="","","Out-of-Scope") | AB16: =IF($A16="","","Out-of-Scope") | AC16: =IF($A16="","","Out-of-Scope") | ... AL16: =IF($A16="","","Out-of-Scope") | AO16: =IF($A16="","","Out-of-Scope")
B17: =IF($A17="","","Out-of-Scope") | C17: =IF($A17="","","Out-of-Scope") | D17: =IF($A17="","","Out-of-Scope") | E17: =IF($A17="","","Out-of-Scope") | F17: =IF($A17="","","Out-of-Scope") | G17: =IF($A17="","","Out-of-Scope") | H17: =IF($A17="","","Out-of-Scope") | I17: =IF($A17="","","Out-of-Scope") | ... S17: =IF($A17="","","Out-of-Scope") | V17: =IF($A17="","","Out-of-Scope") | W17: =IF($A17="","","Out-of-Scope") | X17: =IF($A17="","","Out-of-Scope") | Y17: =IF($A17="","","Out-of-Scope") | Z17: =IF($A17="","","Out-of-Scope") | AA17: =IF($A17="","","Out-of-Scope") | AB17: =IF($A17="","","Out-of-Scope") | AC17: =IF($A17="","","Out-of-Scope") | ... AL17: =IF($A17="","","Out-of-Scope") | AO17: =IF($A17="","","Out-of-Scope")
B18: =IF($A18="","","Out-of-Scope") | C18: =IF($A18="","","Out-of-Scope") | D18: =IF($A18="","","Out-of-Scope") | E18: =IF($A18="","","Out-of-Scope") | F18: =IF($A18="","","Out-of-Scope") | G18: =IF($A18="","","Out-of-Scope") | H18: =IF($A18="","","Out-of-Scope") | I18: =IF($A18="","","Out-of-Scope") | ... S18: =IF($A18="","","Out-of-Scope") | V18: =IF($A18="","","Out-of-Scope") | W18: =IF($A18="","","Out-of-Scope") | X18: =IF($A18="","","Out-of-Scope") | Y18: =IF($A18="","","Out-of-Scope") | Z18: =IF($A18="","","Out-of-Scope") | AA18: =IF($A18="","","Out-of-Scope") | AB18: =IF($A18="","","Out-of-Scope") | AC18: =IF($A18="","","Out-of-Scope") | ... AL18: =IF($A18="","","Out-of-Scope") | AO18: =IF($A18="","","Out-of-Scope")
... B52: =IF($A52="","","Out-of-Scope") | C52: =IF($A52="","","Out-of-Scope") | D52: =IF($A52="","","Out-of-Scope") | E52: =IF($A52="","","Out-of-Scope") | F52: =IF($A52="","","Out-of-Scope") | G52: =IF($A52="","","Out-of-Scope") | H52: =IF($A52="","","Out-of-Scope") | I52: =IF($A52="","","Out-of-Scope") | ... S52: =IF($A52="","","Out-of-Scope") | V52: =IF($A52="","","Out-of-Scope") | W52: =IF($A52="","","Out-of-Scope") | X52: =IF($A52="","","Out-of-Scope") | Y52: =IF($A52="","","Out-of-Scope") | Z52: =IF($A52="","","Out-of-Scope") | AA52: =IF($A52="","","Out-of-Scope") | AB52: =IF($A52="","","Out-of-Scope") | AC52: =IF($A52="","","Out-of-Scope") | ... AL52: =IF($A52="","","Out-of-Scope") | AO52: =IF($A52="","","Out-of-Scope")

Sheet X-Project Exceptions
B1: CMMI-DEV Appraisals | V1: CMMI-SVC Appraisals
A2: Project Name (Copy list of projects from [T-4 Projects]) | B2: PI Product Integration | C2: TS Technical Solution | D2: PQA Process Quality Assurance | E2: PR Peer Reviews | F2: RDM Requirements Development and Management | G2: VV Verification and Validation | H2: MPM Managing Performance and Measurement | I2: PAD Process Asset Development | J2: PCM Process Management | K2: RSK Risk and Opportunity Management | L2: OT Organizational Training | M2: EST Estimating | N2: MC Monitor and Control | O2: PLAN Planning | P2: CAR Causal Analysis and Resolution | Q2: CM Configuration Management | R2: DAR Decision Analysis and Resolution | S2: SAM Supplier Agreement Management | T2: Explanation for any Practice Area other than "In-Scope" | V2: SDM Service Delivery Management | W2: STSM Strategic Service Management | X2: PQA Process Quality Assurance | Y2: PR Peer Reviews | Z2: RDM Requirements Development and Management | AA2: VV Verification and Validation | AB2: MPM Managing Performance and Measurement | AC2: PAD Process Asset Development | AD2: PCM Process Management | AE2: CONT Continuity | AF2: IRP Incident Resolution and Prevention | AG2: RSK Risk and Opportunity Management | AH2: OT Organizational Training | AI2: EST Estimating | AJ2: MC Monitor and Control | AK2: PLAN Planning | AL2: CAR Causal Analysis and Resolution | AM2: CM Configuration Management | AN2: DAR Decision Analysis and Resolution | AO2: SAM Supplier Agreement Management | AP2: Explanation for any Practice Area other than "In-Scope"
A3: Arizona Project | B3: =IF($A3="","","In-Scope") -> In-Scope | C3: =IF($A3="","","In-Scope") -> In-Scope | D3: =IF($A3="","","In-Scope") -> In-Scope | E3: =IF($A3="","","In-Scope") -> In-Scope | F3: =IF($A3="","","In-Scope") -> In-Scope | G3: =IF($A3="","","In-Scope") -> In-Scope | H3: =IF($A3="","","In-Scope") -> In-Scope | I3: =IF($A3="","","Out-of-Scope") -> Out-of-Scope | J3: =IF($A3="","","Out-of-Scope") -> Out-of-Scope | K3: =IF($A3="","","In-Scope") -> In-Scope | L3: =IF($A3="","","Out-of-Scope") -> Out-of-Scope | M3: =IF($A3="","","In-Scope") -> In-Scope | N3: =IF($A3="","","In-Scope") -> In-Scope | O3: =IF($A3="","","In-Scope") -> In-Scope | P3: =IF($A3="","","In-Scope") -> In-Scope | Q3: =IF($A3="","","In-Scope") -> In-Scope | R3: =IF($A3="","","In-Scope") -> In-Scope | S3: =IF($A3="","","In-Scope") -> In-Scope | V3: =IF($A3="","","In-Scope") -> In-Scope | W3: =IF($A3="","","In-Scope") -> In-Scope | X3: =IF($A3="","","In-Scope") -> In-Scope | Y3: =IF($A3="","","In-Scope") -> In-Scope | Z3: =IF($A3="","","In-Scope") -> In-Scope | AA3: =IF($A3="","","In-Scope") -> In-Scope | AB3: =IF($A3="","","In-Scope") -> In-Scope | AC3: =IF($A3="","","In-Scope") -> In-Scope | ... AO3: =IF($A3="","","In-Scope") -> In-Scope
A4: Florida Project | B4: =IF($A4="","","In-Scope") -> In-Scope | C4: =IF($A4="","","In-Scope") -> In-Scope | D4: =IF($A4="","","In-Scope") -> In-Scope | E4: =IF($A4="","","In-Scope") -> In-Scope | F4: =IF($A4="","","In-Scope") -> In-Scope | G4: =IF($A4="","","In-Scope") -> In-Scope | H4: =IF($A4="","","In-Scope") -> In-Scope | I4: =IF($A4="","","Out-of-Scope") -> Out-of-Scope | J4: =IF($A4="","","Out-of-Scope") -> Out-of-Scope | K4: =IF($A4="","","In-Scope") -> In-Scope | L4: =IF($A4="","","Out-of-Scope") -> Out-of-Scope | M4: =IF($A4="","","In-Scope") -> In-Scope | N4: =IF($A4="","","In-Scope") -> In-Scope | O4: =IF($A4="","","In-Scope") -> In-Scope | P4: =IF($A4="","","In-Scope") -> In-Scope | Q4: =IF($A4="","","In-Scope") -> In-Scope | R4: =IF($A4="","","In-Scope") -> In-Scope | S4: =IF($A4="","","In-Scope") -> In-Scope | V4: =IF($A4="","","In-Scope") -> In-Scope | W4: =IF($A4="","","In-Scope") -> In-Scope | X4: =IF($A4="","","In-Scope") -> In-Scope | Y4: =IF($A4="","","In-Scope") -> In-Scope | Z4: =IF($A4="","","In-Scope") -> In-Scope | AA4: =IF($A4="","","In-Scope") -> In-Scope | AB4: =IF($A4="","","In-Scope") -> In-Scope | AC4: =IF($A4="","","In-Scope") -> In-Scope | ... AO4: =IF($A4="","","In-Scope") -> In-Scope
A5: South Carolina Project | B5: =IF($A5="","","In-Scope") -> In-Scope | C5: =IF($A5="","","In-Scope") -> In-Scope | D5: =IF($A5="","","In-Scope") -> In-Scope | E5: =IF($A5="","","In-Scope") -> In-Scope | F5: =IF($A5="","","In-Scope") -> In-Scope | G5: =IF($A5="","","In-Scope") -> In-Scope | H5: =IF($A5="","","In-Scope") -> In-Scope | I5: =IF($A5="","","Out-of-Scope") -> Out-of-Scope | J5: =IF($A5="","","Out-of-Scope") -> Out-of-Scope | K5: =IF($A5="","","In-Scope") -> In-Scope | L5: =IF($A5="","","Out-of-Scope") -> Out-of-Scope | M5: =IF($A5="","","In-Scope") -> In-Scope | N5: =IF($A5="","","In-Scope") -> In-Scope | O5: =IF($A5="","","In-Scope") -> In-Scope | P5: =IF($A5="","","In-Scope") -> In-Scope | Q5: =IF($A5="","","In-Scope") -> In-Scope | R5: =IF($A5="","","In-Scope") -> In-Scope | S5: =IF($A5="","","In-Scope") -> In-Scope | V5: =IF($A5="","","In-Scope") -> In-Scope | W5: =IF($A5="","","In-Scope") -> In-Scope | X5: =IF($A5="","","In-Scope") -> In-Scope | Y5: =IF($A5="","","In-Scope") -> In-Scope | Z5: =IF($A5="","","In-Scope") -> In-Scope | AA5: =IF($A5="","","In-Scope") -> In-Scope | AB5: =IF($A5="","","In-Scope") -> In-Scope | AC5: =IF($A5="","","In-Scope") -> In-Scope | ... AO5: =IF($A5="","","In-Scope") -> In-Scope
A6: West Virginia Project | B6: =IF($A6="","","In-Scope") -> In-Scope | C6: =IF($A6="","","In-Scope") -> In-Scope | D6: =IF($A6="","","In-Scope") -> In-Scope | E6: =IF($A6="","","In-Scope") -> In-Scope | F6: =IF($A6="","","In-Scope") -> In-Scope | G6: =IF($A6="","","In-Scope") -> In-Scope | H6: =IF($A6="","","In-Scope") -> In-Scope | I6: =IF($A6="","","Out-of-Scope") -> Out-of-Scope | J6: =IF($A6="","","Out-of-Scope") -> Out-of-Scope | K6: =IF($A6="","","In-Scope") -> In-Scope | L6: =IF($A6="","","Out-of-Scope") -> Out-of-Scope | M6: =IF($A6="","","In-Scope") -> In-Scope | N6: =IF($A6="","","In-Scope") -> In-Scope | O6: =IF($A6="","","In-Scope") -> In-Scope | P6: =IF($A6="","","In-Scope") -> In-Scope | Q6: =IF($A6="","","In-Scope") -> In-Scope | R6: =IF($A6="","","In-Scope") -> In-Scope | S6: =IF($A6="","","In-Scope") -> In-Scope | V6: =IF($A6="","","In-Scope") -> In-Scope | W6: =IF($A6="","","In-Scope") -> In-Scope | X6: =IF($A6="","","In-Scope") -> In-Scope | Y6: =IF($A6="","","In-Scope") -> In-Scope | Z6: =IF($A6="","","In-Scope") -> In-Scope | AA6: =IF($A6="","","In-Scope") -> In-Scope | AB6: =IF($A6="","","In-Scope") -> In-Scope | AC6: =IF($A6="","","In-Scope") -> In-Scope | ... AO6: =IF($A6="","","In-Scope") -> In-Scope
A7: Massachusetts Project | B7: =IF($A7="","","In-Scope") -> In-Scope | C7: =IF($A7="","","In-Scope") -> In-Scope | D7: =IF($A7="","","In-Scope") -> In-Scope | E7: =IF($A7="","","In-Scope") -> In-Scope | F7: =IF($A7="","","In-Scope") -> In-Scope | G7: =IF($A7="","","In-Scope") -> In-Scope | H7: =IF($A7="","","In-Scope") -> In-Scope | I7: =IF($A7="","","Out-of-Scope") -> Out-of-Scope | J7: =IF($A7="","","Out-of-Scope") -> Out-of-Scope | K7: =IF($A7="","","In-Scope") -> In-Scope | L7: =IF($A7="","","Out-of-Scope") -> Out-of-Scope | M7: =IF($A7="","","In-Scope") -> In-Scope | N7: =IF($A7="","","In-Scope") -> In-Scope | O7: =IF($A7="","","In-Scope") -> In-Scope | P7: =IF($A7="","","In-Scope") -> In-Scope | Q7: =IF($A7="","","In-Scope") -> In-Scope | R7: =IF($A7="","","In-Scope") -> In-Scope | S7: =IF($A7="","","In-Scope") -> In-Scope | V7: =IF($A7="","","In-Scope") -> In-Scope | W7: =IF($A7="","","In-Scope") -> In-Scope | X7: =IF($A7="","","In-Scope") -> In-Scope | Y7: =IF($A7="","","In-Scope") -> In-Scope | Z7: =IF($A7="","","In-Scope") -> In-Scope | AA7: =IF($A7="","","In-Scope") -> In-Scope | AB7: =IF($A7="","","In-Scope") -> In-Scope | AC7: =IF($A7="","","In-Scope") -> In-Scope | ... AO7: =IF($A7="","","In-Scope") -> In-Scope
A8: Mississippi Project | B8: =IF($A8="","","In-Scope") -> In-Scope | C8: =IF($A8="","","In-Scope") -> In-Scope | D8: =IF($A8="","","In-Scope") -> In-Scope | E8: =IF($A8="","","In-Scope") -> In-Scope | F8: =IF($A8="","","In-Scope") -> In-Scope | G8: =IF($A8="","","In-Scope") -> In-Scope | H8: =IF($A8="","","In-Scope") -> In-Scope | I8: =IF($A8="","","Out-of-Scope") -> Out-of-Scope | J8: =IF($A8="","","Out-of-Scope") -> Out-of-Scope | K8: =IF($A8="","","In-Scope") -> In-Scope | L8: =IF($A8="","","Out-of-Scope") -> Out-of-Scope | M8: =IF($A8="","","In-Scope") -> In-Scope | N8: =IF($A8="","","In-Scope") -> In-Scope | O8: =IF($A8="","","In-Scope") -> In-Scope | P8: =IF($A8="","","In-Scope") -> In-Scope | Q8: =IF($A8="","","In-Scope") -> In-Scope | R8: =IF($A8="","","In-Scope") -> In-Scope | S8: =IF($A8="","","In-Scope") -> In-Scope | V8: =IF($A8="","","In-Scope") -> In-Scope | W8: =IF($A8="","","In-Scope") -> In-Scope | X8: =IF($A8="","","In-Scope") -> In-Scope | Y8: =IF($A8="","","In-Scope") -> In-Scope | Z8: =IF($A8="","","In-Scope") -> In-Scope | AA8: =IF($A8="","","In-Scope") -> In-Scope | AB8: =IF($A8="","","In-Scope") -> In-Scope | AC8: =IF($A8="","","In-Scope") -> In-Scope | ... AO8: =IF($A8="","","In-Scope") -> In-Scope
A9: Delaware Project | B9: =IF($A9="","","In-Scope") -> In-Scope | C9: =IF($A9="","","In-Scope") -> In-Scope | D9: =IF($A9="","","In-Scope") -> In-Scope | E9: =IF($A9="","","In-Scope") -> In-Scope | F9: =IF($A9="","","In-Scope") -> In-Scope | G9: =IF($A9="","","In-Scope") -> In-Scope | H9: =IF($A9="","","In-Scope") -> In-Scope | I9: =IF($A9="","","Out-of-Scope") -> Out-of-Scope | J9: =IF($A9="","","Out-of-Scope") -> Out-of-Scope | K9: =IF($A9="","","In-Scope") -> In-Scope | L9: =IF($A9="","","Out-of-Scope") -> Out-of-Scope | M9: =IF($A9="","","In-Scope") -> In-Scope | N9: =IF($A9="","","In-Scope") -> In-Scope | O9: =IF($A9="","","In-Scope") -> In-Scope | P9: =IF($A9="","","In-Scope") -> In-Scope | Q9: =IF($A9="","","In-Scope") -> In-Scope | R9: =IF($A9="","","In-Scope") -> In-Scope | S9: =IF($A9="","","In-Scope") -> In-Scope | V9: =IF($A9="","","In-Scope") -> In-Scope | W9: =IF($A9="","","In-Scope") -> In-Scope | X9: =IF($A9="","","In-Scope") -> In-Scope | Y9: =IF($A9="","","In-Scope") -> In-Scope | Z9: =IF($A9="","","In-Scope") -> In-Scope | AA9: =IF($A9="","","In-Scope") -> In-Scope | AB9: =IF($A9="","","In-Scope") -> In-Scope | AC9: =IF($A9="","","In-Scope") -> In-Scope | ... AO9: =IF($A9="","","In-Scope") -> In-Scope
A10: Hawaii Project | B10: =IF($A10="","","In-Scope") -> In-Scope | C10: =IF($A10="","","In-Scope") -> In-Scope | D10: =IF($A10="","","In-Scope") -> In-Scope | E10: =IF($A10="","","In-Scope") -> In-Scope | F10: =IF($A10="","","In-Scope") -> In-Scope | G10: =IF($A10="","","In-Scope") -> In-Scope | H10: =IF($A10="","","In-Scope") -> In-Scope | I10: =IF($A10="","","Out-of-Scope") -> Out-of-Scope | J10: =IF($A10="","","Out-of-Scope") -> Out-of-Scope | K10: =IF($A10="","","In-Scope") -> In-Scope | L10: =IF($A10="","","Out-of-Scope") -> Out-of-Scope | M10: =IF($A10="","","In-Scope") -> In-Scope | N10: =IF($A10="","","In-Scope") -> In-Scope | O10: =IF($A10="","","In-Scope") -> In-Scope | P10: =IF($A10="","","In-Scope") -> In-Scope | Q10: =IF($A10="","","In-Scope") -> In-Scope | R10: =IF($A10="","","In-Scope") -> In-Scope | S10: =IF($A10="","","In-Scope") -> In-Scope | V10: =IF($A10="","","In-Scope") -> In-Scope | W10: =IF($A10="","","In-Scope") -> In-Scope | X10: =IF($A10="","","In-Scope") -> In-Scope | Y10: =IF($A10="","","In-Scope") -> In-Scope | Z10: =IF($A10="","","In-Scope") -> In-Scope | AA10: =IF($A10="","","In-Scope") -> In-Scope | AB10: =IF($A10="","","In-Scope") -> In-Scope | AC10: =IF($A10="","","In-Scope") -> In-Scope | ... AO10: =IF($A10="","","In-Scope") -> In-Scope
A11: Louisiana Project | B11: =IF($A11="","","In-Scope") -> In-Scope | C11: =IF($A11="","","In-Scope") -> In-Scope | D11: =IF($A11="","","In-Scope") -> In-Scope | E11: =IF($A11="","","In-Scope") -> In-Scope | F11: =IF($A11="","","In-Scope") -> In-Scope | G11: =IF($A11="","","In-Scope") -> In-Scope | H11: =IF($A11="","","In-Scope") -> In-Scope | I11: =IF($A11="","","Out-of-Scope") -> Out-of-Scope | J11: =IF($A11="","","Out-of-Scope") -> Out-of-Scope | K11: =IF($A11="","","In-Scope") -> In-Scope | L11: =IF($A11="","","Out-of-Scope") -> Out-of-Scope | M11: =IF($A11="","","In-Scope") -> In-Scope | N11: =IF($A11="","","In-Scope") -> In-Scope | O11: =IF($A11="","","In-Scope") -> In-Scope | P11: =IF($A11="","","In-Scope") -> In-Scope | Q11: =IF($A11="","","In-Scope") -> In-Scope | R11: =IF($A11="","","In-Scope") -> In-Scope | S11: =IF($A11="","","In-Scope") -> In-Scope | V11: =IF($A11="","","In-Scope") -> In-Scope | W11: =IF($A11="","","In-Scope") -> In-Scope | X11: =IF($A11="","","In-Scope") -> In-Scope | Y11: =IF($A11="","","In-Scope") -> In-Scope | Z11: =IF($A11="","","In-Scope") -> In-Scope | AA11: =IF($A11="","","In-Scope") -> In-Scope | AB11: =IF($A11="","","In-Scope") -> In-Scope | AC11: =IF($A11="","","In-Scope") -> In-Scope | ... AO11: =IF($A11="","","In-Scope") -> In-Scope
A12: PennsylvaniaRhode Island Project | B12: =IF($A12="","","In-Scope") -> In-Scope | C12: =IF($A12="","","In-Scope") -> In-Scope | D12: =IF($A12="","","In-Scope") -> In-Scope | E12: =IF($A12="","","In-Scope") -> In-Scope | F12: =IF($A12="","","In-Scope") -> In-Scope | G12: =IF($A12="","","In-Scope") -> In-Scope | H12: =IF($A12="","","In-Scope") -> In-Scope | I12: =IF($A12="","","Out-of-Scope") -> Out-of-Scope | J12: =IF($A12="","","Out-of-Scope") -> Out-of-Scope | K12: =IF($A12="","","In-Scope") -> In-Scope | L12: =IF($A12="","","Out-of-Scope") -> Out-of-Scope | M12: =IF($A12="","","In-Scope") -> In-Scope | N12: =IF($A12="","","In-Scope") -> In-Scope | O12: =IF($A12="","","In-Scope") -> In-Scope | P12: =IF($A12="","","In-Scope") -> In-Scope | Q12: =IF($A12="","","In-Scope") -> In-Scope | R12: =IF($A12="","","In-Scope") -> In-Scope | S12: =IF($A12="","","In-Scope") -> In-Scope | V12: =IF($A12="","","In-Scope") -> In-Scope | W12: =IF($A12="","","In-Scope") -> In-Scope | X12: =IF($A12="","","In-Scope") -> In-Scope | Y12: =IF($A12="","","In-Scope") -> In-Scope | Z12: =IF($A12="","","In-Scope") -> In-Scope | AA12: =IF($A12="","","In-Scope") -> In-Scope | AB12: =IF($A12="","","In-Scope") -> In-Scope | AC12: =IF($A12="","","In-Scope") -> In-Scope | ... AO12: =IF($A12="","","In-Scope") -> In-Scope
A13: Oregon Project | B13: =IF($A13="","","In-Scope") -> In-Scope | C13: =IF($A13="","","In-Scope") -> In-Scope | D13: =IF($A13="","","In-Scope") -> In-Scope | E13: =IF($A13="","","In-Scope") -> In-Scope | F13: =IF($A13="","","In-Scope") -> In-Scope | G13: =IF($A13="","","In-Scope") -> In-Scope | H13: =IF($A13="","","In-Scope") -> In-Scope | I13: =IF($A13="","","Out-of-Scope") -> Out-of-Scope | J13: =IF($A13="","","Out-of-Scope") -> Out-of-Scope | K13: =IF($A13="","","In-Scope") -> In-Scope | L13: =IF($A13="","","Out-of-Scope") -> Out-of-Scope | M13: =IF($A13="","","In-Scope") -> In-Scope | N13: =IF($A13="","","In-Scope") -> In-Scope | O13: =IF($A13="","","In-Scope") -> In-Scope | P13: =IF($A13="","","In-Scope") -> In-Scope | Q13: =IF($A13="","","In-Scope") -> In-Scope | R13: =IF($A13="","","In-Scope") -> In-Scope | S13: =IF($A13="","","In-Scope") -> In-Scope | V13: =IF($A13="","","In-Scope") -> In-Scope | W13: =IF($A13="","","In-Scope") -> In-Scope | X13: =IF($A13="","","In-Scope") -> In-Scope | Y13: =IF($A13="","","In-Scope") -> In-Scope | Z13: =IF($A13="","","In-Scope") -> In-Scope | AA13: =IF($A13="","","In-Scope") -> In-Scope | AB13: =IF($A13="","","In-Scope") -> In-Scope | AC13: =IF($A13="","","In-Scope") -> In-Scope | ... AO13: =IF($A13="","","In-Scope") -> In-Scope
A14: New Hampshire Project | B14: =IF($A14="","","In-Scope") -> In-Scope | C14: =IF($A14="","","In-Scope") -> In-Scope | D14: =IF($A14="","","In-Scope") -> In-Scope | E14: =IF($A14="","","In-Scope") -> In-Scope | F14: =IF($A14="","","In-Scope") -> In-Scope | G14: =IF($A14="","","In-Scope") -> In-Scope | H14: =IF($A14="","","In-Scope") -> In-Scope | I14: =IF($A14="","","Out-of-Scope") -> Out-of-Scope | J14: =IF($A14="","","Out-of-Scope") -> Out-of-Scope | K14: =IF($A14="","","In-Scope") -> In-Scope | L14: =IF($A14="","","Out-of-Scope") -> Out-of-Scope | M14: =IF($A14="","","In-Scope") -> In-Scope | N14: =IF($A14="","","In-Scope") -> In-Scope | O14: =IF($A14="","","In-Scope") -> In-Scope | P14: =IF($A14="","","In-Scope") -> In-Scope | Q14: =IF($A14="","","In-Scope") -> In-Scope | R14: =IF($A14="","","In-Scope") -> In-Scope | S14: =IF($A14="","","In-Scope") -> In-Scope | V14: =IF($A14="","","In-Scope") -> In-Scope | W14: =IF($A14="","","In-Scope") -> In-Scope | X14: =IF($A14="","","In-Scope") -> In-Scope | Y14: =IF($A14="","","In-Scope") -> In-Scope | Z14: =IF($A14="","","In-Scope") -> In-Scope | AA14: =IF($A14="","","In-Scope") -> In-Scope | AB14: =IF($A14="","","In-Scope") -> In-Scope | AC14: =IF($A14="","","In-Scope") -> In-Scope | ... AO14: =IF($A14="","","In-Scope") -> In-Scope
A15: IllinoisIndiana Project | B15: =IF($A15="","","In-Scope") -> In-Scope | C15: =IF($A15="","","In-Scope") -> In-Scope | D15: =IF($A15="","","In-Scope") -> In-Scope | E15: =IF($A15="","","In-Scope") -> In-Scope | F15: =IF($A15="","","In-Scope") -> In-Scope | G15: =IF($A15="","","In-Scope") -> In-Scope | H15: =IF($A15="","","In-Scope") -> In-Scope | I15: =IF($A15="","","Out-of-Scope") -> Out-of-Scope | J15: =IF($A15="","","Out-of-Scope") -> Out-of-Scope | K15: =IF($A15="","","In-Scope") -> In-Scope | L15: =IF($A15="","","Out-of-Scope") -> Out-of-Scope | M15: =IF($A15="","","In-Scope") -> In-Scope | N15: =IF($A15="","","In-Scope") -> In-Scope | O15: =IF($A15="","","In-Scope") -> In-Scope | P15: =IF($A15="","","In-Scope") -> In-Scope | Q15: =IF($A15="","","In-Scope") -> In-Scope | R15: =IF($A15="","","In-Scope") -> In-Scope | S15: =IF($A15="","","In-Scope") -> In-Scope | V15: =IF($A15="","","In-Scope") -> In-Scope | W15: =IF($A15="","","In-Scope") -> In-Scope | X15: =IF($A15="","","In-Scope") -> In-Scope | Y15: =IF($A15="","","In-Scope") -> In-Scope | Z15: =IF($A15="","","In-Scope") -> In-Scope | AA15: =IF($A15="","","In-Scope") -> In-Scope | AB15: =IF($A15="","","In-Scope") -> In-Scope | AC15: =IF($A15="","","In-Scope") -> In-Scope | ... AO15: =IF($A15="","","In-Scope") -> In-Scope
A16: New Mexico Project | B16: =IF($A16="","","In-Scope") -> In-Scope | C16: =IF($A16="","","In-Scope") -> In-Scope | D16: =IF($A16="","","In-Scope") -> In-Scope | E16: =IF($A16="","","In-Scope") -> In-Scope | F16: =IF($A16="","","Out-of-Scope") -> Out-of-Scope | G16: =IF($A16="","","In-Scope") -> In-Scope | H16: =IF($A16="","","In-Scope") -> In-Scope | I16: =IF($A16="","","Out-of-Scope") -> Out-of-Scope | J16: =IF($A16="","","Out-of-Scope") -> Out-of-Scope | K16: =IF($A16="","","In-Scope") -> In-Scope | L16: =IF($A16="","","Out-of-Scope") -> Out-of-Scope | M16: =IF($A16="","","In-Scope") -> In-Scope | N16: =IF($A16="","","In-Scope") -> In-Scope | O16: =IF($A16="","","In-Scope") -> In-Scope | P16: =IF($A16="","","In-Scope") -> In-Scope | Q16: =IF($A16="","","In-Scope") -> In-Scope | R16: =IF($A16="","","In-Scope") -> In-Scope | S16: =IF($A16="","","In-Scope") -> In-Scope | T16: RDM: The client contracted with a 3rd party to gneerate and manage the requirements | V16: =IF($A16="","","In-Scope") -> In-Scope | W16: =IF($A16="","","In-Scope") -> In-Scope | X16: =IF($A16="","","In-Scope") -> In-Scope | Y16: =IF($A16="","","In-Scope") -> In-Scope | Z16: =IF($A16="","","In-Scope") -> In-Scope | AA16: =IF($A16="","","In-Scope") -> In-Scope | AB16: =IF($A16="","","In-Scope") -> In-Scope | AC16: =IF($A16="","","In-Scope") -> In-Scope | ... AO16: =IF($A16="","","In-Scope") -> In-Scope
A17: Kentucky Project | B17: =IF($A17="","","In-Scope") -> In-Scope | C17: =IF($A17="","","In-Scope") -> In-Scope | D17: =IF($A17="","","In-Scope") -> In-Scope | E17: =IF($A17="","","In-Scope") -> In-Scope | F17: =IF($A17="","","In-Scope") -> In-Scope | G17: =IF($A17="","","In-Scope") -> In-Scope | H17: =IF($A17="","","In-Scope") -> In-Scope | I17: =IF($A17="","","Out-of-Scope") -> Out-of-Scope | J17: =IF($A17="","","Out-of-Scope") -> Out-of-Scope | K17: =IF($A17="","","In-Scope") -> In-Scope | L17: =IF($A17="","","Out-of-Scope") -> Out-of-Scope | M17: =IF($A17="","","In-Scope") -> In-Scope | N17: =IF($A17="","","In-Scope") -> In-Scope | O17: =IF($A17="","","In-Scope") -> In-Scope | P17: =IF($A17="","","In-Scope") -> In-Scope | Q17: =IF($A17="","","In-Scope") -> In-Scope | R17: =IF($A17="","","In-Scope") -> In-Scope | S17: =IF($A17="","","In-Scope") -> In-Scope | V17: =IF($A17="","","In-Scope") -> In-Scope | W17: =IF($A17="","","In-Scope") -> In-Scope | X17: =IF($A17="","","In-Scope") -> In-Scope | Y17: =IF($A17="","","In-Scope") -> In-Scope | Z17: =IF($A17="","","In-Scope") -> In-Scope | AA17: =IF($A17="","","In-Scope") -> In-Scope | AB17: =IF($A17="","","In-Scope") -> In-Scope | AC17: =IF($A17="","","In-Scope") -> In-Scope | ... AO17: =IF($A17="","","In-Scope") -> In-Scope
A18: MontanaNebraska Project | B18: =IF($A18="","","In-Scope") -> In-Scope | C18: =IF($A18="","","In-Scope") -> In-Scope | D18: =IF($A18="","","In-Scope") -> In-Scope | E18: =IF($A18="","","In-Scope") -> In-Scope | F18: =IF($A18="","","In-Scope") -> In-Scope | G18: =IF($A18="","","In-Scope") -> In-Scope | H18: =IF($A18="","","In-Scope") -> In-Scope | I18: =IF($A18="","","Out-of-Scope") -> Out-of-Scope | J18: =IF($A18="","","Out-of-Scope") -> Out-of-Scope | K18: =IF($A18="","","In-Scope") -> In-Scope | L18: =IF($A18="","","Out-of-Scope") -> Out-of-Scope | M18: =IF($A18="","","In-Scope") -> In-Scope | N18: =IF($A18="","","In-Scope") -> In-Scope | O18: =IF($A18="","","In-Scope") -> In-Scope | P18: =IF($A18="","","In-Scope") -> In-Scope | Q18: =IF($A18="","","In-Scope") -> In-Scope | R18: =IF($A18="","","In-Scope") -> In-Scope | S18: =IF($A18="","","In-Scope") -> In-Scope | V18: =IF($A18="","","In-Scope") -> In-Scope | W18: =IF($A18="","","In-Scope") -> In-Scope | X18: =IF($A18="","","In-Scope") -> In-Scope | Y18: =IF($A18="","","In-Scope") -> In-Scope | Z18: =IF($A18="","","In-Scope") -> In-Scope | AA18: =IF($A18="","","In-Scope") -> In-Scope | AB18: =IF($A18="","","In-Scope") -> In-Scope | AC18: =IF($A18="","","In-Scope") -> In-Scope | ... AO18: =IF($A18="","","In-Scope") -> In-Scope
A19: Arkansas Project | B19: =IF($A19="","","In-Scope") -> In-Scope | C19: =IF($A19="","","In-Scope") -> In-Scope | D19: =IF($A19="","","In-Scope") -> In-Scope | E19: =IF($A19="","","In-Scope") -> In-Scope | F19: =IF($A19="","","In-Scope") -> In-Scope | G19: =IF($A19="","","In-Scope") -> In-Scope | H19: =IF($A19="","","In-Scope") -> In-Scope | I19: =IF($A19="","","Out-of-Scope") -> Out-of-Scope | J19: =IF($A19="","","Out-of-Scope") -> Out-of-Scope | K19: =IF($A19="","","In-Scope") -> In-Scope | L19: =IF($A19="","","Out-of-Scope") -> Out-of-Scope | M19: =IF($A19="","","In-Scope") -> In-Scope | N19: =IF($A19="","","In-Scope") -> In-Scope | O19: =IF($A19="","","In-Scope") -> In-Scope | P19: =IF($A19="","","In-Scope") -> In-Scope | Q19: =IF($A19="","","In-Scope") -> In-Scope | R19: =IF($A19="","","In-Scope") -> In-Scope | S19: =IF($A19="","","In-Scope") -> In-Scope | V19: =IF($A19="","","In-Scope") -> In-Scope | W19: =IF($A19="","","In-Scope") -> In-Scope | X19: =IF($A19="","","In-Scope") -> In-Scope | Y19: =IF($A19="","","In-Scope") -> In-Scope | Z19: =IF($A19="","","In-Scope") -> In-Scope | AA19: =IF($A19="","","In-Scope") -> In-Scope | AB19: =IF($A19="","","In-Scope") -> In-Scope | AC19: =IF($A19="","","In-Scope") -> In-Scope | ... AO19: =IF($A19="","","In-Scope") -> In-Scope
A20: Alabama Project | B20: =IF($A20="","","In-Scope") -> In-Scope | C20: =IF($A20="","","In-Scope") -> In-Scope | D20: =IF($A20="","","In-Scope") -> In-Scope | E20: =IF($A20="","","In-Scope") -> In-Scope | F20: =IF($A20="","","In-Scope") -> In-Scope | G20: =IF($A20="","","In-Scope") -> In-Scope | H20: =IF($A20="","","In-Scope") -> In-Scope | I20: =IF($A20="","","Out-of-Scope") -> Out-of-Scope | J20: =IF($A20="","","Out-of-Scope") -> Out-of-Scope | K20: =IF($A20="","","In-Scope") -> In-Scope | L20: =IF($A20="","","Out-of-Scope") -> Out-of-Scope | M20: =IF($A20="","","In-Scope") -> In-Scope | N20: =IF($A20="","","In-Scope") -> In-Scope | O20: =IF($A20="","","In-Scope") -> In-Scope | P20: =IF($A20="","","In-Scope") -> In-Scope | Q20: =IF($A20="","","In-Scope") -> In-Scope | R20: =IF($A20="","","In-Scope") -> In-Scope | S20: =IF($A20="","","In-Scope") -> In-Scope | V20: =IF($A20="","","In-Scope") -> In-Scope | W20: =IF($A20="","","In-Scope") -> In-Scope | X20: =IF($A20="","","In-Scope") -> In-Scope | Y20: =IF($A20="","","In-Scope") -> In-Scope | Z20: =IF($A20="","","In-Scope") -> In-Scope | AA20: =IF($A20="","","In-Scope") -> In-Scope | AB20: =IF($A20="","","In-Scope") -> In-Scope | AC20: =IF($A20="","","In-Scope") -> In-Scope | ... AO20: =IF($A20="","","In-Scope") -> In-Scope
A21: North Carolina Project | B21: =IF($A21="","","In-Scope") -> In-Scope | C21: =IF($A21="","","In-Scope") -> In-Scope | D21: =IF($A21="","","In-Scope") -> In-Scope | E21: =IF($A21="","","In-Scope") -> In-Scope | F21: =IF($A21="","","In-Scope") -> In-Scope | G21: =IF($A21="","","In-Scope") -> In-Scope | H21: =IF($A21="","","In-Scope") -> In-Scope | I21: =IF($A21="","","Out-of-Scope") -> Out-of-Scope | J21: =IF($A21="","","Out-of-Scope") -> Out-of-Scope | K21: =IF($A21="","","In-Scope") -> In-Scope | L21: =IF($A21="","","Out-of-Scope") -> Out-of-Scope | M21: =IF($A21="","","In-Scope") -> In-Scope | N21: =IF($A21="","","In-Scope") -> In-Scope | O21: =IF($A21="","","In-Scope") -> In-Scope | P21: =IF($A21="","","In-Scope") -> In-Scope | Q21: =IF($A21="","","In-Scope") -> In-Scope | R21: =IF($A21="","","In-Scope") -> In-Scope | S21: =IF($A21="","","In-Scope") -> In-Scope | V21: =IF($A21="","","In-Scope") -> In-Scope | W21: =IF($A21="","","In-Scope") -> In-Scope | X21: =IF($A21="","","In-Scope") -> In-Scope | Y21: =IF($A21="","","In-Scope") -> In-Scope | Z21: =IF($A21="","","In-Scope") -> In-Scope | AA21: =IF($A21="","","In-Scope") -> In-Scope | AB21: =IF($A21="","","In-Scope") -> In-Scope | AC21: =IF($A21="","","In-Scope") -> In-Scope | ... AO21: =IF($A21="","","In-Scope") -> In-Scope
A22: Washington Project | B22: =IF($A22="","","In-Scope") -> In-Scope | C22: =IF($A22="","","In-Scope") -> In-Scope | D22: =IF($A22="","","In-Scope") -> In-Scope | E22: =IF($A22="","","In-Scope") -> In-Scope | F22: =IF($A22="","","In-Scope") -> In-Scope | G22: =IF($A22="","","In-Scope") -> In-Scope | H22: =IF($A22="","","In-Scope") -> In-Scope | I22: =IF($A22="","","Out-of-Scope") -> Out-of-Scope | J22: =IF($A22="","","Out-of-Scope") -> Out-of-Scope | K22: =IF($A22="","","In-Scope") -> In-Scope | L22: =IF($A22="","","Out-of-Scope") -> Out-of-Scope | M22: =IF($A22="","","In-Scope") -> In-Scope | N22: =IF($A22="","","In-Scope") -> In-Scope | O22: =IF($A22="","","In-Scope") -> In-Scope | P22: =IF($A22="","","In-Scope") -> In-Scope | Q22: =IF($A22="","","In-Scope") -> In-Scope | R22: =IF($A22="","","In-Scope") -> In-Scope | S22: =IF($A22="","","In-Scope") -> In-Scope | V22: =IF($A22="","","In-Scope") -> In-Scope | W22: =IF($A22="","","In-Scope") -> In-Scope | X22: =IF($A22="","","In-Scope") -> In-Scope | Y22: =IF($A22="","","In-Scope") -> In-Scope | Z22: =IF($A22="","","In-Scope") -> In-Scope | AA22: =IF($A22="","","In-Scope") -> In-Scope | AB22: =IF($A22="","","In-Scope") -> In-Scope | AC22: =IF($A22="","","In-Scope") -> In-Scope | ... AO22: =IF($A22="","","In-Scope") -> In-Scope
A23: Missouri Project | B23: =IF($A23="","","In-Scope") -> In-Scope | C23: =IF($A23="","","In-Scope") -> In-Scope | D23: =IF($A23="","","In-Scope") -> In-Scope | E23: =IF($A23="","","In-Scope") -> In-Scope | F23: =IF($A23="","","In-Scope") -> In-Scope | G23: =IF($A23="","","In-Scope") -> In-Scope | H23: =IF($A23="","","In-Scope") -> In-Scope | I23: =IF($A23="","","Out-of-Scope") -> Out-of-Scope | J23: =IF($A23="","","Out-of-Scope") -> Out-of-Scope | K23: =IF($A23="","","In-Scope") -> In-Scope | L23: =IF($A23="","","Out-of-Scope") -> Out-of-Scope | M23: =IF($A23="","","In-Scope") -> In-Scope | N23: =IF($A23="","","In-Scope") -> In-Scope | O23: =IF($A23="","","In-Scope") -> In-Scope | P23: =IF($A23="","","In-Scope") -> In-Scope | Q23: =IF($A23="","","In-Scope") -> In-Scope | R23: Not Yet | S23: =IF($A23="","","In-Scope") -> In-Scope | T23: The project has not yet had the need or opportunity to use DAR. | V23: =IF($A23="","","In-Scope") -> In-Scope | W23: =IF($A23="","","In-Scope") -> In-Scope | X23: =IF($A23="","","In-Scope") -> In-Scope | Y23: =IF($A23="","","In-Scope") -> In-Scope | Z23: =IF($A23="","","In-Scope") -> In-Scope | AA23: =IF($A23="","","In-Scope") -> In-Scope | AB23: =IF($A23="","","In-Scope") -> In-Scope | AC23: =IF($A23="","","In-Scope") -> In-Scope | ... AO23: =IF($A23="","","In-Scope") -> In-Scope
A24: North Dakota Project | B24: =IF($A24="","","In-Scope") -> In-Scope | C24: =IF($A24="","","In-Scope") -> In-Scope | D24: =IF($A24="","","In-Scope") -> In-Scope | E24: =IF($A24="","","In-Scope") -> In-Scope | F24: =IF($A24="","","In-Scope") -> In-Scope | G24: =IF($A24="","","In-Scope") -> In-Scope | H24: =IF($A24="","","In-Scope") -> In-Scope | I24: =IF($A24="","","Out-of-Scope") -> Out-of-Scope | J24: =IF($A24="","","Out-of-Scope") -> Out-of-Scope | K24: =IF($A24="","","In-Scope") -> In-Scope | L24: =IF($A24="","","Out-of-Scope") -> Out-of-Scope | M24: =IF($A24="","","In-Scope") -> In-Scope | N24: =IF($A24="","","In-Scope") -> In-Scope | O24: =IF($A24="","","In-Scope") -> In-Scope | P24: =IF($A24="","","In-Scope") -> In-Scope | Q24: =IF($A24="","","In-Scope") -> In-Scope | R24: =IF($A24="","","In-Scope") -> In-Scope | S24: =IF($A24="","","In-Scope") -> In-Scope | V24: =IF($A24="","","In-Scope") -> In-Scope | W24: =IF($A24="","","In-Scope") -> In-Scope | X24: =IF($A24="","","In-Scope") -> In-Scope | Y24: =IF($A24="","","In-Scope") -> In-Scope | Z24: =IF($A24="","","In-Scope") -> In-Scope | AA24: =IF($A24="","","In-Scope") -> In-Scope | AB24: =IF($A24="","","In-Scope") -> In-Scope | AC24: =IF($A24="","","In-Scope") -> In-Scope | ... AO24: =IF($A24="","","In-Scope") -> In-Scope
A25: Kansas Project | B25: =IF($A25="","","In-Scope") -> In-Scope | C25: =IF($A25="","","In-Scope") -> In-Scope | D25: =IF($A25="","","In-Scope") -> In-Scope | E25: =IF($A25="","","In-Scope") -> In-Scope | F25: =IF($A25="","","In-Scope") -> In-Scope | G25: =IF($A25="","","In-Scope") -> In-Scope | H25: =IF($A25="","","In-Scope") -> In-Scope | I25: =IF($A25="","","Out-of-Scope") -> Out-of-Scope | J25: =IF($A25="","","Out-of-Scope") -> Out-of-Scope | K25: =IF($A25="","","In-Scope") -> In-Scope | L25: =IF($A25="","","Out-of-Scope") -> Out-of-Scope | M25: =IF($A25="","","In-Scope") -> In-Scope | N25: =IF($A25="","","In-Scope") -> In-Scope | O25: =IF($A25="","","In-Scope") -> In-Scope | P25: =IF($A25="","","In-Scope") -> In-Scope | Q25: =IF($A25="","","In-Scope") -> In-Scope | R25: =IF($A25="","","In-Scope") -> In-Scope | S25: =IF($A25="","","In-Scope") -> In-Scope | V25: =IF($A25="","","In-Scope") -> In-Scope | W25: =IF($A25="","","In-Scope") -> In-Scope | X25: =IF($A25="","","In-Scope") -> In-Scope | Y25: =IF($A25="","","In-Scope") -> In-Scope | Z25: =IF($A25="","","In-Scope") -> In-Scope | AA25: =IF($A25="","","In-Scope") -> In-Scope | AB25: =IF($A25="","","In-Scope") -> In-Scope | AC25: =IF($A25="","","In-Scope") -> In-Scope | ... AO25: =IF($A25="","","In-Scope") -> In-Scope
A26: South Dakota Project | B26: =IF($A26="","","In-Scope") -> In-Scope | C26: =IF($A26="","","In-Scope") -> In-Scope | D26: =IF($A26="","","In-Scope") -> In-Scope | E26: =IF($A26="","","In-Scope") -> In-Scope | F26: =IF($A26="","","In-Scope") -> In-Scope | G26: =IF($A26="","","In-Scope") -> In-Scope | H26: =IF($A26="","","In-Scope") -> In-Scope | I26: =IF($A26="","","Out-of-Scope") -> Out-of-Scope | J26: =IF($A26="","","Out-of-Scope") -> Out-of-Scope | K26: =IF($A26="","","In-Scope") -> In-Scope | L26: =IF($A26="","","Out-of-Scope") -> Out-of-Scope | M26: =IF($A26="","","In-Scope") -> In-Scope | N26: =IF($A26="","","In-Scope") -> In-Scope | O26: =IF($A26="","","In-Scope") -> In-Scope | P26: =IF($A26="","","In-Scope") -> In-Scope | Q26: =IF($A26="","","In-Scope") -> In-Scope | R26: =IF($A26="","","In-Scope") -> In-Scope | S26: =IF($A26="","","In-Scope") -> In-Scope | V26: =IF($A26="","","In-Scope") -> In-Scope | W26: =IF($A26="","","In-Scope") -> In-Scope | X26: =IF($A26="","","In-Scope") -> In-Scope | Y26: =IF($A26="","","In-Scope") -> In-Scope | Z26: =IF($A26="","","In-Scope") -> In-Scope | AA26: =IF($A26="","","In-Scope") -> In-Scope | AB26: =IF($A26="","","In-Scope") -> In-Scope | AC26: =IF($A26="","","In-Scope") -> In-Scope | ... AO26: =IF($A26="","","In-Scope") -> In-Scope
A27: California Project | B27: =IF($A27="","","In-Scope") -> In-Scope | C27: =IF($A27="","","In-Scope") -> In-Scope | D27: =IF($A27="","","In-Scope") -> In-Scope | E27: =IF($A27="","","In-Scope") -> In-Scope | F27: =IF($A27="","","In-Scope") -> In-Scope | G27: =IF($A27="","","In-Scope") -> In-Scope | H27: =IF($A27="","","In-Scope") -> In-Scope | I27: =IF($A27="","","Out-of-Scope") -> Out-of-Scope | J27: =IF($A27="","","Out-of-Scope") -> Out-of-Scope | K27: =IF($A27="","","In-Scope") -> In-Scope | L27: =IF($A27="","","Out-of-Scope") -> Out-of-Scope | M27: =IF($A27="","","In-Scope") -> In-Scope | N27: =IF($A27="","","In-Scope") -> In-Scope | O27: =IF($A27="","","In-Scope") -> In-Scope | P27: =IF($A27="","","In-Scope") -> In-Scope | Q27: =IF($A27="","","In-Scope") -> In-Scope | R27: =IF($A27="","","In-Scope") -> In-Scope | S27: =IF($A27="","","In-Scope") -> In-Scope | V27: =IF($A27="","","In-Scope") -> In-Scope | W27: =IF($A27="","","In-Scope") -> In-Scope | X27: =IF($A27="","","In-Scope") -> In-Scope | Y27: =IF($A27="","","In-Scope") -> In-Scope | Z27: =IF($A27="","","In-Scope") -> In-Scope | AA27: =IF($A27="","","In-Scope") -> In-Scope | AB27: =IF($A27="","","In-Scope") -> In-Scope | AC27: =IF($A27="","","In-Scope") -> In-Scope | ... AO27: =IF($A27="","","In-Scope") -> In-Scope
A28: Oklahoma Project | B28: =IF($A28="","","In-Scope") -> In-Scope | C28: =IF($A28="","","In-Scope") -> In-Scope | D28: =IF($A28="","","In-Scope") -> In-Scope | E28: =IF($A28="","","In-Scope") -> In-Scope | F28: =IF($A28="","","In-Scope") -> In-Scope | G28: =IF($A28="","","In-Scope") -> In-Scope | H28: =IF($A28="","","In-Scope") -> In-Scope | I28: =IF($A28="","","Out-of-Scope") -> Out-of-Scope | J28: =IF($A28="","","Out-of-Scope") -> Out-of-Scope | K28: =IF($A28="","","In-Scope") -> In-Scope | L28: =IF($A28="","","Out-of-Scope") -> Out-of-Scope | M28: =IF($A28="","","In-Scope") -> In-Scope | N28: =IF($A28="","","In-Scope") -> In-Scope | O28: =IF($A28="","","In-Scope") -> In-Scope | P28: =IF($A28="","","In-Scope") -> In-Scope | Q28: =IF($A28="","","In-Scope") -> In-Scope | R28: =IF($A28="","","In-Scope") -> In-Scope | S28: =IF($A28="","","In-Scope") -> In-Scope | V28: =IF($A28="","","In-Scope") -> In-Scope | W28: =IF($A28="","","In-Scope") -> In-Scope | X28: =IF($A28="","","In-Scope") -> In-Scope | Y28: =IF($A28="","","In-Scope") -> In-Scope | Z28: =IF($A28="","","In-Scope") -> In-Scope | AA28: =IF($A28="","","In-Scope") -> In-Scope | AB28: =IF($A28="","","In-Scope") -> In-Scope | AC28: =IF($A28="","","In-Scope") -> In-Scope | ... AO28: =IF($A28="","","In-Scope") -> In-Scope
A29: Georgia Project | B29: =IF($A29="","","In-Scope") -> In-Scope | C29: =IF($A29="","","In-Scope") -> In-Scope | D29: =IF($A29="","","In-Scope") -> In-Scope | E29: =IF($A29="","","In-Scope") -> In-Scope | F29: =IF($A29="","","In-Scope") -> In-Scope | G29: =IF($A29="","","In-Scope") -> In-Scope | H29: =IF($A29="","","In-Scope") -> In-Scope | I29: =IF($A29="","","Out-of-Scope") -> Out-of-Scope | J29: =IF($A29="","","Out-of-Scope") -> Out-of-Scope | K29: =IF($A29="","","In-Scope") -> In-Scope | L29: =IF($A29="","","Out-of-Scope") -> Out-of-Scope | M29: =IF($A29="","","In-Scope") -> In-Scope | N29: =IF($A29="","","In-Scope") -> In-Scope | O29: =IF($A29="","","In-Scope") -> In-Scope | P29: =IF($A29="","","In-Scope") -> In-Scope | Q29: =IF($A29="","","In-Scope") -> In-Scope | R29: =IF($A29="","","In-Scope") -> In-Scope | S29: =IF($A29="","","In-Scope") -> In-Scope | V29: =IF($A29="","","In-Scope") -> In-Scope | W29: =IF($A29="","","In-Scope") -> In-Scope | X29: =IF($A29="","","In-Scope") -> In-Scope | Y29: =IF($A29="","","In-Scope") -> In-Scope | Z29: =IF($A29="","","In-Scope") -> In-Scope | AA29: =IF($A29="","","In-Scope") -> In-Scope | AB29: =IF($A29="","","In-Scope") -> In-Scope | AC29: =IF($A29="","","In-Scope") -> In-Scope | ... AO29: =IF($A29="","","In-Scope") -> In-Scope
A30: Connecticut Project | B30: =IF($A30="","","In-Scope") -> In-Scope | C30: =IF($A30="","","In-Scope") -> In-Scope | D30: =IF($A30="","","In-Scope") -> In-Scope | E30: =IF($A30="","","In-Scope") -> In-Scope | F30: =IF($A30="","","In-Scope") -> In-Scope | G30: =IF($A30="","","In-Scope") -> In-Scope | H30: =IF($A30="","","In-Scope") -> In-Scope | I30: =IF($A30="","","Out-of-Scope") -> Out-of-Scope | J30: =IF($A30="","","Out-of-Scope") -> Out-of-Scope | K30: =IF($A30="","","In-Scope") -> In-Scope | L30: =IF($A30="","","Out-of-Scope") -> Out-of-Scope | M30: =IF($A30="","","In-Scope") -> In-Scope | N30: =IF($A30="","","In-Scope") -> In-Scope | O30: =IF($A30="","","In-Scope") -> In-Scope | P30: =IF($A30="","","In-Scope") -> In-Scope | Q30: =IF($A30="","","In-Scope") -> In-Scope | R30: =IF($A30="","","In-Scope") -> In-Scope | S30: =IF($A30="","","In-Scope") -> In-Scope | V30: =IF($A30="","","In-Scope") -> In-Scope | W30: =IF($A30="","","In-Scope") -> In-Scope | X30: =IF($A30="","","In-Scope") -> In-Scope | Y30: =IF($A30="","","In-Scope") -> In-Scope | Z30: =IF($A30="","","In-Scope") -> In-Scope | AA30: =IF($A30="","","In-Scope") -> In-Scope | AB30: =IF($A30="","","In-Scope") -> In-Scope | AC30: =IF($A30="","","In-Scope") -> In-Scope | ... AO30: =IF($A30="","","In-Scope") -> In-Scope
A31: Ohio Project | B31: =IF($A31="","","In-Scope") -> In-Scope | C31: =IF($A31="","","In-Scope") -> In-Scope | D31: =IF($A31="","","In-Scope") -> In-Scope | E31: =IF($A31="","","In-Scope") -> In-Scope | F31: =IF($A31="","","In-Scope") -> In-Scope | G31: =IF($A31="","","In-Scope") -> In-Scope | H31: =IF($A31="","","In-Scope") -> In-Scope | I31: =IF($A31="","","Out-of-Scope") -> Out-of-Scope | J31: =IF($A31="","","Out-of-Scope") -> Out-of-Scope | K31: =IF($A31="","","In-Scope") -> In-Scope | L31: =IF($A31="","","Out-of-Scope") -> Out-of-Scope | M31: =IF($A31="","","In-Scope") -> In-Scope | N31: =IF($A31="","","In-Scope") -> In-Scope | O31: =IF($A31="","","In-Scope") -> In-Scope | P31: =IF($A31="","","In-Scope") -> In-Scope | Q31: =IF($A31="","","In-Scope") -> In-Scope | R31: =IF($A31="","","In-Scope") -> In-Scope | S31: =IF($A31="","","In-Scope") -> In-Scope | V31: =IF($A31="","","In-Scope") -> In-Scope | W31: =IF($A31="","","In-Scope") -> In-Scope | X31: =IF($A31="","","In-Scope") -> In-Scope | Y31: =IF($A31="","","In-Scope") -> In-Scope | Z31: =IF($A31="","","In-Scope") -> In-Scope | AA31: =IF($A31="","","In-Scope") -> In-Scope | AB31: =IF($A31="","","In-Scope") -> In-Scope | AC31: =IF($A31="","","In-Scope") -> In-Scope | ... AO31: =IF($A31="","","In-Scope") -> In-Scope
A32: New Jersey Project | B32: =IF($A32="","","In-Scope") -> In-Scope | C32: =IF($A32="","","In-Scope") -> In-Scope | D32: =IF($A32="","","In-Scope") -> In-Scope | E32: =IF($A32="","","In-Scope") -> In-Scope | F32: =IF($A32="","","In-Scope") -> In-Scope | G32: =IF($A32="","","In-Scope") -> In-Scope | H32: =IF($A32="","","In-Scope") -> In-Scope | I32: =IF($A32="","","Out-of-Scope") -> Out-of-Scope | J32: =IF($A32="","","Out-of-Scope") -> Out-of-Scope | K32: =IF($A32="","","In-Scope") -> In-Scope | L32: =IF($A32="","","Out-of-Scope") -> Out-of-Scope | M32: =IF($A32="","","In-Scope") -> In-Scope | N32: =IF($A32="","","In-Scope") -> In-Scope | O32: =IF($A32="","","In-Scope") -> In-Scope | P32: =IF($A32="","","In-Scope") -> In-Scope | Q32: =IF($A32="","","In-Scope") -> In-Scope | R32: =IF($A32="","","In-Scope") -> In-Scope | S32: =IF($A32="","","In-Scope") -> In-Scope | V32: =IF($A32="","","In-Scope") -> In-Scope | W32: =IF($A32="","","In-Scope") -> In-Scope | X32: =IF($A32="","","In-Scope") -> In-Scope | Y32: =IF($A32="","","In-Scope") -> In-Scope | Z32: =IF($A32="","","In-Scope") -> In-Scope | AA32: =IF($A32="","","In-Scope") -> In-Scope | AB32: =IF($A32="","","In-Scope") -> In-Scope | AC32: =IF($A32="","","In-Scope") -> In-Scope | ... AO32: =IF($A32="","","In-Scope") -> In-Scope
A33: Tennessee Project | B33: =IF($A33="","","In-Scope") -> In-Scope | C33: =IF($A33="","","In-Scope") -> In-Scope | D33: =IF($A33="","","In-Scope") -> In-Scope | E33: =IF($A33="","","In-Scope") -> In-Scope | F33: =IF($A33="","","In-Scope") -> In-Scope | G33: =IF($A33="","","In-Scope") -> In-Scope | H33: =IF($A33="","","In-Scope") -> In-Scope | I33: =IF($A33="","","Out-of-Scope") -> Out-of-Scope | J33: =IF($A33="","","Out-of-Scope") -> Out-of-Scope | K33: =IF($A33="","","In-Scope") -> In-Scope | L33: =IF($A33="","","Out-of-Scope") -> Out-of-Scope | M33: =IF($A33="","","In-Scope") -> In-Scope | N33: =IF($A33="","","In-Scope") -> In-Scope | O33: =IF($A33="","","In-Scope") -> In-Scope | P33: =IF($A33="","","In-Scope") -> In-Scope | Q33: =IF($A33="","","In-Scope") -> In-Scope | R33: =IF($A33="","","In-Scope") -> In-Scope | S33: =IF($A33="","","In-Scope") -> In-Scope | V33: =IF($A33="","","In-Scope") -> In-Scope | W33: =IF($A33="","","In-Scope") -> In-Scope | X33: =IF($A33="","","In-Scope") -> In-Scope | Y33: =IF($A33="","","In-Scope") -> In-Scope | Z33: =IF($A33="","","In-Scope") -> In-Scope | AA33: =IF($A33="","","In-Scope") -> In-Scope | AB33: =IF($A33="","","In-Scope") -> In-Scope | AC33: =IF($A33="","","In-Scope") -> In-Scope | ... AO33: =IF($A33="","","In-Scope") -> In-Scope
A34: Virginia Project | B34: =IF($A34="","","In-Scope") -> In-Scope | C34: =IF($A34="","","In-Scope") -> In-Scope | D34: =IF($A34="","","In-Scope") -> In-Scope | E34: =IF($A34="","","In-Scope") -> In-Scope | F34: =IF($A34="","","In-Scope") -> In-Scope | G34: =IF($A34="","","In-Scope") -> In-Scope | H34: =IF($A34="","","In-Scope") -> In-Scope | I34: =IF($A34="","","Out-of-Scope") -> Out-of-Scope | J34: =IF($A34="","","Out-of-Scope") -> Out-of-Scope | K34: =IF($A34="","","In-Scope") -> In-Scope | L34: =IF($A34="","","Out-of-Scope") -> Out-of-Scope | M34: =IF($A34="","","In-Scope") -> In-Scope | N34: =IF($A34="","","In-Scope") -> In-Scope | O34: =IF($A34="","","In-Scope") -> In-Scope | P34: =IF($A34="","","In-Scope") -> In-Scope | Q34: =IF($A34="","","In-Scope") -> In-Scope | R34: =IF($A34="","","In-Scope") -> In-Scope | S34: =IF($A34="","","In-Scope") -> In-Scope | V34: =IF($A34="","","In-Scope") -> In-Scope | W34: =IF($A34="","","In-Scope") -> In-Scope | X34: =IF($A34="","","In-Scope") -> In-Scope | Y34: =IF($A34="","","In-Scope") -> In-Scope | Z34: =IF($A34="","","In-Scope") -> In-Scope | AA34: =IF($A34="","","In-Scope") -> In-Scope | AB34: =IF($A34="","","In-Scope") -> In-Scope | AC34: =IF($A34="","","In-Scope") -> In-Scope | ... AO34: =IF($A34="","","In-Scope") -> In-Scope
A35: Michigan Project | B35: =IF($A35="","","In-Scope") -> In-Scope | C35: =IF($A35="","","In-Scope") -> In-Scope | D35: =IF($A35="","","In-Scope") -> In-Scope | E35: =IF($A35="","","In-Scope") -> In-Scope | F35: =IF($A35="","","In-Scope") -> In-Scope | G35: =IF($A35="","","In-Scope") -> In-Scope | H35: =IF($A35="","","In-Scope") -> In-Scope | I35: =IF($A35="","","Out-of-Scope") -> Out-of-Scope | J35: =IF($A35="","","Out-of-Scope") -> Out-of-Scope | K35: =IF($A35="","","In-Scope") -> In-Scope | L35: =IF($A35="","","Out-of-Scope") -> Out-of-Scope | M35: =IF($A35="","","In-Scope") -> In-Scope | N35: =IF($A35="","","In-Scope") -> In-Scope | O35: =IF($A35="","","In-Scope") -> In-Scope | P35: Not Yet | Q35: =IF($A35="","","In-Scope") -> In-Scope | R35: =IF($A35="","","In-Scope") -> In-Scope | S35: =IF($A35="","","In-Scope") -> In-Scope | T35: The project has not yet had the need or opportunity to use CAR. | V35: =IF($A35="","","In-Scope") -> In-Scope | W35: =IF($A35="","","In-Scope") -> In-Scope | X35: =IF($A35="","","In-Scope") -> In-Scope | Y35: =IF($A35="","","In-Scope") -> In-Scope | Z35: =IF($A35="","","In-Scope") -> In-Scope | AA35: =IF($A35="","","In-Scope") -> In-Scope | AB35: =IF($A35="","","In-Scope") -> In-Scope | AC35: =IF($A35="","","In-Scope") -> In-Scope | ... AO35: =IF($A35="","","In-Scope") -> In-Scope
A36: Utah Project | B36: =IF($A36="","","In-Scope") -> In-Scope | C36: =IF($A36="","","In-Scope") -> In-Scope | D36: =IF($A36="","","In-Scope") -> In-Scope | E36: =IF($A36="","","In-Scope") -> In-Scope | F36: =IF($A36="","","In-Scope") -> In-Scope | G36: =IF($A36="","","In-Scope") -> In-Scope | H36: =IF($A36="","","In-Scope") -> In-Scope | I36: =IF($A36="","","Out-of-Scope") -> Out-of-Scope | J36: =IF($A36="","","Out-of-Scope") -> Out-of-Scope | K36: =IF($A36="","","In-Scope") -> In-Scope | L36: =IF($A36="","","Out-of-Scope") -> Out-of-Scope | M36: =IF($A36="","","In-Scope") -> In-Scope | N36: =IF($A36="","","In-Scope") -> In-Scope | O36: =IF($A36="","","In-Scope") -> In-Scope | P36: =IF($A36="","","In-Scope") -> In-Scope | Q36: =IF($A36="","","In-Scope") -> In-Scope | R36: =IF($A36="","","In-Scope") -> In-Scope | S36: =IF($A36="","","In-Scope") -> In-Scope | V36: =IF($A36="","","In-Scope") -> In-Scope | W36: =IF($A36="","","In-Scope") -> In-Scope | X36: =IF($A36="","","In-Scope") -> In-Scope | Y36: =IF($A36="","","In-Scope") -> In-Scope | Z36: =IF($A36="","","In-Scope") -> In-Scope | AA36: =IF($A36="","","In-Scope") -> In-Scope | AB36: =IF($A36="","","In-Scope") -> In-Scope | AC36: =IF($A36="","","In-Scope") -> In-Scope | ... AO36: =IF($A36="","","In-Scope") -> In-Scope
A37: Wisconsin Project | B37: =IF($A37="","","In-Scope") -> In-Scope | C37: =IF($A37="","","In-Scope") -> In-Scope | D37: =IF($A37="","","In-Scope") -> In-Scope | E37: =IF($A37="","","In-Scope") -> In-Scope | F37: =IF($A37="","","In-Scope") -> In-Scope | G37: =IF($A37="","","In-Scope") -> In-Scope | H37: =IF($A37="","","In-Scope") -> In-Scope | I37: =IF($A37="","","Out-of-Scope") -> Out-of-Scope | J37: =IF($A37="","","Out-of-Scope") -> Out-of-Scope | K37: =IF($A37="","","In-Scope") -> In-Scope | L37: =IF($A37="","","Out-of-Scope") -> Out-of-Scope | M37: =IF($A37="","","In-Scope") -> In-Scope | N37: =IF($A37="","","In-Scope") -> In-Scope | O37: =IF($A37="","","In-Scope") -> In-Scope | P37: =IF($A37="","","In-Scope") -> In-Scope | Q37: =IF($A37="","","In-Scope") -> In-Scope | R37: =IF($A37="","","In-Scope") -> In-Scope | S37: =IF($A37="","","In-Scope") -> In-Scope | V37: =IF($A37="","","In-Scope") -> In-Scope | W37: =IF($A37="","","In-Scope") -> In-Scope | X37: =IF($A37="","","In-Scope") -> In-Scope | Y37: =IF($A37="","","In-Scope") -> In-Scope | Z37: =IF($A37="","","In-Scope") -> In-Scope | AA37: =IF($A37="","","In-Scope") -> In-Scope | AB37: =IF($A37="","","In-Scope") -> In-Scope | AC37: =IF($A37="","","In-Scope") -> In-Scope | ... AO37: =IF($A37="","","In-Scope") -> In-Scope
A38: Texas Project | B38: =IF($A38="","","In-Scope") -> In-Scope | C38: =IF($A38="","","In-Scope") -> In-Scope | D38: =IF($A38="","","In-Scope") -> In-Scope | E38: =IF($A38="","","In-Scope") -> In-Scope | F38: =IF($A38="","","In-Scope") -> In-Scope | G38: =IF($A38="","","In-Scope") -> In-Scope | H38: =IF($A38="","","In-Scope") -> In-Scope | I38: =IF($A38="","","Out-of-Scope") -> Out-of-Scope | J38: =IF($A38="","","Out-of-Scope") -> Out-of-Scope | K38: =IF($A38="","","In-Scope") -> In-Scope | L38: =IF($A38="","","Out-of-Scope") -> Out-of-Scope | M38: =IF($A38="","","In-Scope") -> In-Scope | N38: =IF($A38="","","In-Scope") -> In-Scope | O38: =IF($A38="","","In-Scope") -> In-Scope | P38: =IF($A38="","","In-Scope") -> In-Scope | Q38: =IF($A38="","","In-Scope") -> In-Scope | R38: =IF($A38="","","In-Scope") -> In-Scope | S38: =IF($A38="","","In-Scope") -> In-Scope | V38: =IF($A38="","","In-Scope") -> In-Scope | W38: =IF($A38="","","In-Scope") -> In-Scope | X38: =IF($A38="","","In-Scope") -> In-Scope | Y38: =IF($A38="","","In-Scope") -> In-Scope | Z38: =IF($A38="","","In-Scope") -> In-Scope | AA38: =IF($A38="","","In-Scope") -> In-Scope | AB38: =IF($A38="","","In-Scope") -> In-Scope | AC38: =IF($A38="","","In-Scope") -> In-Scope | ... AO38: =IF($A38="","","In-Scope") -> In-Scope
A39: Maryland Project | B39: =IF($A39="","","In-Scope") -> In-Scope | C39: =IF($A39="","","In-Scope") -> In-Scope | D39: =IF($A39="","","In-Scope") -> In-Scope | E39: =IF($A39="","","In-Scope") -> In-Scope | F39: =IF($A39="","","In-Scope") -> In-Scope | G39: =IF($A39="","","In-Scope") -> In-Scope | H39: =IF($A39="","","In-Scope") -> In-Scope | I39: =IF($A39="","","Out-of-Scope") -> Out-of-Scope | J39: =IF($A39="","","Out-of-Scope") -> Out-of-Scope | K39: =IF($A39="","","In-Scope") -> In-Scope | L39: =IF($A39="","","Out-of-Scope") -> Out-of-Scope | M39: =IF($A39="","","In-Scope") -> In-Scope | N39: =IF($A39="","","In-Scope") -> In-Scope | O39: =IF($A39="","","In-Scope") -> In-Scope | P39: =IF($A39="","","In-Scope") -> In-Scope | Q39: =IF($A39="","","In-Scope") -> In-Scope | R39: =IF($A39="","","In-Scope") -> In-Scope | S39: =IF($A39="","","In-Scope") -> In-Scope | V39: =IF($A39="","","In-Scope") -> In-Scope | W39: =IF($A39="","","In-Scope") -> In-Scope | X39: =IF($A39="","","In-Scope") -> In-Scope | Y39: =IF($A39="","","In-Scope") -> In-Scope | Z39: =IF($A39="","","In-Scope") -> In-Scope | AA39: =IF($A39="","","In-Scope") -> In-Scope | AB39: =IF($A39="","","In-Scope") -> In-Scope | AC39: =IF($A39="","","In-Scope") -> In-Scope | ... AO39: =IF($A39="","","In-Scope") -> In-Scope
B40: =IF($A40="","","In-Scope") | C40: =IF($A40="","","In-Scope") | D40: =IF($A40="","","In-Scope") | E40: =IF($A40="","","In-Scope") | F40: =IF($A40="","","In-Scope") | G40: =IF($A40="","","In-Scope") | H40: =IF($A40="","","In-Scope") | I40: =IF($A40="","","In-Scope") | ... S40: =IF($A40="","","In-Scope") | V40: =IF($A40="","","In-Scope") | W40: =IF($A40="","","In-Scope") | X40: =IF($A40="","","In-Scope") | Y40: =IF($A40="","","In-Scope") | Z40: =IF($A40="","","In-Scope") | AA40: =IF($A40="","","In-Scope") | AB40: =IF($A40="","","In-Scope") | AC40: =IF($A40="","","In-Scope") | ... AO40: =IF($A40="","","In-Scope")
B41: =IF($A41="","","In-Scope") | C41: =IF($A41="","","In-Scope") | D41: =IF($A41="","","In-Scope") | E41: =IF($A41="","","In-Scope") | F41: =IF($A41="","","In-Scope") | G41: =IF($A41="","","In-Scope") | H41: =IF($A41="","","In-Scope") | I41: =IF($A41="","","In-Scope") | ... S41: =IF($A41="","","In-Scope") | V41: =IF($A41="","","In-Scope") | W41: =IF($A41="","","In-Scope") | X41: =IF($A41="","","In-Scope") | Y41: =IF($A41="","","In-Scope") | Z41: =IF($A41="","","In-Scope") | AA41: =IF($A41="","","In-Scope") | AB41: =IF($A41="","","In-Scope") | AC41: =IF($A41="","","In-Scope") | ... AO41: =IF($A41="","","In-Scope")
B42: =IF($A42="","","In-Scope") | C42: =IF($A42="","","In-Scope") | D42: =IF($A42="","","In-Scope") | E42: =IF($A42="","","In-Scope") | F42: =IF($A42="","","In-Scope") | G42: =IF($A42="","","In-Scope") | H42: =IF($A42="","","In-Scope") | I42: =IF($A42="","","In-Scope") | ... S42: =IF($A42="","","In-Scope") | V42: =IF($A42="","","In-Scope") | W42: =IF($A42="","","In-Scope") | X42: =IF($A42="","","In-Scope") | Y42: =IF($A42="","","In-Scope") | Z42: =IF($A42="","","In-Scope") | AA42: =IF($A42="","","In-Scope") | AB42: =IF($A42="","","In-Scope") | AC42: =IF($A42="","","In-Scope") | ... AO42: =IF($A42="","","In-Scope")
B43: =IF($A43="","","In-Scope") | C43: =IF($A43="","","In-Scope") | D43: =IF($A43="","","In-Scope") | E43: =IF($A43="","","In-Scope") | F43: =IF($A43="","","In-Scope") | G43: =IF($A43="","","In-Scope") | H43: =IF($A43="","","In-Scope") | I43: =IF($A43="","","In-Scope") | ... S43: =IF($A43="","","In-Scope") | V43: =IF($A43="","","In-Scope") | W43: =IF($A43="","","In-Scope") | X43: =IF($A43="","","In-Scope") | Y43: =IF($A43="","","In-Scope") | Z43: =IF($A43="","","In-Scope") | AA43: =IF($A43="","","In-Scope") | AB43: =IF($A43="","","In-Scope") | AC43: =IF($A43="","","In-Scope") | ... AO43: =IF($A43="","","In-Scope")
B44: =IF($A44="","","In-Scope") | C44: =IF($A44="","","In-Scope") | D44: =IF($A44="","","In-Scope") | E44: =IF($A44="","","In-Scope") | F44: =IF($A44="","","In-Scope") | G44: =IF($A44="","","In-Scope") | H44: =IF($A44="","","In-Scope") | I44: =IF($A44="","","In-Scope") | ... S44: =IF($A44="","","In-Scope") | V44: =IF($A44="","","In-Scope") | W44: =IF($A44="","","In-Scope") | X44: =IF($A44="","","In-Scope") | Y44: =IF($A44="","","In-Scope") | Z44: =IF($A44="","","In-Scope") | AA44: =IF($A44="","","In-Scope") | AB44: =IF($A44="","","In-Scope") | AC44: =IF($A44="","","In-Scope") | ... AO44: =IF($A44="","","In-Scope")
B45: =IF($A45="","","In-Scope") | C45: =IF($A45="","","In-Scope") | D45: =IF($A45="","","In-Scope") | E45: =IF($A45="","","In-Scope") | F45: =IF($A45="","","In-Scope") | G45: =IF($A45="","","In-Scope") | H45: =IF($A45="","","In-Scope") | I45: =IF($A45="","","In-Scope") | ... S45: =IF($A45="","","In-Scope") | V45: =IF($A45="","","In-Scope") | W45: =IF($A45="","","In-Scope") | X45: =IF($A45="","","In-Scope") | Y45: =IF($A45="","","In-Scope") | Z45: =IF($A45="","","In-Scope") | AA45: =IF($A45="","","In-Scope") | AB45: =IF($A45="","","In-Scope") | AC45: =IF($A45="","","In-Scope") | ... AO45: =IF($A45="","","In-Scope")
B46: =IF($A46="","","In-Scope") | C46: =IF($A46="","","In-Scope") | D46: =IF($A46="","","In-Scope") | E46: =IF($A46="","","In-Scope") | F46: =IF($A46="","","In-Scope") | G46: =IF($A46="","","In-Scope") | H46: =IF($A46="","","In-Scope") | I46: =IF($A46="","","In-Scope") | ... S46: =IF($A46="","","In-Scope") | V46: =IF($A46="","","In-Scope") | W46: =IF($A46="","","In-Scope") | X46: =IF($A46="","","In-Scope") | Y46: =IF($A46="","","In-Scope") | Z46: =IF($A46="","","In-Scope") | AA46: =IF($A46="","","In-Scope") | AB46: =IF($A46="","","In-Scope") | AC46: =IF($A46="","","In-Scope") | ... AO46: =IF($A46="","","In-Scope")
B47: =IF($A47="","","In-Scope") | C47: =IF($A47="","","In-Scope") | D47: =IF($A47="","","In-Scope") | E47: =IF($A47="","","In-Scope") | F47: =IF($A47="","","In-Scope") | G47: =IF($A47="","","In-Scope") | H47: =IF($A47="","","In-Scope") | I47: =IF($A47="","","In-Scope") | ... S47: =IF($A47="","","In-Scope") | V47: =IF($A47="","","In-Scope") | W47: =IF($A47="","","In-Scope") | X47: =IF($A47="","","In-Scope") | Y47: =IF($A47="","","In-Scope") | Z47: =IF($A47="","","In-Scope") | AA47: =IF($A47="","","In-Scope") | AB47: =IF($A47="","","In-Scope") | AC47: =IF($A47="","","In-Scope") | ... AO47: =IF($A47="","","In-Scope")
B48: =IF($A48="","","In-Scope") | C48: =IF($A48="","","In-Scope") | D48: =IF($A48="","","In-Scope") | E48: =IF($A48="","","In-Scope") | F48: =IF($A48="","","In-Scope") | G48: =IF($A48="","","In-Scope") | H48: =IF($A48="","","In-Scope") | I48: =IF($A48="","","In-Scope") | ... S48: =IF($A48="","","In-Scope") | V48: =IF($A48="","","In-Scope") | W48: =IF($A48="","","In-Scope") | X48: =IF($A48="","","In-Scope") | Y48: =IF($A48="","","In-Scope") | Z48: =IF($A48="","","In-Scope") | AA48: =IF($A48="","","In-Scope") | AB48: =IF($A48="","","In-Scope") | AC48: =IF($A48="","","In-Scope") | ... AO48: =IF($A48="","","In-Scope")
B49: =IF($A49="","","In-Scope") | C49: =IF($A49="","","In-Scope") | D49: =IF($A49="","","In-Scope") | E49: =IF($A49="","","In-Scope") | F49: =IF($A49="","","In-Scope") | G49: =IF($A49="","","In-Scope") | H49: =IF($A49="","","In-Scope") | I49: =IF($A49="","","In-Scope") | ... S49: =IF($A49="","","In-Scope") | V49: =IF($A49="","","In-Scope") | W49: =IF($A49="","","In-Scope") | X49: =IF($A49="","","In-Scope") | Y49: =IF($A49="","","In-Scope") | Z49: =IF($A49="","","In-Scope") | AA49: =IF($A49="","","In-Scope") | AB49: =IF($A49="","","In-Scope") | AC49: =IF($A49="","","In-Scope") | ... AO49: =IF($A49="","","In-Scope")
B50: =IF($A50="","","In-Scope") | C50: =IF($A50="","","In-Scope") | D50: =IF($A50="","","In-Scope") | E50: =IF($A50="","","In-Scope") | F50: =IF($A50="","","In-Scope") | G50: =IF($A50="","","In-Scope") | H50: =IF($A50="","","In-Scope") | I50: =IF($A50="","","In-Scope") | ... S50: =IF($A50="","","In-Scope") | V50: =IF($A50="","","In-Scope") | W50: =IF($A50="","","In-Scope") | X50: =IF($A50="","","In-Scope") | Y50: =IF($A50="","","In-Scope") | Z50: =IF($A50="","","In-Scope") | AA50: =IF($A50="","","In-Scope") | AB50: =IF($A50="","","In-Scope") | AC50: =IF($A50="","","In-Scope") | ... AO50: =IF($A50="","","In-Scope")
B51: =IF($A51="","","In-Scope") | C51: =IF($A51="","","In-Scope") | D51: =IF($A51="","","In-Scope") | E51: =IF($A51="","","In-Scope") | F51: =IF($A51="","","In-Scope") | G51: =IF($A51="","","In-Scope") | H51: =IF($A51="","","In-Scope") | I51: =IF($A51="","","In-Scope") | ... S51: =IF($A51="","","In-Scope") | V51: =IF($A51="","","In-Scope") | W51: =IF($A51="","","In-Scope") | X51: =IF($A51="","","In-Scope") | Y51: =IF($A51="","","In-Scope") | Z51: =IF($A51="","","In-Scope") | AA51: =IF($A51="","","In-Scope") | AB51: =IF($A51="","","In-Scope") | AC51: =IF($A51="","","In-Scope") | ... AO51: =IF($A51="","","In-Scope")
... B990: =IF($A990="","","In-Scope") | C990: =IF($A990="","","In-Scope") | D990: =IF($A990="","","In-Scope") | E990: =IF($A990="","","In-Scope") | F990: =IF($A990="","","In-Scope") | G990: =IF($A990="","","In-Scope") | H990: =IF($A990="","","In-Scope") | I990: =IF($A990="","","In-Scope") | ... S990: =IF($A990="","","In-Scope") | V990: =IF($A990="","","In-Scope") | W990: =IF($A990="","","In-Scope") | X990: =IF($A990="","","In-Scope") | Y990: =IF($A990="","","In-Scope") | Z990: =IF($A990="","","In-Scope") | AA990: =IF($A990="","","In-Scope") | AB990: =IF($A990="","","In-Scope") | AC990: =IF($A990="","","In-Scope") | ... AO990: =IF($A990="","","In-Scope")

Sheet X-Appraisal Team
A1: Used to Establish Team Members | J1: Used to Establish Team Experience and Responsibilities
B2: Team Member Name | C2: Appraisal Role | D2: Organizational Affiliation | E2: OU Relationship | F2: Reporting Relationship | G2: Other Reporting Relationships | H2: Relationship Description | I2: Phone Number | J2: Years of Development Domain Experience | K2: Justification for Fewer than 3 Years of Experience | L2: Type of Domain Experience | M2: Years of Management Experience | N2: Mini-Team Assignment | O2: Specific Responsibilities
A3: 1
A4: 2
A5: 3
A6: 4
A7: 5
A8: 6
A9: 7
A10: 8

Sheet T1-Training Schedule
A1: Database ID (blank for new records) | B1: Appraisal Team Member(required) | C1: Description (required) | D1: Group Training | E1: Time (hours) (required) | F1: Training Date
B2: =IF('X-Appraisal Team'!B3="","",'X-Appraisal Team'!B3)
B3: =IF('X-Appraisal Team'!B4="","",'X-Appraisal Team'!B4)
B4: =IF('X-Appraisal Team'!B5="","",'X-Appraisal Team'!B5)
B5: =IF('X-Appraisal Team'!B6="","",'X-Appraisal Team'!B6)
B6: =IF('X-Appraisal Team'!B7="","",'X-Appraisal Team'!B7)
B7: =IF('X-Appraisal Team'!B8="","",'X-Appraisal Team'!B8)
B8: =IF('X-Appraisal Team'!B9="","",'X-Appraisal Team'!B9)
B9: =IF('X-Appraisal Team'!B10="","",'X-Appraisal Team'!B10)
B10: =IF('X-Appraisal Team'!B11="","",'X-Appraisal Team'!B11)
B11: =IF('X-Appraisal Team'!B12="","",'X-Appraisal Team'!B12)
B12: =IF('X-Appraisal Team'!B13="","",'X-Appraisal Team'!B13)
B13: =IF('X-Appraisal Team'!B14="","",'X-Appraisal Team'!B14)
... B39: =IF('X-Appraisal Team'!B40="","",'X-Appraisal Team'!B40)

Sheet T9-Participants
E1: Put an X in the column for each OU the participant will represent
A2: Database ID (blank for new records) | B2: Participant's Full Name (required) | C2: Participant's Role (required) | D2: Function (required) | E2: <Organizational Unit>

Sheet T10-Resource Estimate
A1: Database ID (blank for new records) | B1: Participant Group (required) | C1: Participant Individuals (required) | D1: Task (required) | E1: Time (hours) (required)

Sheet CAS Boilerplate
B1: This spreadsheet houses the "boilerplate" text required for each Benchmark appraisal planned in CAS.
B2: This information covers 80% of the input required for the section, "Phase 1: Plan Appraisal Record" as this information
B3: is reasonably consistent from one Benchmark appraisal to the other. Having said that, it is STRONGLY ENCOURAGE
B4: to review and tailor as necessary, the boilerplate text maintained below and/or in a "Appraisal Plan Template" CAS record.
B5: Note that none of the boilerplate information is required prior to generating the RGS, but much of it is required thereafter.
A7: VSD | B7: Filter code for Column A | F7: VSD: Information related to Virtual Service Delivery
A8: ESL | F8: ESL: Information related to foreign-language appraisals
A9: VSD/ESL | F9: Both VSD and ESL (see immediately above)
B11: CAS Section
C12: Subsection
D13: Entry Field Section
E14: CAS Entry Field
F15: Entry Fields | G15: Notes
B17: Phase 1: Plan Appraisal Readiness
C18: Required Outputs
A19: ESL | D19: Final Findings
A20: ESL | E20: Description of output delivery | F20: The Final Finding PowerPoint presentation is evolved from the Preliminary Findings presentation and will be presented by the lead appraiser to the appraisal sponsor, all discussion group participants, all appraisal team members, and anyone else the appraisal sponsor decides to invite. This presentation is made on the final day of Phase 2. The PowerPoint file is then provided to the appraisal sponsor and to the CMMI Institute (via CAS) at the conclusion of the appraisal as a required appraisal deliverable to both. The Final Findings presentation is generated in both English and Chinese. The Chinese version is displayed to the audience, while the ATL is using his computer as a teleprompter to display the English version. Because there are multiple certified lead appraisers on the team, we typically have a Chinese lead appraiser present the front material and ML2/3 findings, while the ATL presents all ML4 and ML5 findings.
E21: Owner | F21: Appraisal sponsor.
E22: Controls or Restrictions on Use | F22: Permission of the appraisal sponsor.
D23: Click "Update Output"
A25: ESL | D25: Sampled Project and OSF-level Practice Characterization Worksheets
A26: ESL | E26: Description of output delivery | F26: The PA Worksheets used to capture, analyze, and characterize the CMMI practices (which is the same set of worksheets used to rate practice groups) will be aggregated into a single workbook prior to submission. The "observation level detail" and the specific documents reviewed throughout the appraisal will be purged prior to submission to the Institute via CAS. However, the final set of PA Worksheets used to generate this consolidated workbook will be provided to the appraisal sponsor, and a copy of these PA Worksheets will be archived by PACT for possible use in future appraisals conducted for this client organization. Note that for China-based appraisals, all weaknesses, improvement opportunities, and exemplary strengths in the ML2 and ML3 worksheets will be translated into English by the interpreter, herself a certified lead appraiser. The same items in the ML4 and ML5 worksheets will be translated into Chinese for consumption by the ATMs.
E27: Owner | F27: During the appraisal, the ATL owns this set of PA Worksheets. Throughout the appraisal, the appraisal team members are capturing observation-level detail from documents, discussion groups, questionnaires, and findings validation sessions (i.e., Preliminary Findings). At the end of the appraisal, the worksheets are cleansed of attribution and non-public CMMI model components, and provided to the Appraisal Sponsor with the recommendation that they should be made available to the EPG for ongoing improvement activities. As indicated above, a copy of the full set of PA Worksheets is maintained by PACT for possible use in future appraisals conducted for this client organization.
E28: Controls or Restrictions on Use | F28: Permission of the Appraisal Sponsor. The Appraisal Sponsor is strongly advised to grant the EPG permission to use the PA Worksheets as a basis for ongoing performance improvement activity. With the sponsor's permission, the PA Worksheets for the current appraisal will be added to the PA Workbooks for future appraisals to help the future appraisal team members understand what documentation was previously reviewed for each practice. Furthermore, the historical data will also help the future appraisal team understand historically weak areas so that they can evaluate the corrective actions taken to address the weaknesses and render judgment as to their effectiveness. Obviously, if the appraisal sponsor does not provide such permission for use, the historical data will not be made available to the next appraisal team.
D29: Click "Update Output"
A31: ESL | D31: Sampled Project and OSF-level Ratings Worksheets
A32: ESL | E32: Description of output delivery | F32: The PA Worksheets used to capture, analyze, and characterize the CMMI practices (which is the same set of worksheets used to rate practice groups) will be aggregated into a single workbook prior to submission. The "observation level detail" and the specific documents reviewed throughout the appraisal will be purged prior to submission to the Institute via CAS. However, the final set of PA Worksheets used to generate this consolidated workbook will be provided to the appraisal sponsor, and a copy of these PA Worksheets will be archived by PACT for possible use in future appraisals conducted for this client organization. Note that for China-based appraisals, all weaknesses, improvement opportunities, and exemplary strengths in the ML2 and ML3 worksheets will be translated into English by the interpreter, herself a certified lead appraiser. The same items in the ML4 and ML5 worksheets will be translated into Chinese for consumption by the ATMs.
E33: Owner | F33: During the appraisal, the ATL owns this set of PA Worksheets. Throughout the appraisal, the appraisal team members are capturing observation-level detail from documents, discussion groups, questionnaires, and findings validation sessions (i.e., Preliminary Findings). At the end of the appraisal, the worksheets are cleansed of attribution and non-public CMMI model components, and provided to the Appraisal Sponsor with the recommendation that they should be made available to the EPG for ongoing improvement activities. As indicated above, a copy of the full set of PA Worksheets is maintained by PACT for possible use in future appraisals conducted for this client organization.
E34: Controls or Restrictions on Use | F34: Permission of the Appraisal Sponsor. The Appraisal Sponsor is strongly advised to grant the EPG permission to use the PA Worksheets as a basis for ongoing performance improvement activity. With the sponsor's permission, the PA Worksheets for the current appraisal will be added to the PA Workbooks for future appraisals to help the future appraisal team members understand what documentation was previously reviewed for each practice. Furthermore, the historical data will also help the future appraisal team understand historically weak areas so that they can evaluate the corrective actions taken to address the weaknesses and render judgment as to their effectiveness. Obviously, if the appraisal sponsor does not provide such permission for use, the historical data will not be made available to the next appraisal team.
D35: Click "Update Output"
A37: ESL | D37: Schedule
A38: ESL | E38: Description of output delivery | F38: The Onsite Schedule documents when the various presentations will be given (Opening Briefing, Preliminary Findings, Executive Briefing, and Final Findings) as well as when each of the discussion groups will be conducted and their corresponding topics. The Excel file will be submitted to the CMMI Institute at the conclusion of the appraisal as a required appraisal deliverable. Note that the schedule does NOT cover the pre-onsite documentation review as each team member is empowered to perform this work as time permits. The only requirement is that all documentation review has been completed by Day #1 of the Onsite Period. Finally, for China-based appraisals, the appraisal will be conducted in local China time, with the ATL shifting his hours to accommodate. The ATL maintains an Onsite schedule displaying the times of the session in Eastern Standard Time to simply avoid confusion.
E39: Owner | F39: Appraisal sponsor.
E40: Controls or Restrictions on Use | F40: Unrestricted use
D41: Click "Update Output"
C43: Performance Report Output
D44: Performance Report | F44: Download Performance Report template | G44: Performance Report template
C46: Optional Appraisal Outputs
A47: ESL | D47: Optional Output | F47: Executive Summary
A48: ESL | E48: Other Optional Output
A49: ESL | E49: Description of output delivery | F49: The PowerPoint-based Executive Briefing will be presented to the appraisal sponsor immediately preceding the Final Findings presentation on the final day of Phase 2. This is simply a proper subset of the material that will be shared in the Final Findings presentation. It is a single-use slide deck that will not be provided to the organization unless explicitly requested. The Executive Briefing will be submitted via CAS to the CMMI Institute at the conclusion of the appraisal. The Final Finding PowerPoint presentation is evolved from the Preliminary Findings presentation and will be presented by the lead appraiser to the appraisal sponsor, all discussion group participants, all appraisal team members, and anyone else the appraisal sponsor decides to invite. This presentation is made on the final day of Phase 2. The PowerPoint file is then provided to the appraisal sponsor and to the CMMI Institute (via CAS) at the conclusion of the appraisal as a required appraisal deliverable to both. The Executive Briefing presentation is generated in both English and Chinese. The Chinese version is displayed to the appraisal sponsor, while the ATL is using his computer as a teleprompter to display the English version. Typically, the Executive Briefing covers the ML2 and ML3 findings at a summary level, and the ATL presents all ML4 and ML5 finding as they will be presented in the Final Findings. | G49: Provide a detailed description of how this output will be delivered to the sponsor. NOTE: When using an "Appraisal Plan Template" in CAS as the basis for establishing your next CAS record, Optional Outputs are NOT retained, so you'll have to cut and paste this from the CAS Kit into the new CAS record which was copied from the template.
E50: Owner | F50: ATL | G50: Specify the owner of each output.
E51: Controls or Restrictions on Use | F51: This is a single-use presentation and is not left behind for the organization unless explicitly requested. (In some cases, the appraisal sponsor wants to use this more concise presentation material to brief his/her higher-ups.)
D52: Click "Update Output"
B54: OE Collection Plan
C55: OE Collection Approach
E56: Collection Approach | F56: Managed Discovery | G56: Select the OE Collection Approach
E57: Description | F57: The organization will be gathering the documents needed by the appraisal team to evaluate the projects and support groups, although additional documents may be required during the Onsite Period to get sufficient coverage and understanding. | G57: Describe the reasoning for using this approach.
D58: Click "Update OE Collection Approach"
C60: OE Collection Techniques
D61: New OE Collection Technique
A62: VSD | E62: Collection Technique | F62: Demonstrations | G62: Select the technique used for collecting the OE.
E63: Other Technique | G63: Name the technique if "other" was selected from the dropdown.
A64: VSD | E64: OE Type | F64: Affirmation and Artifacts
A65: VSD | E65: Description | F65: On an as-needed basis, organizational and project personnel may demonstrate specific systems or tools used to perform or facilitate their work. Such demonstrations are conducted in an interactive manner, including extensive discussion with the appraisal team. As such, these demonstrations serve as a source of both artifact and affirmation OE. Ideally, such demonstrations are provided in-person. However, it may be the case that one or more ATMs may be participating virtually. In such cases, additional time should be allocated to allow for more explanation, questions, and "repeat performances" as necessary to ensure that the demonstration adequately conveys the information. As with all sessions attended by remote participants, the Waiting Room (or equivalent) should be enabled to prevent unscheduled participation by "uninvited guests." | G65: Describe how this technique will be used for collecting OE.
D66: Click "Add OE Collection Technique"
A68: VSD | E68: Collection Technique | F68: Interview | G68: Select the technique used for collecting the OE.
E69: Other Technique | G69: Name the technique if "other" was selected from the dropdown.
A70: VSD | E70: OE Type | F70: Affirmation
A71: VSD | E71: Description | F71: Discussion groups will be conducted with organizational and project personnel to elicit affirmations and to explore the behaviors and outcomes associated with their various process activities. If conducted virtually, each discussion group participant - both ATMs and invited guests - should have their computer cameras enabled. Ideally, there would also be a camera that shows the entire conference room. As with all sessions attended by remote participants, the Waiting Room (or equivalent) should be enabled to prevent unscheduled participation by "uninvited guests." | G71: Describe how this technique will be used for collecting OE.
D72: Click "Add OE Collection Technique"
D74: New OE Collection Technique
A75: VSD/ESL | E75: Collection Technique | F75: Presentation | G75: Select the technique used for collecting the OE.
E76: Other Technique | G76: Name the technique if "other" was selected from the dropdown.
A77: VSD/ESL | E77: OE Type | F77: Affirmation
A78: VSD/ESL | E78: Description | F78: The Preliminary Findings session is conducted in a very interactive manner. It is used to validate the findings developed by the appraisal team and to elicit additional appraisal information from the organizational and project personnel. The invitees, each of whom will have participated in one or more discussion groups, is shown one finding at a time followed by the questions, "Did we get it right?" "Will this motivate management to take the right kinds of actions?" If conducted virtually, each presentation participant - both ATMs and invited guests - should have their computer cameras enabled. Ideally, there would also be a camera that shows the entire conference room. As with all sessions attended by remote participants, the Waiting Room (or equivalent) should be enabled to prevent unscheduled participation by "uninvited guests." The Final Finding PowerPoint presentation is evolved from the Preliminary Findings presentation and will be presented by the lead appraiser to the appraisal sponsor, all discussion group participants, all appraisal team members, and anyone else the appraisal sponsor decides to invite. This presentation is made on the final day of Phase 2. The PowerPoint file is then provided to the appraisal sponsor and to the CMMI Institute (via CAS) at the conclusion of the appraisal as a required appraisal deliverable to both. The Preliminary Findings presentation is generated in both English and Chinese. The Chinese version is displayed to the audience, while the ATL is using his computer as a teleprompter to display the English version. Because there are multiple certified lead appraisers on the team, we typically have a Chinese lead appraiser present the front material and ML2/3 findings, while the ATL presents all ML4 and ML5 finding. | G78: Describe how this technique will be used for collecting OE.
D79: Click "Add OE Collection Technique"
D81: New OE Collection Technique
A82: ESL | E82: Collection Technique | F82: Written | G82: Select the technique used for collecting the OE.
E83: Other Technique | G83: Name the technique if "other" was selected from the dropdown.
A84: ESL | E84: OE Type | F84: Affirmation
A85: ESL | E85: Description | F85: Questionnaires will be used to collect written affirmations related to GOV and II. These questionnaires are administered 30 days in advance of the Onsite Period and are submitted back to the lead appraiser no later than 15 days prior to the start of the Onsite Period. The data from the questionnaires is aggregated and used to guide discussion groups during the Onsite Period. Because the questionnaires use MS Word, for China-base appraisals the MS Work translate facility is used to translate the responses into English. The translation is surprisingly high quality. If there are any questions or concerns, the interpreter, herself a certified lead appraiser, is asked to translate the troublesome Chinese into English. This is rarely required, however. | G85: Describe how this technique will be used for collecting OE.
D86: Click "Add OE Collection Technique"
D88: New OE Collection Technique
A89: ESL | E89: Collection Technique | F89: Written | G89: Select the technique used for collecting the OE.
E90: Other Technique | G90: Name the technique if "other" was selected from the dropdown.
A91: ESL | E91: OE Type | F91: Artifacts
A92: ESL | E92: Description | F92: The gathering of documentation related to the identified Project/PA and Support Function/PA assignments (RGA or supplemental) will be facilitated by the Site Coordinator. Typically, these documents are evaluated by the appraisal team members 1-2 weeks prior to the Onsite Period. Additional documentation may be collected throughout the Onsite Period by either the Site Coordinator or the appraisal team members themselves. The ATL will evaluate all high maturity artifacts. If the artifacts are in MS Word, then the MS Word translation function will be used to translate the documents from Chinese to English. If the artifacts are in Excel, PowerPoint, or another file format, then the interpreter, herself a certified lead appraiser, will selectively translate the artifact into English prior to providing it to the ATL. Having worked together on 25+ appraisals, Helen is well aware of what I deem necessary to evaluate the HM practices. | G92: Describe how this technique will be used for collecting OE.
D93: Click "Add OE Collection Technique"
C95: Responsibility for Collection
D96: New Responsible Entity
E97: Responsible Entity | F97: ATL
E98: Other Entity
E99: Description | F99: During the pre-Onsite Period documentation review as well as throughout the Onsite Period, the lead appraiser will work with the appraisal team members to identify any holes in coverage (i.e., insufficient OE) and will work with the Site Coordinator to determine if additional OE can be made available for consideration (or not).
D100: Click "Update Responsible Entity"
D102: New Responsible Entity
E103: Responsible Entity | F103: ATL
E104: Other Entity
E105: Description | F105: The appraisal team members, facilitated by the lead appraiser, will guide the discussion groups to elicit affirmation OE.
D106: Click "Update Responsible Entity"
D108: New Responsible Entity
E109: Responsible Entity | F109: OU
E110: Other Entity
E111: Description | F111: The actual pre-Onsite Period collection of organizational, project, and support function documentation, although facilitated by the Site Coordinator, is primarily the responsibility of organizational, project, and support function personnel.
D112: Click "Update Responsible Entity"
D114: New Responsible Entity
E115: Responsible Entity | F115: Other
E116: Other Entity | F116: Site Coordinator
E117: Description | F117: The Site Coordinator will facilitate the collection of additional OE, if needed and available, to fill holes in coverage identified by the appraisal team members.
D118: Click "Update Responsible Entity"
...
